Workbook
Name Recover: [1]Macro1!$A$45
Name TableName: "Dummy"

Sheet Aging Formulas
A2: Closing Month End Date | B2: =TODAY() -> 46251
A4: Aging Buckets
A5: Age | B5: Bucket
A6: 0 | B6: 0-30
A7: 1 | B7: 0-30
A8: 2 | B8: 0-30
A9: 3 | B9: 0-30
A10: 4 | B10: 0-30
A11: 5 | B11: 0-30
A12: 6 | B12: 0-30
A13: 7 | B13: 0-30
A14: 8 | B14: 0-30
A15: 9 | B15: 0-30
A16: 10 | B16: 0-30
A17: 11 | B17: 0-30
... A8575: 8569 | B8575: 365+

Sheet JAN-23
A3: Row Labels | B3: Sum of Entered Amount | F3: GL Balance per TB
A4: Federal Citizen Services | B4: 865908.8
A5: 12014 | B5: 865908.8 | F5: Difference | G5: =B35-G3 -> -1253619
A6: 1CDATA-21-C-0075 Reclassing streamline balance to correct PL - Should resolve in the next couple months. $374K CR in other BS Account | B6: 543000
A7: FCN EA Cost Deferral - CG emailed 11/15, possibly need vendor credit. Pricing correct see CMG email 11/17 | B7: 322908.8
A8: Federal Healthcare | B8: -1352553.6
A9: 11010 | B9: -1352553.6
A10: Awaiting fufillment - Closed Complete in August - Release? Check old cost recs AA sub for DCOGS Dec-21 thru present on public sector | B10: 52152.75
A11: Four Points Order on hold - Emailed Dawn 2/13/2023 - Check Cost Rec for reversal 2/17 | B11: 20953.35
A12: Orders on hold - follow up with team 10702660/10702659/10702554/10705836/10702668 | B12: 221281.44
A13: VA EA Deal | B13: -1646941.1
A14: Federal House | B14: 44929.56
A15: 11016 | B15: 44929.56
A16: PO 1CDATA-21-C-0075, to reverse US postal in February | B16: 44929.56
A17: Federal Intel | B17: 68161.14
A18: 12012 | B18: 68161.14
A19: Timing - RecVue Pending Credit - Follow up on credit | B19: 68161.14
A20: Federal Intel Moonshot | B20: -1100000
A21: 12022 | B21: -1100000
A22: Moonshot SAAS RecVue | B22: -1100000
A23: Federal Law Enforcement | B23: -41798.4
A24: 12013 | B24: -41798.4
A25: Monthly Timing - follow email 1/20 & 1/27 - followed up 2/13/2023 | B25: -41798.4
A26: Federal Navy | B26: 200826
A27: 11023 | B27: 200826
A28: Timing - Streamline FEDERAL RESOURCES PO 157803 | B28: 200826
A29: Federal Scientific | B29: 7355
A30: 12021 | B30: 7355
A31: Timing - Streamline CGI Federal PR20005283 | B31: 7355
A32: SLED Central | B32: 53552.52
A33: 13006 | B33: 53552.52
A34: Timing - Pending Credit - See email for pending Cisco Credit… Descrepancy on amount billed vs credited. Sitting in 24500 code to 50210 6k diff to SC | B34: 53552.52
A35: Grand Total | B35: -1253619

Sheet FEB-23
A3: Row Labels | B3: Sum of Entered Amount | F3: GL Balance per TB | G3: ='[2]Timing Variances'!$C$62 -> -1988221
A4: Federal Air Force | B4: 106212.6
A5: 11001 | B5: 106212.6 | F5: Difference | G5: =B35-G3 -> -2.7939677e-09
A6: (blank) | B6: 106212.6
A7: Federal Citizen Services | B7: -252091.2
A8: 12014 | B8: -252091.2
A9: FCN EA Cost Deferral - CG emailed 11/15, possibly need vendor credit. Pricing correct see CMG email 11/17 | B9: 322908.8
A10: (blank) | B10: -575000
A11: Federal COCOMs | B11: 335257.6
A12: 12015 | B12: 335257.6
A13: (blank) | B13: 335257.6
A14: Federal Healthcare | B14: -1214443.7
A15: 11010 | B15: -1214443.7
A16: Awaiting fufillment - Closed Complete in August - Release? Check old cost recs AA sub for DCOGS Dec-21 thru present on public sector | B16: 52152.75
A17: Orders on hold - follow up with team 10702660/10702659/10702554/10705836/10702668 | B17: 221281.44
A18: (blank) | B18: -1487877.9
A19: Federal House | B19: 575000
A20: 11016 | B20: 575000
A21: (blank) | B21: 575000
A22: Federal Intel | B22: 68161.14
A23: 12012 | B23: 68161.14
A24: Timing - RecVue Pending Credit - Follow up on credit | B24: 68161.14
A25: Federal Law Enforcement | B25: -41798.4
A26: 12013 | B26: -41798.4
A27: Monthly Timing - follow email 1/20 & 1/27 - followed up 2/13/2023 | B27: -41798.4
A28: Federal Navy | B28: 200826
A29: 11023 | B29: 200826
A30: Timing - Streamline FEDERAL RESOURCES PO 157803 | B30: 200826
A31: Federal Scientific | B31: -1765345
A32: 12021 | B32: -1765345
A33: Timing - Streamline CGI Federal PR20005283 | B33: 7355
A34: (blank) | B34: -1772700
A35: Grand Total | B35: -1988221

Sheet MAR-23
A3: Row Labels | B3: Sum of Entered Amount
A4: Federal Air Force | B4: 29762.6
A5: 11001 | B5: 29762.6
A6: (blank) | B6: 29762.6
A7: Federal Citizen Services | B7: -252091.2
A8: 12014 | B8: -252091.2
A9: FCN EA Cost Deferral - CG emailed 11/15, possibly need vendor credit. Pricing correct see CMG email 11/17 | B9: 322908.8
A10: Reclass between P&L | B10: -575000
A11: Federal COCOMs | B11: 335257.6
A12: 12015 | B12: 335257.6
A13: To defer cost on Customer PO 10000410, SO 10768674, Emailed Shelly on 2/23, 3/14 | B13: 369435.6
A14: To defer revenue & cost on Customer PO 10000410, SO 10230194 - Emailed Shelly on 2/22, 3/14 CUB 2173719 creating issue | B14: -34178
A15: Federal Healthcare | B15: -508197.14
A16: 11010 | B16: -508197.14
A17: 128k * 2 + 14k | B17: 270985
A18: Awaiting fufillment - Closed Complete in August - Release? Check old cost recs AA sub for DCOGS Dec-21 thru present on public sector | B18: 52152.75
A19: Defer Federal Health WWTINCSAAS924, PO 22P09282 | B19: 128000
A20: Reversed in April | B20: 456543
A21: Reversed in April - VA EA March AP Invoices | B21: -1415877.9
A22: Federal House | B22: 575000
A23: 11016 | B23: 575000
A24: Reclass between P&L | B24: 575000
A25: Federal Intel | B25: 80451.04
A26: 12012 | B26: 80451.04
A27: Timing - RecVue Pending Credit - Follow up on credit | B27: 68161.14
A28: (blank) | B28: 12289.9
A29: Federal Law Enforcement | B29: -32743.78
A30: 12013 | B30: -32743.78
A31: Monthly Timing - follow email 1/20 & 1/27 - followed up 2/13, 3/15, 4/14 | B31: -41798.4
A32: Needs to be reversed in April | B32: 9054.62
A33: Federal Navy | B33: 200826
A34: 11023 | B34: 200826
A35: Timing - Streamline FEDERAL RESOURCES PO 157803 - should reverse in May | B35: 200826
A36: Federal Navy NGEN | B36: 73709.27
A37: 11024 | B37: 73709.27
A38: Part of Inv Reserve in AR other account | B38: 73709.27
A39: Federal Scientific | B39: 7355
A40: 12021 | B40: 7355
A41: Timing - Streamline CGI Federal PR20005283 | B41: 7355
A42: Federal USACE | B42: -6022.36
A43: 12016 | B43: -6022.36
A44: Reclass to AR other account offsets | B44: -4784.22
A45: RMA on hold - Reclass to AR other account | B45: -1238.14
A46: SLED Central | B46: -178677.57
A47: 13006 | B47: -178677.57
A48: Expecting Cost in July | B48: -45396.3
A49: Reversed in April | B49: -96517.01
A50: Streamline P3882300203 SO 10539163 | B50: -36764.26
A51: SLED HI/Comm | B51: -22112.74
A52: 13001 | B52: -22112.74
A53: Reverse in April emailed M Hofer about AR inv hitting in March | B53: -22112.74
A54: Grand Total | B54: 302516.72

Sheet MAY-23
A3: Row Labels | B3: Sum of Entered Amount
A4: Federal Air Force | B4: 29762.6
A5: (blank) | B5: 29762.6
A6: Federal Army Enterprise | B6: -183844.21
A7: (blank) | B7: -130197.21
A8: Sent Email for missing Cost in May 6/14/23 | B8: -53647 | D8: WWT PO 4183946 was matched but didn't transact on OPR missing 50,610k of cost. Drop Shipped org 39????????
A9: Federal Citizen Services | B9: 322908.8
A10: FCN EA Cost Deferral - CG emailed 11/15, possibly need vendor credit. Pricing correct see CMG email 11/17, 6/15 | B10: 322908.8 | D10: Emailed 6/15 - Pricing issue to determine additional billing to customer
A11: Federal COCOMs | B11: 335257.6
A12: To defer cost on Customer PO 10000410, SO 10768674, Emailed Shelly on 2/23, 3/14, 4/19, 6/15 - Jake is working on matching Hours completed with customer and IUB will be booked | B12: 335257.6 | D12: Jake V is working with Customer on services completed and matching hours. IUB should be booked to help offset issues with CUB.
A13: Federal Healthcare | B13: 99921.1
A14: Awaiting fufillment - Closed Complete in August - Release? Check old cost recs AA sub for DCOGS Dec-21 thru present on public sector | B14: 52152.75
A15: Awaiting fufillment, follow up with Dawn - Reversed in June | B15: 18800 | D15: Reversed in June
A16: Defer Federal Health WWTINCSAAS924, PO 22P09282 | B16: 398985 | D16: VA EA
A17: Reversing portion of VA EA related cost | B17: -370016.65 | D17: VA EA
A18: Federal Intel | B18: 80451.04
A19: Emailed 4/5 for missing Rev | B19: 12289.9
A20: Timing - RecVue Pending Credit - Follow up on credit | B20: 68161.14 | D20: Emailed 6/15/23 Jessica Laux & Karen Melton to see if there is a Credit from Cisco on WWTINCSAAS752 Invoice # 81025413 - Reverse it at later point confirm with molly
A21: Federal Law Enforcement | B21: -32743.78
A22: Monthly Timing - follow email 1/20 & 1/27 - followed up 2/13, 3/15, 4/14 | B22: -41798.4 | D22: Issue with Cost on WWT PO 4080608 missing from Vendor
A23: Reversed in June - Needs to be reversed in May | B23: 9054.62 | D23: Reversed in June
A24: Federal Navy | B24: 200826
A25: Timing - Streamline FEDERAL RESOURCES PO 157803 - should reverse in May | B25: 200826 | D25: Streamline - BL for later period
A26: Federal Navy NGEN | B26: 1553790.8
A27: Reversed in June - Part of Inv Reserve in AR other account | B27: 1553790.8 | D27: Working on JE's to move to Federal House offset in 130509
A28: Federal Scientific | B28: 7355
A29: Timing - Streamline CGI Federal PR20005283 | B29: 7355 | D29: Streamline
A30: SLED Central | B30: -45396.3
A31: PO P3152301398 SO 10764155 Expecting Cost in July | B31: -45396.3
A32: SLED Southeast | B32: -37685.19
A33: Cost Accrual - expected in October | B33: -37685.19
A34: Grand Total | B34: 2330603.4

Sheet July-23
A3: Row Labels | B3: Sum of Entered Amount
A4: Federal Air Force | B4: 29762.6
A5: (blank) | B5: 29762.6
A6: Federal Army Enterprise | B6: -53647
A7: Sent Email for missing Cost in May 6/14/23 | B7: -53647
A8: Federal Citizen Services | B8: -10602091 | D8: WWT PO 4183946 was matched but didn't transact on OPR missing 50,610k of cost. Drop Shipped org 39????????
A9: (blank) | B9: -10925000
A10: FCN EA Cost Deferral - CG emailed 11/15, possibly need vendor credit. Pricing correct see CMG email 11/17, 6/15 | B10: 322908.8 | D10: Emailed 6/15 - Pricing issue to determine additional billing to customer
A11: Federal COCOMs | B11: 335257.6
A12: To defer cost on Customer PO 10000410, SO 10768674, Emailed Shelly on 2/23, 3/14, 4/19, 6/15 - Jake is working on matching Hours completed with customer and IUB will be booked | B12: 335257.6 | D12: Jake V is working with Customer on services completed and matching hours. IUB should be booked to help offset issues with CUB.
A13: Federal Healthcare | B13: 52152.75
A14: Awaiting fufillment - Closed Complete in August - Release? Check old cost recs AA sub for DCOGS Dec-21 thru present on public sector | B14: 52152.75
A15: Federal Intel | B15: 80451.04 | D15: Reversed in June
A16: Emailed 4/5 for missing Rev | B16: 12289.9 | D16: VA EA
A17: Timing - RecVue Pending Credit - Follow up on credit | B17: 68161.14 | D17: VA EA
A18: Federal Law Enforcement | B18: 86843.47
A19: Monthly Timing - follow email 1/20 & 1/27 - followed up 2/13, 3/15, 4/14 | B19: -41798.4
A20: (blank) | B20: 128641.87 | D20: Emailed 6/15/23 Jessica Laux & Karen Melton to see if there is a Credit from Cisco on WWTINCSAAS752 Invoice # 81025413 - Reverse it at later point confirm with molly
A21: Federal Navy | B21: -77500
A22: (blank) | B22: -77500 | D22: Issue with Cost on WWT PO 4080608 missing from Vendor
A23: Federal Scientific | B23: 7355 | D23: Reversed in June
A24: Timing - Streamline CGI Federal PR20005283 | B24: 7355
A25: Federal Intel Moonshot | B25: 558594.33 | D25: Streamline - BL for later period
A26: (blank) | B26: 558594.33
A27: Grand Total | B27: -9582821.4 | D27: Working on JE's to move to Federal House offset in 130509
D29: Streamline

Sheet Aug-23
A3: Row Labels | B3: Sum of Entered Amount
A4: Federal Air Force | B4: 4762.6
A5: Ops Issue | B5: 29762.6 | D5: SO 10650154
A6: Finder's Fee | B6: -25000 | D6: Check request once paid.
A7: Federal Army Enterprise | B7: -53647
A8: Sent Email for missing Cost in May 6/14/23 | B8: -53647 | D8: WWT PO 4183946 was matched but didn't transact on OPR missing 50,610k of cost. Drop Shipped org 39????????
A9: Federal Citizen Services | B9: 322908.8
A10: FCN EA Cost Deferral - CG emailed 11/15, possibly need vendor credit. Pricing correct see CMG email 11/17, 6/15 | B10: 322908.8 | D10: Emailed 6/15 - Pricing issue to determine additional billing to customer
A11: Federal Healthcare | B11: 2141402.8
A12: Awaiting fufillment - Closed Complete in August - Release? Check old cost recs AA sub for DCOGS Dec-21 thru present on public sector | B12: 52152.75 | D12: Jake V is working with Customer on services completed and matching hours. IUB should be booked to help offset issues with CUB.
A13: Annual billing through RecVue awaiting RMA/RTV | B13: 2089250 | D13: Double check RMA/RTV. On cost side
A14: Federal Intel | B14: 80451.04
A15: Emailed 4/5 for missing Rev | B15: 12289.9
A16: Timing - RecVue Pending Credit - Follow up on credit | B16: 68161.14
A17: Federal Law Enforcement | B17: -17423.4
A18: Monthly Timing - follow email 1/20 & 1/27 - followed up 2/13, 3/15, 4/14 | B18: -41798.4
A19: Ops Issue | B19: 24375 | D19: SO 10944744 IUB
A20: Federal Navy | B20: 971656.3
A21: Replacement orders needing RMA/RTV | B21: 971656.3 | D21: SO 10941581 / 5
A22: Federal Scientific | B22: 7355 | D22: Issue with Cost on WWT PO 4080608 missing from Vendor
A23: Timing - Streamline CGI Federal PR20005283 | B23: 7355 | D23: Reversed in June
A24: Federal Intel Moonshot | B24: -85230.24
A25: Moonshot | B25: -85230.24 | D25: Streamline - BL for later period
A26: Federal Army/SOF House | B26: -1065122.5
A27: Reverse in September | B27: -1065122.5 | D27: Working on JE's to move to Federal House offset in 130509
A28: Grand Total | B28: 2307113.3
D29: Streamline

Sheet Sept-23
A3: Row Labels | B3: Sum of Entered Amount
A4: Federal Air Force | B4: -25292.18
A5: Ops Issue | B5: 29762.6 | D5: SO 10650154 | E5: Reverse in October
A6: Finder's Fee | B6: -30054.78 | D6: SO 1105877
A7: Reversed in October Finder's Fee - Check Request submitted should be reversed in October | B7: -25000 | D7: Reversed in October
A8: Federal Army Enterprise | B8: -53647
A9: Sent Email for missing Cost in May 6/14/23 | B9: -53647 | D9: WWT PO 4183946 was matched but didn't transact on OPR missing 50,610k of cost. Drop Shipped org 39???????? Rework needed.
A10: Federal Citizen Services | B10: 491772.46
A11: FCN EA Cost Deferral - CG emailed 11/15, possibly need vendor credit. Pricing correct see CMG email 11/17, 6/15 | B11: 322908.8
A12: Awaiting RMA/RTV rework Email from Angie H 10/11/23 Needs to be Released. | B12: 168863.66
A13: Federal Healthcare | B13: 52152.75
A14: Awaiting fufillment - Closed Complete in August - Release? Check old cost recs AA sub for DCOGS Dec-21 thru present on public sector | B14: 52152.75 | D14: SO 9796205 | E14: Needs more research
A15: Federal Intel | B15: 80451.04
A16: Emailed 4/5 for missing Rev | B16: 12289.9 | D16: SO 10805628 | E16: Need More research and follow up
A17: Timing - RecVue Pending Credit - Follow up on credit | B17: 68161.14
A18: Federal Law Enforcement | B18: -17423.4
A19: Monthly Timing - follow email 1/20 & 1/27 - followed up 2/13, 3/15, 4/14 | B19: -41798.4 | D19: Working with Julie on resulition
A20: Ops Issue | B20: 24375 | D20: Follow up with Tyler for resolution - from august
A21: Federal Navy | B21: 971656.3
A22: Replacement orders needing RMA/RTV | B22: 971656.3 | D22: SO 10941581 & 10941585 - August
A23: Federal Scientific | B23: 7355
A24: Timing - Streamline CGI Federal PR20005283 | B24: 133855 | D24: Needs to be reversed from timing. Nothing in BL - Reverse out in August
A25: Timing - Streamline CGI Federal PR20005283 - | B25: -126500 | D25: Needs to be reversed from timing. Nothing in BL - Reverse out in August
A26: Federal Intel Moonshot | B26: -1239252.6
A27: Moonshot - Needs research Material Distribution Report | B27: -85230.24 | D27: Material Distribution Report
A28: Reversed in October | B28: -1154022.3 | D28: Reversed in October
A29: SLED Southeast | B29: -1557.97
A30: Need Ticket for stuck SAAS AP invoice hit OPR but not GL | B30: -1557.97
A31: SLED PANYNJ NESS | B31: -81871.89
A32: Finder's Fee | B32: -81871.89
A33: Grand Total | B33: 184342.53

Sheet Oct-23
A3: Row Labels | B3: Sum of Entered Amount
A4: Federal Air Force | B4: -30054.78
A5: Reversed in November Finder's Fee - Check Request Processed 11/8 | B5: -30054.78 | D5: Reversed in November
A6: Federal Army Enterprise | B6: -53647 | D6: SO 1105877
A7: Sent Email for missing Cost in May 6/14/23 | B7: -53647 | D7: Working with Julie for resolution SO 10920127 / WWT PO 4183946 was matched but didn't transact on OPR missing 50,610k of cost. Drop Shipped org 39???????? Rework needed.
A8: Federal Citizen Services | B8: 322908.8
A9: FCN EA Cost Deferral - CG emailed 11/15, possibly need vendor credit. Pricing correct see CMG email 11/17, 6/15, 11/13 | B9: 322908.8 | D9: WWT cost was accurate and need update in extra qty should be billed to customer pricing issue SO 10537043
A10: Federal Healthcare | B10: 52152.75
A11: Needs to be Reversed out in November - Awaiting fufillment - Closed Complete in August - Release? Check old cost recs AA sub for DCOGS Dec-21 thru present on public sector | B11: 52152.75 | D11: Needs to be reversed out of timing. Confirm with Christine/Laura if we can take this to G/A
A12: Federal Intel | B12: 80451.04
A13: Emailed 4/5 for missing Rev | B13: 12289.9
A14: Timing - RecVue Pending Credit - Follow up on credit | B14: 68161.14 | D14: RecVue credit to use on future order?
A15: Federal Law Enforcement | B15: -17423.4
A16: Monthly Timing - follow email 1/20 & 1/27 - followed up 2/13, 3/15, 4/14 | B16: -41798.4 | D16: Working with Julie Cost changed to $0 and need rework or correction
A17: Reversed in November | B17: 24375 | D17: Reversed in November - Pick up in Prior month.
A18: Federal Navy | B18: 971656.3
A19: Replacement orders needing RMA/RTV emailed 10/19 & 11/14 | B19: 971656.3 | D19: RMA/RTV being processed not yet complete
A20: Federal Intel Moonshot | B20: -85230.24
A21: Reversed in November Moonshot - Needs research Material Distribution Report | B21: -85230.24 | D21: Reversed in November
A22: SLED Southeast | B22: 2675298.7
A23: Need Ticket for stuck SAAS AP invoice hit OPR but not GL | B23: -1557.97 | D23: Ticket needed for missing GL amount
A24: Waiting on IUB's to process - Emailed 11/14 | B24: 2676856.7 | D24: Awaiting IUB's on Bulk PO's
A25: SLED PANYNJ NESS | B25: -81871.89
A26: Finder's Fee - Awaiting Payment | B26: -81871.89 | D26: Finder's Fee
A27: SLED HI/Comm | B27: 187267.68
A28: Reversed in November | B28: 187267.68 | D28: Reversed in November
A29: Federal AF/DISA/DA House | B29: -771663.59
A30: Termination Fee to be paid by EOY | B30: -771663.59 | D30: Termination Fee check request to submitted to clear by EOY
A31: SLED Northeast | B31: -385157.57
A32: Finder's Fee - Awaiting Payment | B32: -385157.57 | D32: Finder's Fee
A33: Grand Total | B33: 2864686.8

Sheet NOV-23
A3: Row Labels | B3: Sum of Entered Amount
A4: Federal AF/DISA/DA House | B4: -771663.59
A5: Termination Fee to be paid by EOY | B5: -771663.59 | D5: Megan following up
A6: Federal Army Enterprise | B6: -53647
A7: Sent Email for missing Cost in May 6/14/23 | B7: -53647 | D7: SO 10920127 Emailed 10/26 & 12/19
A8: Federal Citizen Services | B8: 106778.22
A9: Accrued Missing WWT Cost PO 1CDATA-22-C-0113_3 for proper recognition | B9: -216130.58
A10: FCN EA Cost Deferral - CG emailed 11/15, possibly need vendor credit. Pricing correct see CMG email 11/17, 6/15, 11/13 | B10: 322908.8 | D10: SO 10537043 Latest email sent 11/15 & 12/19 - See PO 63353P email from Dawn | K10: 63550P
A11: Federal DOD House | B11: -1107269
A12: To be released in December | B12: -1107269 | D12: Reverse in December
A13: Federal Healthcare | B13: -75847.25
A14: Needs to be Reversed out in November - Awaiting fufillment - Closed Complete in August - Release? Check old cost recs AA sub for DCOGS Dec-21 thru present on public sector | B14: 52152.75 | D14: JE to be made to G/A by Christine
A15: Will offset in Decemeber Check other timing account | B15: -128000 | D15: Reverse in December
A16: Federal Intel | B16: 80451.04
A17: Emailed 4/5 for missing Rev | B17: 12289.9
A18: Timing - RecVue Pending Credit - Follow up on credit | B18: 68161.14 | D18: Emailed 6/15/23 Jessica Laux & Karen Melton to see if there is a Credit from Cisco on WWTINCSAAS752 Invoice # 81025413 - Reverse it at later point confirm with molly
A19: Federal Intel Moonshot | B19: -85230.24
A20: Moonshot - Needs research Material Distribution Report | B20: -85230.24 | D20: PO Receipt adj tied to a canceled SO in Dinga Linda SC - WWT PO 4031126 SO 10269777
A21: Federal Law Enforcement | B21: -41798.4
A22: Monthly Timing - follow email 1/20 & 1/27 - followed up 2/13, 3/15, 4/14 | B22: -41798.4 | D22: SO 10479984 - PO lines were received in at $0 in error, so the cost is incorrect. Need Avg cost adj follow up with Dan Besmer
A23: Federal Navy | B23: 971656.3
A24: Replacement orders needing RMA/RTV emailed 10/19 & 11/14 | B24: 971656.3 | D24: half the gear being returned.
A25: SLED Northeast | B25: -385157.57
A26: Finder's Fee - Awaiting Payment | B26: -385157.57 | D26: Finder's Fee - partially paid 8 invoices
A27: SLED PANYNJ NESS | B27: -81871.89
A28: Finder's Fee - Awaiting Payment | B28: -81871.89 | D28: Finder's Fee - Still not paid
A29: SLED Southeast | B29: 2739888.3
A30: Need Ticket for stuck SAAS AP invoice hit OPR but not GL | B30: -1557.97
A31: Waiting on IUB's to process - Emailed 11/14 | B31: 2741446.3 | D31: Reverse 1M of WWT cost from IUB's released in December
A32: Grand Total | B32: 1296288.9

Sheet DEC-23
A3: Row Labels | B3: Sum of Entered Amount
A4: Federal AF/DISA/DA House | B4: -771663.59
A5: Termination Fee to be paid by EOY | B5: -771663.59
A6: Federal Air Force | B6: -46391
A7: Finder's Fee - Awaiting Payment | B7: -46391 | D7: Finder's Fee
A8: Federal Army Enterprise | B8: -53647
A9: Sent Email for missing Cost in May 6/14/23 | B9: -53647 | D9: Ops issue due to bring material back on hand @ $0
A10: Federal Citizen Services | B10: 106778.22
A11: Accrued Missing WWT Cost PO 1CDATA-22-C-0113_3 for proper recognition | B11: -216130.58
A12: FCN EA Cost Deferral - CG emailed 11/15, possibly need vendor credit. Pricing correct see CMG email 11/17, 6/15, 11/13 | B12: 322908.8 | D12: SO 10537043
A13: Federal COCOMs | B13: 235689.25
A14: Avg cost correction | B14: 235689.25 | D14: Avg cost correction SO 10811548 Part GSCUSTFCD PO 1268959 - Run material distrubition on Part #
A15: Federal Healthcare | B15: -598997
A16: EA Aqueon | B16: -456012 | D16: To be corrected in January.
A17: Reverse in January | B17: -14985 | D17: Reversed in January
A18: Will offset in Decemeber Check other timing account | B18: -128000 | D18: Dig into 128k and OPR for correction.
A19: Federal Intel | B19: 137062.42
A20: Emailed 4/5 for missing Rev | B20: 12289.9 | D20: SO 10805628
A21: Ops issue needs rework | B21: 56611.38 | D21: SO 11258948 - Needs research and followup
A22: Timing - RecVue Pending Credit - Follow up on credit | B22: 68161.14
A23: Federal Intel Moonshot | B23: -85230.24
A24: Moonshot - Needs research Material Distribution Report | B24: -85230.24 | D24: WWTPO 4031126 SO 10269777 hitting Dinga Linda SC / Move to Main SC in January
A25: Federal Law Enforcement | B25: -41798.4
A26: Monthly Timing - follow email 1/20 & 1/27 - followed up 2/13, 3/15, 4/14 | B26: -41798.4 | D26: SO 10479984
A27: SLED Northeast | B27: -385157.57
A28: Finder's Fee - Awaiting Payment | B28: -385157.57 | D28: Finder's Fee - Check Request or possible invoice.
A29: SLED PANYNJ NESS | B29: -81871.89
A30: Finder's Fee - Awaiting Payment | B30: -81871.89 | D30: To be reversed in January.
A31: SLED Southeast | B31: 1335237.3
A32: Need Ticket for stuck SAAS AP invoice hit OPR but not GL | B32: -1557.97
A33: Waiting on IUB's to process - Emailed 11/14 | B33: 1336795.3 | D33: Waiting rest of IUB's to process next week in January
A34: Grand Total | B34: -249989.47

Sheet Jan-24
A4: Row Labels | B4: Sum of Entered Amount
A5: Federal AF/DISA/DA House | B5: -771663.59
A6: Termination Fee to be paid by EOY | B6: -771663.59
A7: Federal Air Force | B7: -259345.94
A8: Missing Cost on PO FA568522F0091 | B8: -259345.94
A9: Federal Army Enterprise | B9: -53647
A10: Sent Email for missing Cost in May 6/14/23 | B10: -53647
A11: Federal Citizen Services | B11: 106778.22
A12: Accrued Missing WWT Cost PO 1CDATA-22-C-0113_3 for proper recognition | B12: -216130.58
A13: FCN EA Cost Deferral - CG emailed 11/15, possibly need vendor credit. Pricing correct see CMG email 11/17, 6/15, 11/13 | B13: 322908.8
A14: Federal COCOMs | B14: 235689.25
A15: Avg cost correction - SO 10811548 Part GSCUSTFCD | B15: 235689.25
A16: Federal Healthcare | B16: -142985
... A34: Grand Total | B34: 2909974.3

Sheet FEB-24
A4: Row Labels | B4: Sum of Entered Amount
A5: Federal AF/DISA/DA House | B5: -771663.59
A6: Termination Fee to be paid by EOY | B6: -771663.59
A7: Federal Air Force | B7: -259345.94
A8: Missing Cost on PO FA568522F0091 | B8: -259345.94
A9: Federal Army Enterprise | B9: -53647
A10: Sent Email for missing Cost in May 6/14/23 | B10: -53647
A11: Federal Citizen Services | B11: 106778.22
A12: Accrued Missing WWT Cost PO 1CDATA-22-C-0113_3 for proper recognition | B12: -216130.58
A13: FCN EA Cost Deferral - CG emailed 11/15, possibly need vendor credit. Pricing correct see CMG email 11/17, 6/15, 11/13 | B13: 322908.8
A14: Federal COCOMs | B14: 235689.25
A15: Avg cost correction - SO 10811548 Part GSCUSTFCD | B15: 235689.25
A16: Federal Healthcare | B16: -128000
... A43: Grand Total | B43: 1591395.9

Sheet MAR-24
A1: World Wide Technology
A2: Accrued Liabilities - Public Sector
A3: ON-PREM G/L # 01.XXXX.24521.000
A4: CLOUD GL# 101.XXXXX.245011.XXXX.XXX.XXX.XXXX.XXXX
A5: 45382
A7: Row Labels | B7: Sum of Functional Amount | C7: Sum of Global Amount
A8: Federal Air Force | B8: -259345.94 | C8: -259345.94
A9: Issue: AP Correction Needed | B9: -259345.94 | C9: -259345.94
A10: Federal Army Enterprise | B10: -53647 | C10: -53647
A11: Issue: AP Correction Needed | B11: -53647 | C11: -53647
A12: Federal Citizen Services | B12: 106778.22 | C12: 106778.22
A13: Accrual: Dropship | B13: -216130.58 | C13: -216130.58
A14: Issue: Ops correction Needed - Pricing | B14: 322908.8 | C14: 322908.8
A15: Federal COCOMs | B15: 385175.84 | C15: 385175.84
A16: Timing: Average Cost Streamline | B16: 149486.59 | C16: 149486.59
A17: Timing: Drop Ship Average Cost - Month End | B17: 235689.25 | C17: 235689.25
A18: Federal Healthcare | B18: -128000 | C18: -128000
A19: Issue: AP Correction Needed | B19: -128000 | C19: -128000
... A43: Grand Total | B43: 1899197.2 | C43: 1899197.2

Sheet JUL-24
A1: World Wide Technology
A2: Accrued Liabilities - Public Sector
A3: ON-PREM G/L # 01.XXXX.24521.000
A4: CLOUD GL# 101.XXXXX.245011.XXXX.XXX.XXX.XXXX.XXXX
A5: 45504
A7: Row Labels | B7: Sum of Functional Amount | C7: Sum of Global Amount
A8: Federal Citizen Services | B8: 322908.8 | C8: 322908.8
A9: Issue: Ops correction Needed - Pricing | B9: 322908.8 | C9: 322908.8
A10: Federal Healthcare | B10: 617055.74 | C10: 617055.74
A11: Issue: AP Correction Needed | B11: -128000 | C11: -128000
A12: Timing: Order on Hold | B12: 745055.74 | C12: 745055.74
A13: Federal Law Enforcement | B13: 925397.64 | C13: 925397.64
A14: Issue: AP Correction Needed | B14: 966837.04 | C14: 966837.04
A15: Timing: Order on Hold | B15: -41439.4 | C15: -41439.4
A16: SLED Southeast | B16: 137760 | C16: 137760
A17: Issue: AP Correction Needed | B17: 137760 | C17: 137760
A18: SLED Central | B18: 635780.08 | C18: 635780.08
A19: Issue: Needs Research | B19: 635780.08 | C19: 635780.08
... A26: Grand Total | B26: 3209618.8 | C26: 3209618.8

Sheet AUG-24
A1: World Wide Technology
A2: Accrued Liabilities - Public Sector
A3: ON-PREM G/L # 01.XXXX.24521.000
A4: CLOUD GL# 101.XXXXX.245011.XXXX.XXX.XXX.XXXX.XXXX
A5: 45535
A7: Row Labels | B7: Sum of Functional Amount | C7: Sum of Global Amount
A8: Federal Army Enterprise | B8: 452022.2 | C8: 452022.2
A9: Issue: AP Correction Needed | B9: 452022.2 | C9: 452022.2
A10: Federal Citizen Services | B10: 322908.8 | C10: 322908.8
A11: Issue: Ops correction Needed - Pricing | B11: 322908.8 | C11: 322908.8
A12: Federal COCOMs | B12: -2702135.8 | C12: -2702135.8
A13: Issue: AP Correction Needed | B13: -2702135.8 | C13: -2702135.8
A14: Federal Healthcare | B14: 8822647.4 | C14: 8822647.4
A15: Issue: AP Correction Needed | B15: -128000 | C15: -128000
A16: Timing: Order on Hold | B16: 745055.74 | C16: 745055.74
A17: Issue: Needs Research | B17: 771150 | C17: 771150
A18: Timing: Prelim Deferral | B18: 7434441.7 | C18: 7434441.7
A19: Federal Law Enforcement | B19: 925397.64 | C19: 925397.64
... A41: Grand Total | B41: -562970.29 | C41: -562970.29

Sheet SEP-24
A1: World Wide Technology
A2: Accrued Liabilities - Public Sector
A3: ON-PREM G/L # 01.XXXX.24521.000
A4: CLOUD GL# 101.XXXXX.245011.XXXX.XXX.XXX.XXXX.XXXX
A5: 45565
A7: Row Labels | B7: Sum of Functional Amount | C7: Sum of Global Amount
A8: Federal Army Enterprise | B8: 222306 | C8: 222306
A9: Issue: AP Correction Needed | B9: 222306 | C9: 222306
A10: Federal Healthcare | B10: -203000 | C10: -203000
A11: Accrual: Dropship | B11: -75000 | C11: -75000
A12: Issue: AP Correction Needed | B12: -128000 | C12: -128000
A13: Federal Law Enforcement | B13: 925397.64 | C13: 925397.64
A14: Issue: AP Correction Needed | B14: 966837.04 | C14: 966837.04
A15: Timing: Order on Hold | B15: -41439.4 | C15: -41439.4
A16: SLED Southeast | B16: 99705.5 | C16: 99705.5
A17: Issue: AP Correction Needed | B17: 137760 | C17: 137760
A18: Issue: Needs Research | B18: -38054.5 | C18: -38054.5
A19: SLED Central | B19: 67500 | C19: 67500
... A37: Grand Total | B37: -6955854.4 | C37: -6955854.4

Sheet OCT-24
A1: World Wide Technology
A2: Accrued Liabilities - Public Sector
A3: ON-PREM G/L # 01.XXXX.24521.000
A4: CLOUD GL# 101.XXXXX.245011.XXXX.XXX.XXX.XXXX.XXXX
A5: 45596
A7: Row Labels | B7: Sum of Functional Amount | C7: Sum of Global Amount
A8: Federal Army Enterprise | B8: 44461.2 | C8: 44461.2
A9: Issue: AP Correction Needed | B9: 44461.2 | C9: 44461.2
A10: Federal Healthcare | B10: -71467382 | C10: -71467382
A11: Accrual: Dropship | B11: -75000 | C11: -75000
A12: Issue: AP Correction Needed | B12: -128000 | C12: -128000
A13: Issue: Needs Research | B13: -71264382 | C13: -71264382
A14: Federal Law Enforcement | B14: 925397.64 | C14: 925397.64
A15: Issue: AP Correction Needed | B15: 966837.04 | C15: 966837.04
A16: Timing: Order on Hold | B16: -41439.4 | C16: -41439.4
A17: SLED Southeast | B17: -440435.86 | C17: -440435.86
A18: Issue: AP Correction Needed | B18: 137760 | C18: 137760
A19: Issue: Needs Research | B19: -38054.5 | C19: -38054.5
... A41: Grand Total | B41: -71151671 | C41: -71151671

Sheet DEC-24
A1: World Wide Technology
A2: Accrued Liabilities - Public Sector
A3: ON-PREM G/L # 01.XXXX.24521.000
A4: CLOUD GL# 101.XXXXX.245011.XXXX.XXX.XXX.XXXX.XXXX
A5: 45657
A7: Row Labels | B7: Sum of Functional Amount | C7: Sum of Global Amount
A8: Federal Army Enterprise | B8: 44461.2 | C8: 44461.2
A9: Issue: AP Correction Needed | B9: 44461.2 | C9: 44461.2
A10: Federal Healthcare | B10: 92075.4 | C10: 92075.4
A11: Accrual: Dropship | B11: -75000 | C11: -75000
A12: Timing: Order on Hold | B12: 167075.4 | C12: 167075.4
A13: SLED Southeast | B13: -578195.86 | C13: -578195.86
A14: Issue: AP Correction Needed | B14: -38054.5 | C14: -38054.5
A15: Timing: Streamline | B15: -540141.36 | C15: -540141.36
A16: Federal DoN Tactical | B16: -227442.19 | C16: -227442.19
A17: Issue: AP Correction Needed | B17: 64668 | C17: 64668
A18: Issue: Needs Research | B18: -292110.19 | C18: -292110.19
A19: SLED HI/Comm | B19: 67751.16 | C19: 67751.16
... A36: Grand Total | B36: 1125063 | C36: 1125063

Sheet JAN-25
A1: World Wide Technology
A2: Accrued Liabilities - Public Sector
A3: ON-PREM G/L # 01.XXXX.24521.000
A4: CLOUD GL# 101.XXXXX.245011.XXXX.XXX.XXX.XXXX.XXXX
A5: 45688
A7: Row Labels | B7: Sum of Functional Amount | C7: Sum of Global Amount
A8: Federal Army Enterprise | B8: 44461.2 | C8: 44461.2
A9: Issue: AP Correction Needed | B9: 44461.2 | C9: 44461.2
A10: Federal Healthcare | B10: 92075.4 | C10: 92075.4
A11: Accrual: Dropship | B11: -75000 | C11: -75000
A12: Timing: Order on Hold | B12: 167075.4 | C12: 167075.4
A13: SLED Southeast | B13: -540141.36 | C13: -540141.36
A14: Timing: Streamline | B14: -540141.36 | C14: -540141.36
A15: Federal DoN Tactical | B15: -227442.19 | C15: -227442.19
A16: Issue: AP Correction Needed | B16: 64668 | C16: 64668
A17: Issue: Needs Research | B17: -292110.19 | C17: -292110.19
A18: Federal Intel | B18: -735360 | C18: -735360
A19: Timing: Streamline | B19: -735360 | C19: -735360
... A28: Grand Total | B28: -1040202.4 | C28: -1040202.4

Sheet FEB-25
A1: World Wide Technology
A2: Accrued Liabilities - Public Sector
A3: ON-PREM G/L # 01.XXXX.24521.000
A4: CLOUD GL# 101.XXXXX.245011.XXXX.XXX.XXX.XXXX.XXXX
A5: 45716
A7: Row Labels | B7: Sum of Functional Amount | C7: Sum of Global Amount
A8: Federal Army Enterprise | B8: 29640.8 | C8: 29640.8
A9: Issue: AP Correction Needed | B9: 29640.8 | C9: 29640.8
A10: Federal Healthcare | B10: 92075.4 | C10: 92075.4
A11: Accrual: Dropship | B11: -75000 | C11: -75000
A12: Timing: Order on Hold | B12: 167075.4 | C12: 167075.4
A13: SLED Southeast | B13: -578195.86 | C13: -578195.86
A14: Issue: AP Correction Needed | B14: -38054.5 | C14: -38054.5
A15: Timing: Streamline | B15: -540141.36 | C15: -540141.36
A16: Federal DoN Tactical | B16: -227442.19 | C16: -227442.19
A17: Issue: AP Correction Needed | B17: 64668 | C17: 64668
A18: Issue: Needs Research | B18: -292110.19 | C18: -292110.19
A19: SLED HI/Comm | B19: -659 | C19: -659
... A36: Grand Total | B36: -657554.44 | C36: -657554.44

Sheet MAR-25
A1: World Wide Technology
A2: Accrued Liabilities - Public Sector
A3: ON-PREM G/L # 01.XXXX.24521.000
A4: CLOUD GL# 101.XXXXX.245011.XXXX.XXX.XXX.XXXX.XXXX
A5: 45747
A7: Row Labels | B7: Sum of Functional Amount | C7: Sum of Global Amount
A8: SLED Southeast | B8: -578195.86 | C8: -578195.86
A9: Issue: AP Correction Needed | B9: -38054.5 | C9: -38054.5
A10: Timing: Streamline | B10: -540141.36 | C10: -540141.36
A11: Federal DoN Tactical | B11: -227442.19 | C11: -227442.19
A12: Issue: AP Correction Needed | B12: 64668 | C12: 64668
A13: Issue: Needs Research | B13: -292110.19 | C13: -292110.19
A14: Federal Intel | B14: -635360 | C14: -635360
A15: Issue: AP Correction Needed | B15: 100000 | C15: 100000
A16: Timing: Streamline | B16: -735360 | C16: -735360
A17: SLED California | B17: 881922.6 | C17: 881922.6
A18: Issue: AR Correction Needed | B18: 881922.6 | C18: 881922.6
A19: Federal Law Enforcement | B19: -2105.77 | C19: -2105.77
... A25: Grand Total | B25: -687204.53 | C25: -687204.53
A40: Total | B40: =GETPIVOTDATA("Sum of Functional Amount",$A$7) -> -687204.53
A42: G/L Balance - USD | B42: -628826.53
A44: Variance | B44: =B40-B42 -> -58378
A46: Date Reconciled | B46: 45761

Sheet APR-25
A1: World Wide Technology
A2: Accrued Liabilities - Public Sector
A3: ON-PREM G/L # 01.XXXX.24521.000
A4: CLOUD GL# 101.XXXXX.245011.XXXX.XXX.XXX.XXXX.XXXX
A5: 45777
A7: Row Labels | B7: Sum of Functional Amount | C7: Sum of Global Amount | E7: Total | F7: =GETPIVOTDATA("Sum of Functional Amount",$A$7) -> #REF!
A8: SLED Southeast | B8: -578195.86 | C8: -578195.86
A9: Issue: AP Correction Needed | B9: -38054.5 | C9: -38054.5 | E9: G/L Balance - USD | F9: -475136.12
A10: Timing: Streamline | B10: -540141.36 | C10: -540141.36
A11: Federal DoN Tactical | B11: -227442.19 | C11: -227442.19 | E11: Variance | F11: =F7-F9 -> #REF!
A12: Issue: AP Correction Needed | B12: 64668 | C12: 64668
A13: Issue: Needs Research | B13: -292110.19 | C13: -292110.19 | E13: Date Reconciled | F13: 45791
A14: Federal Intel | B14: -435362 | C14: -435362
A15: Issue: AP Correction Needed | B15: 100000 | C15: 100000
A16: Timing: Order on Hold | B16: 199998 | C16: 199998
A17: Timing: Streamline | B17: -735360 | C17: -735360
A18: SLED California | B18: 881922.6 | C18: 881922.6
A19: Issue: AR Correction Needed | B19: 881922.6 | C19: 881922.6
A20: Federal USAF/USSF | B20: -5029.46 | C20: -5029.46
A21: Timing: Order on Hold | B21: -5029.46 | C21: -5029.46
A22: Federal Law Enforcement | B22: -2105.77 | C22: -2105.77
A23: Issue: Needs Research | B23: -2105.77 | C23: -2105.77
A24: Federal Army House | B24: -1293.75 | C24: -1293.75
A25: Issue: Needs Research | B25: -1293.75 | C25: -1293.75
... A34: Grand Total | B34: -475136.12 | C34: -475136.12

Sheet MAY-25
A1: World Wide Technology
A2: Accrued Liabilities - Public Sector
A3: ON-PREM G/L # 01.XXXX.24521.000
A4: CLOUD GL# 101.XXXXX.245011.XXXX.XXX.XXX.XXXX.XXXX
A5: 45808
A7: Row Labels | B7: Sum of Functional Amount | C7: Sum of Global Amount | E7: Total | F7: =SUMIFS(B8:B143,A8:A143,"Grand Total") -> -1482537.5
A8: SLED Southeast | B8: -578195.86 | C8: -578195.86
A9: Issue: AP Correction Needed | B9: -38054.5 | C9: -38054.5 | E9: G/L Balance - USD | F9: -1482537.5
A10: Timing: Streamline | B10: -540141.36 | C10: -540141.36
A11: Federal DoN Tactical | B11: -112410.73 | C11: -112410.73 | E11: Variance | F11: =F7-F9 -> 0
A12: Issue: AP Correction Needed | B12: 64668 | C12: 64668
A13: Issue: Needs Research | B13: -292110.19 | C13: -292110.19 | E13: Date Reconciled | F13: 45817
A14: Issue: Recvue AR Correction Needed | B14: 115031.46 | C14: 115031.46
A15: Federal Intel | B15: -635360 | C15: -635360
A16: Issue: AP Correction Needed | B16: 100000 | C16: 100000
A17: Timing: Order on Hold | B17: 0 | C17: 0
A18: Timing: Streamline | B18: -735360 | C18: -735360
A19: - | B19: 0 | C19: 0
A20: SLED California | B20: 881922.6 | C20: 881922.6
A21: Issue: AR Correction Needed | B21: 881922.6 | C21: 881922.6
A22: Federal USAF/USSF | B22: -1420584.2 | C22: -1420584.2
A23: Issue: AP Correction Needed | B23: -1415554.7 | C23: -1415554.7
A24: Timing: Order on Hold | B24: -5029.46 | C24: -5029.46
A25: Federal Law Enforcement | B25: -2105.77 | C25: -2105.77
... A40: Issue: AP Correction Needed | B40: -613137.44 | C40: -613137.44
A41: (blank)
A42: (blank)
A43: Grand Total | B43: -1482537.5 | C43: -1482537.5

Sheet JUN-25
A1: World Wide Technology
A2: Accrued Liabilities - Public Sector
A3: ON-PREM G/L # 01.XXXX.24521.000
A4: CLOUD GL# 101.XXXXX.245011.XXXX.XXX.XXX.XXXX.XXXX
A5: 45838
A7: Row Labels | B7: Sum of Functional Amount | C7: Sum of Global Amount | E7: Total | F7: =SUMIFS(B8:B143,A8:A143,"Grand Total") -> -974487.28
A8: SLED Southeast | B8: -578195.86 | C8: -578195.86
A9: Issue: AP Correction Needed | B9: -38054.5 | C9: -38054.5 | E9: G/L Balance - USD | F9: -974487.28
A10: Timing: Streamline | B10: -540141.36 | C10: -540141.36
A11: Federal DoN Tactical | B11: -227442.19 | C11: -227442.19 | E11: Variance | F11: =F7-F9 -> 0
A12: Issue: AP Correction Needed | B12: 64668 | C12: 64668
A13: Issue: Needs Research | B13: -292110.19 | C13: -292110.19 | E13: Date Reconciled | F13: 45848
A14: Issue: Recvue AR Correction Needed | B14: 0 | C14: 0
A15: Federal Intel | B15: -635360 | C15: -635360
A16: Issue: AP Correction Needed | B16: 100000 | C16: 100000
A17: Timing: Streamline | B17: -735360 | C17: -735360
A18: SLED California | B18: 736168.8 | C18: 736168.8
A19: Issue: AP Correction Needed | B19: -145753.8 | C19: -145753.8
A20: Issue: AR Correction Needed | B20: 881922.6 | C20: 881922.6
A21: Federal USAF/USSF | B21: -649632.76 | C21: -649632.76
A22: Issue: AP Correction Needed | B22: -644603.3 | C22: -644603.3
A23: Timing: Order on Hold | B23: -5029.46 | C23: -5029.46
A24: Federal Law Enforcement | B24: -2105.77 | C24: -2105.77
A25: Issue: Needs Research | B25: -2105.77 | C25: -2105.77
... A34: Issue: AP Correction Needed | B34: -613137.44 | C34: -613137.44
A35: (blank)
A36: (blank)
A37: Federal Defense Agencies | B37: -2115.92 | C37: -2115.92
A38: Timing: Order on Hold | B38: -2115.92 | C38: -2115.92
A39: Grand Total | B39: -974487.28 | C39: -974487.28

Sheet JUL-25
A1: World Wide Technology
A2: Accrued Liabilities - Public Sector
A3: ON-PREM G/L # 01.XXXX.24521.000
A4: CLOUD GL# 101.XXXXX.245011.XXXX.XXX.XXX.XXXX.XXXX
A5: 45869
A7: Row Labels | B7: Sum of Functional Amount | C7: Sum of Global Amount | E7: Total | F7: =SUMIFS(B8:B143,A8:A143,"Grand Total") -> -231432.35
A8: SLED Southeast | B8: -578195.86 | C8: -578195.86
A9: Issue: AP Correction Needed | B9: -38054.5 | C9: -38054.5 | E9: G/L Balance - USD | F9: -231432.35
A10: Timing: Streamline | B10: -540141.36 | C10: -540141.36
A11: Federal DoN Tactical | B11: -227442.19 | C11: -227442.19 | E11: Variance | F11: =F7-F9 -> -2.910383e-10
A12: Issue: AP Correction Needed | B12: 64668 | C12: 64668
A13: Issue: Needs Research | B13: -292110.19 | C13: -292110.19 | E13: Date Reconciled | F13: 45883
A14: Federal Intel | B14: 388962.88 | C14: 388962.88
A15: Issue: AP Correction Needed | B15: 100000 | C15: 100000
A16: Timing: Order on Hold | B16: 779202.88 | C16: 779202.88
A17: Timing: Streamline | B17: -490240 | C17: -490240
A18: SLED California | B18: 736168.8 | C18: 736168.8
A19: Issue: AP Correction Needed | B19: -145753.8 | C19: -145753.8
A20: Issue: AR Correction Needed | B20: 881922.6 | C20: 881922.6
A21: Federal USAF/USSF | B21: -649632.76 | C21: -649632.76
A22: Issue: AP Correction Needed | B22: -644603.3 | C22: -644603.3
A23: Timing: Order on Hold | B23: -5029.46 | C23: -5029.46
A24: Federal Law Enforcement | B24: -2105.77 | C24: -2105.77
A25: Issue: Needs Research | B25: -2105.77 | C25: -2105.77
... A41: Grand Total | B41: -231432.35 | C41: -231432.35

Sheet FEB-26
A1: World Wide Technology
A2: Accrued Liabilities - Public Sector
A3: ON-PREM G/L # 01.XXXX.24521.000
A4: CLOUD GL# 101.XXXXX.245011.XXXX.XXX.XXX.XXXX.XXXX
A5: 46081
A7: Row Labels | B7: Sum of Functional Amount | C7: Sum of Global Amount | E7: Total | F7: =SUMIFS(B8:B143,A8:A143,"Grand Total") -> -200536.45
A8: SLED Southeast | B8: -360094.24 | C8: -360094.24
A9: Timing: Streamline | B9: -360094.24 | C9: -360094.24 | E9: G/L Balance - USD | F9: -471599.97
A10: Federal Intel | B10: -346579 | C10: -346579
A11: Timing: Order on Hold | B11: 143661 | C11: 143661 | E11: Variance | F11: =F7-F9 -> 271063.52
A12: Timing: Streamline | B12: -490240 | C12: -490240
A13: SLED California | B13: 881922.6 | C13: 881922.6 | E13: Date Reconciled | F13: 46093
A14: Issue: AR Correction Needed | B14: 881922.6 | C14: 881922.6
A15: Federal Army House | B15: -9056.25 | C15: -9056.25
A16: Issue: AP Correction Needed | B16: -2587.5 | C16: -2587.5
A17: Issue: Needs Research | B17: -6468.75 | C17: -6468.75
A18: Federal Army Tactical | B18: -124729.56 | C18: -124729.56
A19: Issue: AP Correction Needed | B19: -124729.56 | C19: -124729.56
A20: Federal Army Enterprise | B20: 3000 | C20: 3000
A21: Issue: AR Correction Needed | B21: 3000 | C21: 3000
A22: SLED Midwest | B22: -245000 | C22: -245000
A23: Issue: Recvue Needs Research | B23: -245000 | C23: -245000
A24: Grand Total | B24: -200536.45 | C24: -200536.45

Sheet APR-26
A1: World Wide Technology
A2: Accrued Liabilities - Public Sector
A3: ON-PREM G/L # 01.XXXX.24521.000
A4: CLOUD GL# 101.XXXXX.245011.XXXX.XXX.XXX.XXXX.XXXX
A5: 46142
A7: Row Labels | B7: Sum of Functional Amount | C7: Sum of Global Amount | E7: Total | F7: =SUMIFS(B8:B143,A8:A143,"Grand Total") -> 597569.36
A8: SLED Southeast | B8: -360094.24 | C8: -360094.24
A9: Timing: Streamline | B9: -360094.24 | C9: -360094.24 | E9: G/L Balance - USD | F9: 597569.36
A10: Federal Intel | B10: -211949.8 | C10: -211949.8
A11: Issue: AP Correction Needed | B11: 134629.2 | C11: 134629.2 | E11: Variance | F11: =F7-F9 -> 0
A12: Timing: Order on Hold | B12: 143661 | C12: 143661
A13: Timing: Streamline | B13: -490240 | C13: -490240 | E13: Date Reconciled | F13: 46156
A14: SLED California | B14: 881922.6 | C14: 881922.6
A15: Issue: AR Correction Needed | B15: 881922.6 | C15: 881922.6
A16: Federal Army House | B16: -11643.78 | C16: -11643.78
A17: Issue: AP Correction Needed | B17: -2587.5 | C17: -2587.5
A18: Issue: Needs Research | B18: -9056.28 | C18: -9056.28
A19: Federal Army Tactical | B19: -124729.56 | C19: -124729.56
A20: Issue: AP Correction Needed | B20: -124729.56 | C20: -124729.56
A21: Federal Army Enterprise | B21: 98538.95 | C21: 98538.95
A22: Issue: AR Correction Needed | B22: 191538.95 | C22: 191538.95
A23: Accrual: Agent Fee | B23: -93000 | C23: -93000
A24: SLED Midwest | B24: -245000 | C24: -245000
A25: Issue: Recvue Needs Research | B25: -245000 | C25: -245000
... A46: Grand Total | B46: 597569.36 | C46: 597569.36

Sheet MAY-26
A1: World Wide Technology (WWT)
A2: Accrued Liabilities - Public Sector
A3: ON-PREM G/L # 01.XXXX.24521.000
A4: CLOUD GL# 101.XXXXX.245011.XXXX.XXX.XXX.XXXX.XXXX
A5: 46173
A7: Row Labels | B7: Sum of Functional Amount | C7: Sum of Global Amount | E7: Total | F7: =SUMIFS(B8:B143,A8:A143,"Grand Total") -> -13905762
A8: SLED Southeast | B8: -360094.24 | C8: -360094.24
A9: Timing: Streamline | B9: -360094.24 | C9: -360094.24 | E9: G/L Balance - USD | F9: -13905762
A10: Federal Intel | B10: -69629.8 | C10: -69629.8
A11: Issue: AP Correction Needed | B11: 276949.2 | C11: 276949.2 | E11: Variance | F11: =F7-F9 -> 0
A12: Timing: Order on Hold | B12: 143661 | C12: 143661
A13: Timing: Streamline | B13: -490240 | C13: -490240 | E13: Date Reconciled | F13: 46185
A14: SLED California | B14: 881922.6 | C14: 881922.6
A15: Issue: AR Correction Needed | B15: 881922.6 | C15: 881922.6
A16: Federal Army House | B16: -12708351 | C16: -12708351
A17: Issue: AP Correction Needed | B17: -12699295 | C17: -12699295
A18: Issue: Needs Research | B18: -9056.28 | C18: -9056.28
A19: Federal Army Tactical | B19: -124729.56 | C19: -124729.56
A20: Issue: AP Correction Needed | B20: -124729.56 | C20: -124729.56
A21: Federal Army Enterprise | B21: -90000 | C21: -90000
A22: Issue: AR Correction Needed | B22: 3000 | C22: 3000
A23: Accrual: Agent Fee | B23: -93000 | C23: -93000
A24: SLED Midwest | B24: -245000 | C24: -245000
A25: Issue: Recvue Needs Research | B25: -245000 | C25: -245000
... A46: Grand Total | B46: -13905762 | C46: -13905762

Sheet JUN-26
A1: World Wide Technology (WWT)
A2: Accrued Liabilities - Public Sector
A3: ON-PREM G/L # 01.XXXX.24521.000
A4: CLOUD GL# 101.XXXXX.245011.XXXX.XXX.XXX.XXXX.XXXX
A5: 46203
A7: Row Labels | B7: Sum of Functional Amount | C7: Sum of Global Amount | E7: Total | F7: =SUMIFS(B8:B143,A8:A143,"Grand Total") -> -68318647
A8: SLED Southeast | B8: -360094.24 | C8: -360094.24
A9: Timing: Streamline | B9: -360094.24 | C9: -360094.24 | E9: G/L Balance - USD | F9: -68318647
A10: Federal Intel | B10: -346579 | C10: -346579
A11: Issue: AP Correction Needed | B11: 0 | C11: 0 | E11: Variance | F11: =F7-F9 -> 0
A12: Timing: Order on Hold | B12: 143661 | C12: 143661
A13: Timing: Streamline | B13: -490240 | C13: -490240 | E13: Date Reconciled | F13: 46213
A14: SLED California | B14: 413633.27 | C14: 413633.27
A15: Issue: AP Correction Needed | B15: -468289.33 | C15: -468289.33
A16: Issue: AR Correction Needed | B16: 881922.6 | C16: 881922.6
A17: Federal Army House | B17: -7581488.2 | C17: -7581488.2
A18: Issue: AP Correction Needed | B18: -19718940 | C18: -19718940
A19: Issue: Needs Research | B19: -9056.28 | C19: -9056.28
A20: Reclass: Sales Channel Move | B20: 12146508 | C20: 12146508
A21: Federal Army Tactical | B21: -124729.56 | C21: -124729.56
A22: Issue: AP Correction Needed | B22: -124729.56 | C22: -124729.56
A23: Federal Army Enterprise | B23: -90000 | C23: -90000
A24: Issue: AR Correction Needed | B24: 3000 | C24: 3000
A25: Accrual: Agent Fee | B25: -93000 | C25: -93000
... A53: Grand Total | B53: -68318647 | C53: -68318647

Sheet JUL-26
A1: World Wide Technology (WWT)
A2: Accrued Liabilities - Public Sector
A3: ON-PREM G/L # 01.XXXX.24521.000
A4: CLOUD GL# 101.XXXXX.245011.XXXX.XXX.XXX.XXXX.XXXX
A5: 46234
A7: Row Labels | B7: Sum of Functional Amount | C7: Sum of Global Amount | E7: Total | F7: =SUMIFS(B8:B143,A8:A143,"Grand Total") -> 9698734
A8: SLED Southeast | B8: -360094.24 | C8: -360094.24
A9: Timing: Streamline | B9: -360094.24 | C9: -360094.24 | E9: G/L Balance - USD | F9: 9698734
A10: Federal Intel | B10: -14632.92 | C10: -14632.92
A11: Timing: Order on Hold | B11: 143661 | C11: 143661 | E11: Variance | F11: =F7-F9 -> 0
A12: Timing: Streamline | B12: -245120 | C12: -245120
A13: Issue: Recvue Needs Research | B13: 86826.08 | C13: 86826.08 | E13: Date Reconciled | F13: 46244
A14: SLED California | B14: 413633.27 | C14: 413633.27
A15: Issue: AP Correction Needed | B15: -468289.33 | C15: -468289.33
A16: Issue: AR Correction Needed | B16: 881922.6 | C16: 881922.6
A17: Federal Army House | B17: -367481.86 | C17: -367481.86
A18: Issue: AP Correction Needed | B18: -16901059 | C18: -16901059
A19: Issue: Needs Research | B19: -9056.28 | C19: -9056.28
A20: Reclass: Sales Channel Move | B20: 12146508 | C20: 12146508
A21: Issue: Recvue AP Correction Needed | B21: 4396125.7 | C21: 4396125.7
A22: Federal Army Tactical | B22: -124729.56 | C22: -124729.56
A23: Issue: AP Correction Needed | B23: -124729.56 | C23: -124729.56
A24: Federal Army Enterprise | B24: -90000 | C24: -90000
A25: Issue: AR Correction Needed | B25: 3000 | C25: 3000
... A55: Accrual: Dropship | B55: -876000 | C55: -876000
A56: (blank)
A57: (blank)
A58: Grand Total | B58: 9698734 | C58: 9698734

Sheet AUG-26
A1: World Wide Technology (WWT)
A2: Accrued Liabilities - Public Sector
A3: ON-PREM G/L # 01.XXXX.24521.000
A4: CLOUD GL# 101.XXXXX.245011.XXXX.XXX.XXX.XXXX.XXXX
A5: 46265
A7: Row Labels | B7: Sum of Functional Amount | C7: Sum of Global Amount | E7: Total | F7: =SUMIFS(B8:B55,A8:A55,"Grand Total") -> 9611907.9
A8: SLED Southeast | B8: -360094.24 | C8: -360094.24
A9: Timing: Streamline | B9: -360094.24 | C9: -360094.24 | E9: G/L Balance - USD | F9: 9611907.9
A10: Federal Intel | B10: -101459 | C10: -101459
A11: Timing: Order on Hold | B11: 143661 | C11: 143661 | E11: Variance | F11: =F7-F9 -> 0
A12: Timing: Streamline | B12: -245120 | C12: -245120
A13: SLED California | B13: 413633.27 | C13: 413633.27 | E13: Date Reconciled | F13: 46251
A14: Issue: AP Correction Needed | B14: -468289.33 | C14: -468289.33
A15: Issue: AR Correction Needed | B15: 881922.6 | C15: 881922.6
A16: Federal Army House | B16: -367481.86 | C16: -367481.86
A17: Issue: AP Correction Needed | B17: -16901059 | C17: -16901059
A18: Issue: Needs Research | B18: -9056.28 | C18: -9056.28
A19: Reclass: Sales Channel Move | B19: 12146508 | C19: 12146508
A20: Issue: Recvue AP Correction Needed | B20: 4396125.7 | C20: 4396125.7
A21: Federal Army Tactical | B21: -124729.56 | C21: -124729.56
A22: Issue: AP Correction Needed | B22: -124729.56 | C22: -124729.56
A23: Federal Army Enterprise | B23: -90000 | C23: -90000
A24: Issue: AR Correction Needed | B24: 3000 | C24: 3000
A25: Accrual: Agent Fee | B25: -93000 | C25: -93000
... A55: Grand Total | B55: 9611907.9 | C55: 9611907.9

Sheet Details
D1: Offsets
D2: To be worked in APR-24
D3: Action item for APR-24
D4: Mutli JE's
L5: =SUBTOTAL(9,L7:L1048576) -> 9698734
A6: Age | B6: Aging Bucket | C6: CA Manager Comments | D6: Cost Accountant Comments | E6: Analyst | F6: P And L Name Curr | G6: Je Batch Name | H6: Je Name | I6: Je Reason Code | J6: Gl Period Name | K6: Entered Amount | L6: Functional Amount | M6: Global Amount | N6: Currency Code Entered | O6: Currency Code Functional | P6: Description Header | Q6: Description Line | R6: Company Name Curr | S6: Financial Program Curr | T6: Sub Program Curr | U6: P And L Rollup Curr | V6: Concatenated Segments | W6: Company Code | X6: P And L Code | Y6: Account Code | Z6: Cost Cntr Code | AA6: Gl Location Code | AB6: Gl Intercompany Code | AC6: Future1 Code | AD6: Future2 Code | AE6: Account Name Curr | AF6: WWT Po Number | AG6: WWT Po Description | AH6: WWT Source | AI6: Transaction Date | AJ6: Transaction Number | AK6: Je Effective Date | AL6: Je Source | AM6: Ledger Name
A7: =TODAY()-AK7 -> 657 | B7: =IFERROR(VLOOKUP(A7,'Aging Formulas'!A:B,2,FALSE),"365+") -> 365+ | D7: Streamline PO GDIT-33088 General Dynamics Information Tech - Releasing 2026 & 2027 | E7: Fienup, Mary Frances | F7: Federal Intel | G7: TJM-110424-11 Streamline PO GDIT-33088 General Dynamics Information Tech Reverse Year 422 22800007 N | H7: TJM-110424-11 Streamline PO GDIT-33088 General Dynamics Information Tech Reverse Year 5 2027 225358 | I7: Timing: Streamline | J7: Oct-24 | K7: -245120 | L7: -245120 | M7: -245120 | N7: USD | O7: USD | P7: Streamlining PO GDIT-33088 WWTNCSAAS1270 - Cisco credit 6101578249 given in year 1 and year 2 streamlining over the 5 year deal | Q7: Journal Import Created | R7: World Wide Technology, LLC (WWT) | S7: Public Sector | T7: Federal | U7: Federal IC | V7: 101.12012.245011.9999.999.999.9999.9999 | W7: 101 | X7: 12012 | Y7: 245011 | Z7: 9999 | AA7: 999 | AB7: 999 | AC7: 9999 | AD7: 9999 | AE7: Accrued Liabilities - Public Sector | AF7: - | AG7: - | AH7: CLOUD | AJ7: - | AK7: 45594 | AL7: EBS OPR | AM7: WWT US Ledger
A8: =TODAY()-AK8 -> 655 | B8: =IFERROR(VLOOKUP(A8,'Aging Formulas'!A:B,2,FALSE),"365+") -> 365+ | D8: Streamline PO Y25AMW0050 UNC at Chapel Hill Reverse - Releasing 2026 & 2027 | E8: Simms, Amanda | F8: SLED Southeast | G8: TJM-110524-5 Streamline PO Y25AMW0050 UNC at Chapel Hill Reverse Year 4 2027 05-NOV-2024 22800004 N | H8: TJM-110524-5 Streamline PO Y25AMW0050 UNC at Chapel Hill Reverse Year 4 2027 OPR Adjustments | I8: Timing: Streamline | J8: Oct-24 | K8: -180047.12 | L8: -180047.12 | M8: -180047.12 | N8: USD | O8: USD | P8: Streamline PO Y25AMW0050 UNC at Chapel Hill Reverse Year 4 2027 | Q8: Journal Import Created | R8: World Wide Technology, LLC (WWT) | S8: Public Sector | T8: SLED | U8: SLED East | V8: 101.13008.245011.9999.999.999.9999.9999 | W8: 101 | X8: 13008 | Y8: 245011 | Z8: 9999 | AA8: 999 | AB8: 999 | AC8: 9999 | AD8: 9999 | AE8: Accrued Liabilities - Public Sector | AF8: - | AG8: - | AH8: CLOUD | AJ8: - | AK8: 45596 | AL8: EBS OPR | AM8: WWT US Ledger
A9: =TODAY()-AK9 -> 655 | B9: =IFERROR(VLOOKUP(A9,'Aging Formulas'!A:B,2,FALSE),"365+") -> 365+ | D9: Streamline PO Y25AMW0050 UNC at Chapel Hill Reverse - Releasing 2026 & 2027 | E9: Simms, Amanda | F9: SLED Southeast | G9: TJM-110524-4 Streamline PO Y25AMW0050 UNC at Chapel Hill Reverse Year 3 2026 05-NOV-2024 22800004 N | H9: TJM-110524-4 Streamline PO Y25AMW0050 UNC at Chapel Hill Reverse Year 3 2026 OPR Adjustments | I9: Timing: Streamline | J9: Oct-24 | K9: -180047.12 | L9: -180047.12 | M9: -180047.12 | N9: USD | O9: USD | P9: Streamline PO Y25AMW0050 UNC at Chapel Hill Reverse Year 3 2026 | Q9: Journal Import Created | R9: World Wide Technology, LLC (WWT) | S9: Public Sector | T9: SLED | U9: SLED East | V9: 101.13008.245011.9999.999.999.9999.9999 | W9: 101 | X9: 13008 | Y9: 245011 | Z9: 9999 | AA9: 999 | AB9: 999 | AC9: 9999 | AD9: 9999 | AE9: Accrued Liabilities - Public Sector | AF9: - | AG9: - | AH9: CLOUD | AJ9: - | AK9: 45596 | AL9: EBS OPR | AM9: WWT US Ledger
A10: =TODAY()-AK10 -> 594 | B10: =IFERROR(VLOOKUP(A10,'Aging Formulas'!A:B,2,FALSE),"365+") -> 365+ | D10: Correcting or taking hit by Sep-26 - Deferred SO 11858312 PO 19537991-0-CAP out of Dec - working with team to address missing cost | E10: Simms, Amanda | F10: SLED California | G10: TJM-010725-8 Defer SO 11858312 PO 19537991-0-CAP out of Dec-24 07-JAN-2025 12:59:48 EBS O 23865721 N | H10: TJM-010725-8 Defer SO 11858312 PO 19537991-0-CAP out of Dec-24 OPR Adjustments | I10: Issue: AR Correction Needed | J10: Dec-24 | K10: 881922.6 | L10: 881922.6 | M10: 881922.6 | N10: USD | O10: USD | P10: Defer SO 11858312 PO 19537991-0-CAP out of Dec-24 | Q10: Journal Import Created | R10: World Wide Technology, LLC (WWT) | S10: Public Sector | T10: SLED | U10: SLED West | V10: 101.13016.245011.9999.999.999.9999.9999 | W10: 101 | X10: 13016 | Y10: 245011 | Z10: 9999 | AA10: 999 | AB10: 999 | AC10: 9999 | AD10: 9999 | AE10: Accrued Liabilities - Public Sector | AF10: - | AG10: - | AH10: CLOUD | AJ10: - | AK10: 45657 | AL10: EBS OPR | AM10: WWT US Ledger
A11: =TODAY()-AK11 -> 563 | B11: =IFERROR(VLOOKUP(A11,'Aging Formulas'!A:B,2,FALSE),"365+") -> 365+ | D11: Reviewing with Stephanie - related to SEWP Fees - Deferred AP invoice - researching | E11: Maggi, Brandon | F11: Federal Army House | G11: TJM-020625-3 Deferring AP Invoice out of Jan-25 Spreadsheet A 300000305300838 24387210 N | H11: TJM-020625-3 Deferring AP Invoice out of Jan-25 Adjustment | I11: Issue: Needs Research | J11: Jan-25 | K11: -1293.75 | L11: -1293.75 | M11: -1293.75 | N11: USD | O11: USD | P11: Deferring AP Invoice out of Jan-25 | Q11: Journal Import Created | R11: World Wide Technology, LLC (WWT) | S11: Public Sector | T11: Federal | U11: Federal Department of Defense | V11: 101.11002.245011.9999.999.999.9999.9999 | W11: 101 | X11: 11002 | Y11: 245011 | Z11: 9999 | AA11: 999 | AB11: 999 | AC11: 9999 | AD11: 9999 | AE11: Accrued Liabilities - Public Sector | AF11: - | AG11: - | AH11: CLOUD | AJ11: - | AK11: 45688 | AL11: Spreadsheet | AM11: WWT US Ledger
A12: =TODAY()-AK12 -> 504 | B12: =IFERROR(VLOOKUP(A12,'Aging Formulas'!A:B,2,FALSE),"365+") -> 365+ | D12: Reviewing with Stephanie - Deferring AP Invoices Coded to Incorrect Account | E12: Maggi, Brandon | F12: Federal Army Tactical | G12: TJM-040425-9 Deferring AP Invoices Coded to Incorrect Account Spreadsheet A 3000003053008 25423574 N | H12: TJM-040425-9 Deferring AP Invoices Coded to Incorrect Account Adjustment | I12: Issue: AP Correction Needed | J12: Mar-25 | K12: -103941.3 | L12: -103941.3 | M12: -103941.3 | N12: USD | O12: USD | P12: Deferring AP Invoices Coded to Incorrect Account X05635750101CMRECLASS | Q12: Journal Import Created | R12: World Wide Technology, LLC (WWT) | S12: Public Sector | T12: Federal | U12: Federal Department of Defense | V12: 101.11004.245011.9999.999.999.9999.9999 | W12: 101 | X12: 11004 | Y12: 245011 | Z12: 9999 | AA12: 999 | AB12: 999 | AC12: 9999 | AD12: 9999 | AE12: Accrued Liabilities - Public Sector | AF12: P010282017 | AG12: - | AH12: CLOUD | AJ12: - | AK12: 45747 | AL12: Spreadsheet | AM12: WWT US Ledger
A13: =TODAY()-AK13 -> 504 | B13: =IFERROR(VLOOKUP(A13,'Aging Formulas'!A:B,2,FALSE),"365+") -> 365+ | D13: Reviewing with Stephanie - Deferring AP Invoices Coded to Incorrect Account | E13: Maggi, Brandon | F13: Federal Army Tactical | G13: TJM-040425-9 Deferring AP Invoices Coded to Incorrect Account Spreadsheet A 3000003053008 25423574 N | H13: TJM-040425-9 Deferring AP Invoices Coded to Incorrect Account Adjustment | I13: Issue: AP Correction Needed | J13: Mar-25 | K13: -20788.26 | L13: -20788.26 | M13: -20788.26 | N13: USD | O13: USD | P13: Deferring AP Invoices Coded to Incorrect Account X05635750101CMRECLASS | Q13: Journal Import Created | R13: World Wide Technology, LLC (WWT) | S13: Public Sector | T13: Federal | U13: Federal Department of Defense | V13: 101.11004.245011.9999.999.999.9999.9999 | W13: 101 | X13: 11004 | Y13: 245011 | Z13: 9999 | AA13: 999 | AB13: 999 | AC13: 9999 | AD13: 9999 | AE13: Accrued Liabilities - Public Sector | AF13: P010282017 | AG13: - | AH13: CLOUD | AJ13: - | AK13: 45747 | AL13: Spreadsheet | AM13: WWT US Ledger
A14: =TODAY()-AK14 -> 443 | B14: =IFERROR(VLOOKUP(A14,'Aging Formulas'!A:B,2,FALSE),"365+") -> 365+ | D14: Reviewing with Stephanie - related to SEWP Fees - Deferred AP invoice - researching | E14: Maggi, Brandon | F14: Federal Army House | G14: TJM-060525-16 Deferring AP Invoice out of May-25 | H14: TJM-060525-16 Deferring AP Invoice out of May-25 | I14: Issue: AP Correction Needed | J14: May-25 | K14: -1293.75 | L14: -1293.75 | M14: -1293.75 | N14: USD | O14: USD | P14: Deferring AP Invoice out of May-25 | Q14: - | R14: World Wide Technology, LLC (WWT) | S14: Public Sector | T14: Federal | U14: Federal Department of Defense | V14: 101.11002.245011.9999.950.999.9999.9999 | W14: 101 | X14: 11002 | Y14: 245011 | Z14: 9999 | AA14: 950 | AB14: 999 | AC14: 9999 | AD14: 9999 | AE14: Accrued Liabilities - Public Sector | AF14: HC108421F0175 | AG14: - | AH14: CLOUD | AJ14: - | AK14: 45808 | AL14: Manual | AM14: WWT US Ledger
A15: =TODAY()-AK15 -> 351 | B15: =IFERROR(VLOOKUP(A15,'Aging Formulas'!A:B,2,FALSE),"365+") -> 331-365 | D15: Deferred billing for Flywheel | E15: Fienup, Mary Frances | F15: Federal Intel | G15: TJM-090525-2 Deferring SO 12262718 On Hold out of Aug-25 Spreadsheet A 300000305300838 28187533 N | H15: TJM-090525-2 Deferring SO 12262718 On Hold out of Aug-25 Adjustment | I15: Timing: Order on Hold | J15: Aug-25 | K15: 143661 | L15: 143661 | M15: 143661 | N15: USD | O15: USD | P15: Deferring SO 12262718 On Hold out of Aug-25 | Q15: Journal Import Created | R15: World Wide Technology, LLC (WWT) | S15: Public Sector | T15: Federal | U15: Federal IC | V15: 101.12012.245011.9999.950.999.9999.9999 | W15: 101 | X15: 12012 | Y15: 245011 | Z15: 9999 | AA15: 950 | AB15: 999 | AC15: 9999 | AD15: 9999 | AE15: Accrued Liabilities - Public Sector | AF15: GDIT-70665 | AG15: - | AH15: CLOUD | AJ15: - | AK15: 45900 | AL15: Spreadsheet | AM15: WWT US Ledger
A16: =TODAY()-AK16 -> 321 | B16: =IFERROR(VLOOKUP(A16,'Aging Formulas'!A:B,2,FALSE),"365+") -> 301-330 | D16: Reviewing with Stephanie - related to SEWP Fees - Deferred AP invoice - researching | E16: Maggi, Brandon | F16: Federal Army House | G16: TJM-100625-4 Defer SO 11730740 Credit Memo out of Sep-25 Spreadsheet A 300000305300838 28776038 N | H16: TJM-100625-4 Defer SO 11730740 Credit Memo out of Sep-25 Adjustment | I16: Issue: AP Correction Needed | J16: Sep-25 | K16: -1293.75 | L16: -1293.75 | M16: -1293.75 | N16: USD | O16: USD | P16: Defer SO 11730740 Credit Memo out of Sep-25 | Q16: Journal Import Created | R16: World Wide Technology, LLC (WWT) | S16: Public Sector | T16: Federal | U16: Federal Department of Defense | V16: 101.11002.245011.9999.999.999.9999.9999 | W16: 101 | X16: 11002 | Y16: 245011 | Z16: 9999 | AA16: 999 | AB16: 999 | AC16: 9999 | AD16: 9999 | AE16: Accrued Liabilities - Public Sector | AF16: PK803151159C1 | AG16: - | AH16: CLOUD | AJ16: - | AK16: 45930 | AL16: Spreadsheet | AM16: WWT US Ledger
A17: =TODAY()-AK17 -> 321 | B17: =IFERROR(VLOOKUP(A17,'Aging Formulas'!A:B,2,FALSE),"365+") -> 301-330 | D17: Reviewing with Stephanie - Deferred SEWP invoice out of Sep-25 | E17: Maggi, Brandon | F17: Federal Army Enterprise | G17: TJM-100625-9 Defer SEWP Invoice 7680755 out of Sep-25 Spreadsheet A 300000305300838 28779212 N | H17: TJM-100625-9 Defer SEWP Invoice 7680755 out of Sep-25 Adjustment | I17: Issue: AR Correction Needed | J17: Sep-25 | K17: 3000 | L17: 3000 | M17: 3000 | N17: USD | O17: USD | P17: Defer SEWP Invoice 7680755 out of Sep-25 | Q17: Journal Import Created | R17: World Wide Technology, LLC (WWT) | S17: Public Sector | T17: Federal | U17: Federal Department of Defense | V17: 101.11003.245011.9999.950.999.9999.9999 | W17: 101 | X17: 11003 | Y17: 245011 | Z17: 9999 | AA17: 950 | AB17: 999 | AC17: 9999 | AD17: 9999 | AE17: Accrued Liabilities - Public Sector | AF17: - | AG17: - | AH17: CLOUD | AJ17: - | AK17: 45930 | AL17: Spreadsheet | AM17: WWT US Ledger
A18: =TODAY()-AK18 -> 290 | B18: =IFERROR(VLOOKUP(A18,'Aging Formulas'!A:B,2,FALSE),"365+") -> 151-300 | D18: Reviewing with Stephanie - related to SEWP Fees - Deferred AP invoice - researching | E18: Maggi, Brandon | F18: Federal Army House | G18: TJM-110625-7 Defer SO 11730740 Credit Memo out of Oct-25 Spreadsheet A 300000305300838 29368027 N | H18: TJM-110625-7 Defer SO 11730740 Credit Memo out of Oct-25 Adjustment | I18: Issue: Needs Research | J18: Oct-25 | K18: -1293.75 | L18: -1293.75 | M18: -1293.75 | N18: USD | O18: USD | P18: Defer SO 11730740 Credit Memo out of Oct-25 | Q18: Journal Import Created | R18: World Wide Technology, LLC (WWT) | S18: Public Sector | T18: Federal | U18: Federal Department of Defense | V18: 101.11002.245011.9999.999.999.9999.9999 | W18: 101 | X18: 11002 | Y18: 245011 | Z18: 9999 | AA18: 999 | AB18: 999 | AC18: 9999 | AD18: 9999 | AE18: Accrued Liabilities - Public Sector | AF18: PK803151159C1 | AG18: - | AH18: CLOUD | AJ18: - | AK18: 45961 | AL18: Spreadsheet | AM18: WWT US Ledger
... A63: =TODAY()-AK63 -> 17 | B63: =IFERROR(VLOOKUP(A63,'Aging Formulas'!A:B,2,FALSE),"365+") -> 0-30 | D63: Deferred Navy GEMSS Billing | E63: Maggi, Brandon | F63: Federal DoN Tactical | G63: TJM-080526-19 Defer Excess Navy GEMSS Cost out of Jul-26 162306 Recvue A 194974 467030034 33935595 N | H63: TJM-080526-19 Defer Excess Navy GEMSS Cost out of Jul-26 162306 OPR Adjustment USD User 1 OPR Adjus | I63: Issue: AP Correction Needed | J63: Jul-26 | K63: 3897163.4 | L63: 3897163.4 | M63: 3897163.4 | N63: USD | O63: USD | P63: Defer Excess Navy GEMSS Cost out of Jul-26 | Q63: Journal Import Created | R63: World Wide Technology, LLC (WWT) | S63: Public Sector | T63: Federal | U63: Federal Department of Defense | V63: 101.11023.245011.9999.999.999.9999.9999 | W63: 101 | X63: 11023 | Y63: 245011 | Z63: 9999 | AA63: 999 | AB63: 999 | AC63: 9999 | AD63: 9999 | AE63: Accrued Liabilities - Public Sector | AF63: - | AG63: - | AH63: CLOUD | AJ63: - | AK63: 46234 | AL63: EBS Recvue | AM63: WWT US Ledger

Sheet Details AUG-26
D1: Offsets
D2: To be worked in APR-24
D3: Action item for APR-24
D4: Mutli JE's
L5: =SUBTOTAL(9,L7:L1048576) -> 9611907.9
A6: Age | B6: Aging Bucket | C6: CA Manager Comments | D6: Cost Accountant Comments | E6: Analyst | F6: P And L Name Curr | G6: Je Batch Name | H6: Je Name | I6: Je Reason Code | J6: Gl Period Name | K6: Entered Amount | L6: Functional Amount | M6: Global Amount | N6: Currency Code Entered | O6: Currency Code Functional | P6: Description Header | Q6: Description Line | R6: Company Name Curr | S6: Financial Program Curr | T6: Sub Program Curr | U6: P And L Rollup Curr | V6: Concatenated Segments | W6: Company Code | X6: P And L Code | Y6: Account Code | Z6: Cost Cntr Code | AA6: Gl Location Code | AB6: Gl Intercompany Code | AC6: Future1 Code | AD6: Future2 Code | AE6: Account Name Curr | AF6: WWT Po Number | AG6: WWT Po Description | AH6: WWT Source | AI6: Transaction Date | AJ6: Transaction Number | AK6: Je Effective Date | AL6: Je Source | AM6: Ledger Name
A7: =TODAY()-AK7 -> 657 | B7: =IFERROR(VLOOKUP(A7,'Aging Formulas'!A:B,2,FALSE),"365+") -> 365+ | D7: Streamline PO GDIT-33088 General Dynamics Information Tech - Releasing 2026 & 2027 | E7: Fienup, Mary Frances | F7: Federal Intel | G7: TJM-110424-11 Streamline PO GDIT-33088 General Dynamics Information Tech Reverse Year 422 22800007 N | H7: TJM-110424-11 Streamline PO GDIT-33088 General Dynamics Information Tech Reverse Year 5 2027 225358 | I7: Timing: Streamline | J7: Oct-24 | K7: -245120 | L7: -245120 | M7: -245120 | N7: USD | O7: USD | P7: Streamlining PO GDIT-33088 WWTNCSAAS1270 - Cisco credit 6101578249 given in year 1 and year 2 streamlining over the 5 year deal | Q7: Journal Import Created | R7: World Wide Technology, LLC (WWT) | S7: Public Sector | T7: Federal | U7: Federal IC | V7: 101.12012.245011.9999.999.999.9999.9999 | W7: 101 | X7: 12012 | Y7: 245011 | Z7: 9999 | AA7: 999 | AB7: 999 | AC7: 9999 | AD7: 9999 | AE7: Accrued Liabilities - Public Sector | AF7: - | AG7: - | AH7: CLOUD | AJ7: - | AK7: 45594 | AL7: EBS OPR | AM7: WWT US Ledger
A8: =TODAY()-AK8 -> 655 | B8: =IFERROR(VLOOKUP(A8,'Aging Formulas'!A:B,2,FALSE),"365+") -> 365+ | D8: Streamline PO Y25AMW0050 UNC at Chapel Hill Reverse - Releasing 2026 & 2027 | E8: Simms, Amanda | F8: SLED Southeast | G8: TJM-110524-5 Streamline PO Y25AMW0050 UNC at Chapel Hill Reverse Year 4 2027 05-NOV-2024 22800004 N | H8: TJM-110524-5 Streamline PO Y25AMW0050 UNC at Chapel Hill Reverse Year 4 2027 OPR Adjustments | I8: Timing: Streamline | J8: Oct-24 | K8: -180047.12 | L8: -180047.12 | M8: -180047.12 | N8: USD | O8: USD | P8: Streamline PO Y25AMW0050 UNC at Chapel Hill Reverse Year 4 2027 | Q8: Journal Import Created | R8: World Wide Technology, LLC (WWT) | S8: Public Sector | T8: SLED | U8: SLED East | V8: 101.13008.245011.9999.999.999.9999.9999 | W8: 101 | X8: 13008 | Y8: 245011 | Z8: 9999 | AA8: 999 | AB8: 999 | AC8: 9999 | AD8: 9999 | AE8: Accrued Liabilities - Public Sector | AF8: - | AG8: - | AH8: CLOUD | AJ8: - | AK8: 45596 | AL8: EBS OPR | AM8: WWT US Ledger
A9: =TODAY()-AK9 -> 655 | B9: =IFERROR(VLOOKUP(A9,'Aging Formulas'!A:B,2,FALSE),"365+") -> 365+ | D9: Streamline PO Y25AMW0050 UNC at Chapel Hill Reverse - Releasing 2026 & 2027 | E9: Simms, Amanda | F9: SLED Southeast | G9: TJM-110524-4 Streamline PO Y25AMW0050 UNC at Chapel Hill Reverse Year 3 2026 05-NOV-2024 22800004 N | H9: TJM-110524-4 Streamline PO Y25AMW0050 UNC at Chapel Hill Reverse Year 3 2026 OPR Adjustments | I9: Timing: Streamline | J9: Oct-24 | K9: -180047.12 | L9: -180047.12 | M9: -180047.12 | N9: USD | O9: USD | P9: Streamline PO Y25AMW0050 UNC at Chapel Hill Reverse Year 3 2026 | Q9: Journal Import Created | R9: World Wide Technology, LLC (WWT) | S9: Public Sector | T9: SLED | U9: SLED East | V9: 101.13008.245011.9999.999.999.9999.9999 | W9: 101 | X9: 13008 | Y9: 245011 | Z9: 9999 | AA9: 999 | AB9: 999 | AC9: 9999 | AD9: 9999 | AE9: Accrued Liabilities - Public Sector | AF9: - | AG9: - | AH9: CLOUD | AJ9: - | AK9: 45596 | AL9: EBS OPR | AM9: WWT US Ledger
A10: =TODAY()-AK10 -> 594 | B10: =IFERROR(VLOOKUP(A10,'Aging Formulas'!A:B,2,FALSE),"365+") -> 365+ | D10: Correcting or taking hit by Sep-26 - Deferred SO 11858312 PO 19537991-0-CAP out of Dec - working with team to address missing cost | E10: Simms, Amanda | F10: SLED California | G10: TJM-010725-8 Defer SO 11858312 PO 19537991-0-CAP out of Dec-24 07-JAN-2025 12:59:48 EBS O 23865721 N | H10: TJM-010725-8 Defer SO 11858312 PO 19537991-0-CAP out of Dec-24 OPR Adjustments | I10: Issue: AR Correction Needed | J10: Dec-24 | K10: 881922.6 | L10: 881922.6 | M10: 881922.6 | N10: USD | O10: USD | P10: Defer SO 11858312 PO 19537991-0-CAP out of Dec-24 | Q10: Journal Import Created | R10: World Wide Technology, LLC (WWT) | S10: Public Sector | T10: SLED | U10: SLED West | V10: 101.13016.245011.9999.999.999.9999.9999 | W10: 101 | X10: 13016 | Y10: 245011 | Z10: 9999 | AA10: 999 | AB10: 999 | AC10: 9999 | AD10: 9999 | AE10: Accrued Liabilities - Public Sector | AF10: - | AG10: - | AH10: CLOUD | AJ10: - | AK10: 45657 | AL10: EBS OPR | AM10: WWT US Ledger
A11: =TODAY()-AK11 -> 563 | B11: =IFERROR(VLOOKUP(A11,'Aging Formulas'!A:B,2,FALSE),"365+") -> 365+ | D11: Reviewing with Stephanie - related to SEWP Fees - Deferred AP invoice - researching | E11: Maggi, Brandon | F11: Federal Army House | G11: TJM-020625-3 Deferring AP Invoice out of Jan-25 Spreadsheet A 300000305300838 24387210 N | H11: TJM-020625-3 Deferring AP Invoice out of Jan-25 Adjustment | I11: Issue: Needs Research | J11: Jan-25 | K11: -1293.75 | L11: -1293.75 | M11: -1293.75 | N11: USD | O11: USD | P11: Deferring AP Invoice out of Jan-25 | Q11: Journal Import Created | R11: World Wide Technology, LLC (WWT) | S11: Public Sector | T11: Federal | U11: Federal Department of Defense | V11: 101.11002.245011.9999.999.999.9999.9999 | W11: 101 | X11: 11002 | Y11: 245011 | Z11: 9999 | AA11: 999 | AB11: 999 | AC11: 9999 | AD11: 9999 | AE11: Accrued Liabilities - Public Sector | AF11: - | AG11: - | AH11: CLOUD | AJ11: - | AK11: 45688 | AL11: Spreadsheet | AM11: WWT US Ledger
A12: =TODAY()-AK12 -> 504 | B12: =IFERROR(VLOOKUP(A12,'Aging Formulas'!A:B,2,FALSE),"365+") -> 365+ | D12: Reviewing with Stephanie - Deferring AP Invoices Coded to Incorrect Account | E12: Maggi, Brandon | F12: Federal Army Tactical | G12: TJM-040425-9 Deferring AP Invoices Coded to Incorrect Account Spreadsheet A 3000003053008 25423574 N | H12: TJM-040425-9 Deferring AP Invoices Coded to Incorrect Account Adjustment | I12: Issue: AP Correction Needed | J12: Mar-25 | K12: -103941.3 | L12: -103941.3 | M12: -103941.3 | N12: USD | O12: USD | P12: Deferring AP Invoices Coded to Incorrect Account X05635750101CMRECLASS | Q12: Journal Import Created | R12: World Wide Technology, LLC (WWT) | S12: Public Sector | T12: Federal | U12: Federal Department of Defense | V12: 101.11004.245011.9999.999.999.9999.9999 | W12: 101 | X12: 11004 | Y12: 245011 | Z12: 9999 | AA12: 999 | AB12: 999 | AC12: 9999 | AD12: 9999 | AE12: Accrued Liabilities - Public Sector | AF12: P010282017 | AG12: - | AH12: CLOUD | AJ12: - | AK12: 45747 | AL12: Spreadsheet | AM12: WWT US Ledger
A13: =TODAY()-AK13 -> 504 | B13: =IFERROR(VLOOKUP(A13,'Aging Formulas'!A:B,2,FALSE),"365+") -> 365+ | D13: Reviewing with Stephanie - Deferring AP Invoices Coded to Incorrect Account | E13: Maggi, Brandon | F13: Federal Army Tactical | G13: TJM-040425-9 Deferring AP Invoices Coded to Incorrect Account Spreadsheet A 3000003053008 25423574 N | H13: TJM-040425-9 Deferring AP Invoices Coded to Incorrect Account Adjustment | I13: Issue: AP Correction Needed | J13: Mar-25 | K13: -20788.26 | L13: -20788.26 | M13: -20788.26 | N13: USD | O13: USD | P13: Deferring AP Invoices Coded to Incorrect Account X05635750101CMRECLASS | Q13: Journal Import Created | R13: World Wide Technology, LLC (WWT) | S13: Public Sector | T13: Federal | U13: Federal Department of Defense | V13: 101.11004.245011.9999.999.999.9999.9999 | W13: 101 | X13: 11004 | Y13: 245011 | Z13: 9999 | AA13: 999 | AB13: 999 | AC13: 9999 | AD13: 9999 | AE13: Accrued Liabilities - Public Sector | AF13: P010282017 | AG13: - | AH13: CLOUD | AJ13: - | AK13: 45747 | AL13: Spreadsheet | AM13: WWT US Ledger
A14: =TODAY()-AK14 -> 443 | B14: =IFERROR(VLOOKUP(A14,'Aging Formulas'!A:B,2,FALSE),"365+") -> 365+ | D14: Reviewing with Stephanie - related to SEWP Fees - Deferred AP invoice - researching | E14: Maggi, Brandon | F14: Federal Army House | G14: TJM-060525-16 Deferring AP Invoice out of May-25 | H14: TJM-060525-16 Deferring AP Invoice out of May-25 | I14: Issue: AP Correction Needed | J14: May-25 | K14: -1293.75 | L14: -1293.75 | M14: -1293.75 | N14: USD | O14: USD | P14: Deferring AP Invoice out of May-25 | Q14: - | R14: World Wide Technology, LLC (WWT) | S14: Public Sector | T14: Federal | U14: Federal Department of Defense | V14: 101.11002.245011.9999.950.999.9999.9999 | W14: 101 | X14: 11002 | Y14: 245011 | Z14: 9999 | AA14: 950 | AB14: 999 | AC14: 9999 | AD14: 9999 | AE14: Accrued Liabilities - Public Sector | AF14: HC108421F0175 | AG14: - | AH14: CLOUD | AJ14: - | AK14: 45808 | AL14: Manual | AM14: WWT US Ledger
A15: =TODAY()-AK15 -> 351 | B15: =IFERROR(VLOOKUP(A15,'Aging Formulas'!A:B,2,FALSE),"365+") -> 331-365 | D15: Deferred billing for Flywheel | E15: Fienup, Mary Frances | F15: Federal Intel | G15: TJM-090525-2 Deferring SO 12262718 On Hold out of Aug-25 Spreadsheet A 300000305300838 28187533 N | H15: TJM-090525-2 Deferring SO 12262718 On Hold out of Aug-25 Adjustment | I15: Timing: Order on Hold | J15: Aug-25 | K15: 143661 | L15: 143661 | M15: 143661 | N15: USD | O15: USD | P15: Deferring SO 12262718 On Hold out of Aug-25 | Q15: Journal Import Created | R15: World Wide Technology, LLC (WWT) | S15: Public Sector | T15: Federal | U15: Federal IC | V15: 101.12012.245011.9999.950.999.9999.9999 | W15: 101 | X15: 12012 | Y15: 245011 | Z15: 9999 | AA15: 950 | AB15: 999 | AC15: 9999 | AD15: 9999 | AE15: Accrued Liabilities - Public Sector | AF15: GDIT-70665 | AG15: - | AH15: CLOUD | AJ15: - | AK15: 45900 | AL15: Spreadsheet | AM15: WWT US Ledger
A16: =TODAY()-AK16 -> 321 | B16: =IFERROR(VLOOKUP(A16,'Aging Formulas'!A:B,2,FALSE),"365+") -> 301-330 | D16: Reviewing with Stephanie - related to SEWP Fees - Deferred AP invoice - researching | E16: Maggi, Brandon | F16: Federal Army House | G16: TJM-100625-4 Defer SO 11730740 Credit Memo out of Sep-25 Spreadsheet A 300000305300838 28776038 N | H16: TJM-100625-4 Defer SO 11730740 Credit Memo out of Sep-25 Adjustment | I16: Issue: AP Correction Needed | J16: Sep-25 | K16: -1293.75 | L16: -1293.75 | M16: -1293.75 | N16: USD | O16: USD | P16: Defer SO 11730740 Credit Memo out of Sep-25 | Q16: Journal Import Created | R16: World Wide Technology, LLC (WWT) | S16: Public Sector | T16: Federal | U16: Federal Department of Defense | V16: 101.11002.245011.9999.999.999.9999.9999 | W16: 101 | X16: 11002 | Y16: 245011 | Z16: 9999 | AA16: 999 | AB16: 999 | AC16: 9999 | AD16: 9999 | AE16: Accrued Liabilities - Public Sector | AF16: PK803151159C1 | AG16: - | AH16: CLOUD | AJ16: - | AK16: 45930 | AL16: Spreadsheet | AM16: WWT US Ledger
A17: =TODAY()-AK17 -> 321 | B17: =IFERROR(VLOOKUP(A17,'Aging Formulas'!A:B,2,FALSE),"365+") -> 301-330 | D17: Reviewing with Stephanie - Deferred SEWP invoice out of Sep-25 | E17: Maggi, Brandon | F17: Federal Army Enterprise | G17: TJM-100625-9 Defer SEWP Invoice 7680755 out of Sep-25 Spreadsheet A 300000305300838 28779212 N | H17: TJM-100625-9 Defer SEWP Invoice 7680755 out of Sep-25 Adjustment | I17: Issue: AR Correction Needed | J17: Sep-25 | K17: 3000 | L17: 3000 | M17: 3000 | N17: USD | O17: USD | P17: Defer SEWP Invoice 7680755 out of Sep-25 | Q17: Journal Import Created | R17: World Wide Technology, LLC (WWT) | S17: Public Sector | T17: Federal | U17: Federal Department of Defense | V17: 101.11003.245011.9999.950.999.9999.9999 | W17: 101 | X17: 11003 | Y17: 245011 | Z17: 9999 | AA17: 950 | AB17: 999 | AC17: 9999 | AD17: 9999 | AE17: Accrued Liabilities - Public Sector | AF17: - | AG17: - | AH17: CLOUD | AJ17: - | AK17: 45930 | AL17: Spreadsheet | AM17: WWT US Ledger
A18: =TODAY()-AK18 -> 290 | B18: =IFERROR(VLOOKUP(A18,'Aging Formulas'!A:B,2,FALSE),"365+") -> 151-300 | D18: Reviewing with Stephanie - related to SEWP Fees - Deferred AP invoice - researching | E18: Maggi, Brandon | F18: Federal Army House | G18: TJM-110625-7 Defer SO 11730740 Credit Memo out of Oct-25 Spreadsheet A 300000305300838 29368027 N | H18: TJM-110625-7 Defer SO 11730740 Credit Memo out of Oct-25 Adjustment | I18: Issue: Needs Research | J18: Oct-25 | K18: -1293.75 | L18: -1293.75 | M18: -1293.75 | N18: USD | O18: USD | P18: Defer SO 11730740 Credit Memo out of Oct-25 | Q18: Journal Import Created | R18: World Wide Technology, LLC (WWT) | S18: Public Sector | T18: Federal | U18: Federal Department of Defense | V18: 101.11002.245011.9999.999.999.9999.9999 | W18: 101 | X18: 11002 | Y18: 245011 | Z18: 9999 | AA18: 999 | AB18: 999 | AC18: 9999 | AD18: 9999 | AE18: Accrued Liabilities - Public Sector | AF18: PK803151159C1 | AG18: - | AH18: CLOUD | AJ18: - | AK18: 45961 | AL18: Spreadsheet | AM18: WWT US Ledger
... A56: =TODAY()-AK56 -> 17 | B56: =IFERROR(VLOOKUP(A56,'Aging Formulas'!A:B,2,FALSE),"365+") -> 0-30 | D56: Prelim Hit SO 12661094 | E56: Maggi, Brandon | F56: Federal Tribal Nations/USPS | G56: TJM-080526-11 Prelim Hit SO 12661094 134651 Spreadsheet A 194905 467018683 EBS OPR A 2711 33929744 N | H56: TJM-080526-11 Prelim Hit SO 12661094 134651 OPR Adjustment USD User 1 OPR Adjustments | I56: Timing: Dropship Prelim Hit | J56: Jul-26 | K56: 9707.1 | L56: 9707.1 | M56: 9707.1 | N56: USD | O56: USD | P56: Prelim Hit SO 12661094 | Q56: Journal Import Created | R56: World Wide Technology, LLC (WWT) | S56: Public Sector | T56: Federal | U56: Federal Civilian | V56: 101.12014.245011.9999.999.999.9999.9999 | W56: 101 | X56: 12014 | Y56: 245011 | Z56: 9999 | AA56: 999 | AB56: 999 | AC56: 9999 | AD56: 9999 | AE56: Accrued Liabilities - Public Sector | AF56: - | AG56: - | AH56: CLOUD | AJ56: - | AK56: 46234 | AL56: EBS OPR | AM56: WWT US Ledger
A57: =TODAY()-AK58 -> 31 | B57: =IFERROR(VLOOKUP(A58,'Aging Formulas'!A:B,2,FALSE),"365+") -> 0-30 | D57: Army GEMSS Billing Adjustment | E57: Maggi, Brandon | F57: Federal Army House | G57: SMS-071626-02 Release partial TJM-070726-5 133130 Recvue A 194322 465450556 EBS Recvue A 33547970 N | H57: SMS-071626-02 Release partial TJM-070726-5 133130 OPR Adjustment USD User 1 OPR Adjustments | I57: Issue: AP Correction Needed | J57: Jul-26 | K57: 2817880.6 | L57: 2817880.6 | M57: 2817880.6 | N57: USD | O57: USD | P57: Release partial TJM-070726-5 | Q57: Journal Import Created | R57: World Wide Technology, LLC (WWT) | S57: Public Sector | T57: Federal | U57: Federal Department of Defense | V57: 101.11002.245011.9999.999.999.9999.9999 | W57: 101 | X57: 11002 | Y57: 245011 | Z57: 9999 | AA57: 999 | AB57: 999 | AC57: 9999 | AD57: 9999 | AE57: Accrued Liabilities - Public Sector | AF57: - | AG57: - | AH57: CLOUD | AJ57: - | AK57: 46219 | AL57: EBS Recvue | AM57: WWT US Ledger
A58: =TODAY()-AK59 -> 17 | B58: =IFERROR(VLOOKUP(A59,'Aging Formulas'!A:B,2,FALSE),"365+") -> 0-30 | D58: Army GEMSS Billing Adjustment | E58: Maggi, Brandon | F58: Federal Army House | G58: SMS-071726-01 Release partial TJM-070726-5 Spreadsheet A 300000276500728 33537921 N | H58: SMS-071726-01 Release partial TJM-070726-5 Adjustment | I58: Issue: Recvue AP Correction Needed | J58: Jul-26 | K58: 2817880.6 | L58: 2817880.6 | M58: 2817880.6 | N58: USD | O58: USD | P58: Release partial TJM-070726-5 | Q58: Release partial TJM-070726-5 | R58: World Wide Technology, LLC (WWT) | S58: Public Sector | T58: Federal | U58: Federal Department of Defense | V58: 101.11002.245011.9999.999.999.9999.9999 | W58: 101 | X58: 11002 | Y58: 245011 | Z58: 9999 | AA58: 999 | AB58: 999 | AC58: 9999 | AD58: 9999 | AE58: Accrued Liabilities - Public Sector | AF58: - | AG58: - | AH58: CLOUD | AJ58: - | AK58: 46220 | AL58: Spreadsheet | AM58: WWT US Ledger
A59: =TODAY()-AK60 -> 17 | B59: =IFERROR(VLOOKUP(A60,'Aging Formulas'!A:B,2,FALSE),"365+") -> 0-30 | D59: Accrue Cisco Credit into Jul-26 | E59: Simms, Amanda | F59: SLED Midwest | G59: TJM-080626-8 Accrue Cisco Credit into Jul-26 104147 Spreadsheet A 195016 467093685 EBS OP 33950343 N | H59: TJM-080626-8 Accrue Cisco Credit into Jul-26 104147 OPR Adjustment USD User 1 OPR Adjustments | I59: Accrual: Dropship | J59: Jul-26 | K59: -366792.2 | L59: -366792.2 | M59: -366792.2 | N59: USD | O59: USD | P59: Accrue Cisco Credit into Jul-26 | Q59: Journal Import Created | R59: World Wide Technology, LLC (WWT) | S59: Public Sector | T59: SLED | U59: SLED East | V59: 101.13006.245011.9999.999.999.9999.9999 | W59: 101 | X59: 13006 | Y59: 245011 | Z59: 9999 | AA59: 999 | AB59: 999 | AC59: 9999 | AD59: 9999 | AE59: Accrued Liabilities - Public Sector | AF59: - | AG59: - | AH59: CLOUD | AJ59: - | AK59: 46234 | AL59: EBS OPR | AM59: WWT US Ledger
A60: =TODAY()-AK61 -> 17 | B60: =IFERROR(VLOOKUP(A61,'Aging Formulas'!A:B,2,FALSE),"365+") -> 0-30 | D60: Reversing Aug-26 - Accrue Buy Down - City of Phoenix | E60: Simms, Amanda | F60: SLED Pacific Southwest | G60: TJM-080626-14 Accrue Buy Down - City of Phoenix 131836 Spreadsheet A 195051 467106395 EBS 33952496 N | H60: TJM-080626-14 Accrue Buy Down - City of Phoenix 131836 OPR Adjustment USD User 1 OPR Adjustments | I60: Accrual: Dropship | J60: Jul-26 | K60: -876000 | L60: -876000 | M60: -876000 | N60: USD | O60: USD | P60: Accrue Buy Down - City of Phoenix | Q60: Journal Import Created | R60: World Wide Technology, LLC (WWT) | S60: Public Sector | T60: SLED | U60: SLED West | V60: 101.13004.245011.9999.999.999.9999.9999 | W60: 101 | X60: 13004 | Y60: 245011 | Z60: 9999 | AA60: 999 | AB60: 999 | AC60: 9999 | AD60: 9999 | AE60: Accrued Liabilities - Public Sector | AF60: - | AG60: - | AH60: CLOUD | AJ60: - | AK60: 46234 | AL60: EBS OPR | AM60: WWT US Ledger
A61: =TODAY()-AK62 -> 17 | B61: =IFERROR(VLOOKUP(A62,'Aging Formulas'!A:B,2,FALSE),"365+") -> 365+ | D61: Average Cost Correction 12909281 | E61: Simms, Amanda | F61: SLED NYC | G61: TJM-080526-21 Average Cost Correction 12909281 05-AUG-2026 16:31:38 EBS OPR A 2720895 33935546 N | H61: TJM-080526-21 Average Cost Correction 12909281 OPR Adjustments | I61: Timing: Average Cost Streamline | J61: Jul-26 | K61: 378766.36 | L61: 378766.36 | M61: 378766.36 | N61: USD | O61: USD | P61: Average Cost Correction 12909281 | Q61: Journal Import Created | R61: World Wide Technology, LLC (WWT) | S61: Public Sector | T61: SLED | U61: SLED East | V61: 101.13018.245011.9999.999.999.9999.9999 | W61: 101 | X61: 13018 | Y61: 245011 | Z61: 9999 | AA61: 999 | AB61: 999 | AC61: 9999 | AD61: 9999 | AE61: Accrued Liabilities - Public Sector | AF61: - | AG61: - | AH61: CLOUD | AJ61: - | AK61: 46234 | AL61: EBS OPR | AM61: WWT US Ledger
A62: =TODAY()-AK63 -> 46251 | B62: =IFERROR(VLOOKUP(A63,'Aging Formulas'!A:B,2,FALSE),"365+") -> 0-30 | D62: Deferred Navy GEMSS Billing | E62: Maggi, Brandon | F62: Federal DoN Tactical | G62: TJM-080526-19 Defer Excess Navy GEMSS Cost out of Jul-26 162306 Recvue A 194974 467030034 33935595 N | H62: TJM-080526-19 Defer Excess Navy GEMSS Cost out of Jul-26 162306 OPR Adjustment USD User 1 OPR Adjus | I62: Issue: AP Correction Needed | J62: Jul-26 | K62: 3897163.4 | L62: 3897163.4 | M62: 3897163.4 | N62: USD | O62: USD | P62: Defer Excess Navy GEMSS Cost out of Jul-26 | Q62: Journal Import Created | R62: World Wide Technology, LLC (WWT) | S62: Public Sector | T62: Federal | U62: Federal Department of Defense | V62: 101.11023.245011.9999.999.999.9999.9999 | W62: 101 | X62: 11023 | Y62: 245011 | Z62: 9999 | AA62: 999 | AB62: 999 | AC62: 9999 | AD62: 9999 | AE62: Accrued Liabilities - Public Sector | AF62: - | AG62: - | AH62: CLOUD | AJ62: - | AK62: 46234 | AL62: EBS Recvue | AM62: WWT US Ledger

Sheet Offsets
J2: =SUBTOTAL(109,J4:J1048576) -> 0 | K2: =SUBTOTAL(109,K4:K1048576) -> 0 | L2: =SUBTOTAL(109,L4:L1048576) -> 0
A3: Age | B3: Aging Bucket | C3: CA Manager Comments | D3: Cost Accountant Comments | E3: P And L Name Curr | F3: Je Batch Name | G3: Je Name | H3: Je Reason Code | I3: Gl Period Name | J3: Entered Amount | K3: Functional Amount | L3: Global Amount | M3: Currency Code Entered | N3: Currency Code Functional | O3: Description Header | P3: Description Line | Q3: Company Name Curr | R3: Financial Program Curr | S3: Sub Program Curr | T3: P And L Rollup Curr | U3: Concatenated Segments | V3: Company Code | W3: P And L Code | X3: Account Code | Y3: Cost Cntr Code | Z3: Gl Location Code | AA3: Gl Intercompany Code | AB3: Future1 Code | AC3: Future2 Code | AD3: Account Name Curr | AE3: WWT Po Number | AF3: WWT Po Description | AG3: WWT Source | AH3: Transaction Date | AI3: Transaction Number | AJ3: Je Effective Date | AK3: Je Source | AL3: Ledger Name
A4: 99 | B4: 91-120 | D4: VA EA Deal | E4: Federal Healthcare | F4: CMG-120622-3 Accrue Nov-22 Portion of Yearly VA EA Invoice PO 3633043 06-DEC-2022 10:21:1 10913179 N | G4: CMG-120622-3 Accrue Nov-22 Portion of Yearly VA EA Invoice PO 3633043 OPR Adjustments | H4: Accrual: Dropship | I4: Nov-22 | J4: -50160.75 | K4: -50160.75 | L4: -50160.75 | M4: USD | N4: USD | O4: Accrue Nov-22 Portion of Yearly VA EA Invoice PO 3633043 | P4: Journal Import Created | Q4: World Wide Technology, LLC (WWT) | R4: Public Sector | S4: Federal | T4: Federal Civilian | U4: 101.11010.245011.9999.999.999.9999.9999 | V4: 101 | W4: 11010 | X4: 245011 | Y4: 9999 | Z4: 999 | AA4: 999 | AB4: 9999 | AC4: 9999 | AD4: Accrued Liabilities - Public Sector | AE4: - | AF4: - | AG4: CLOUD | AI4: - | AJ4: 44895 | AK4: EBS OPR | AL4: WWT US Ledger
A5: 99 | B5: 91-120 | D5: VA EA Deal | E5: Federal Healthcare | F5: CMG-120622-4 Accrue Oct-22 Portion of Yearly VA EA Invoice PO 3633043 06-DEC-2022 10:22:5 10913179 N | G5: CMG-120622-4 Accrue Oct-22 Portion of Yearly VA EA Invoice PO 3633043 OPR Adjustments | H5: Accrual: Dropship | I5: Nov-22 | J5: -50160.75 | K5: -50160.75 | L5: -50160.75 | M5: USD | N5: USD | O5: Accrue Oct-22 Portion of Yearly VA EA Invoice PO 3633043 | P5: Journal Import Created | Q5: World Wide Technology, LLC (WWT) | R5: Public Sector | S5: Federal | T5: Federal Civilian | U5: 101.11010.245011.9999.999.999.9999.9999 | V5: 101 | W5: 11010 | X5: 245011 | Y5: 9999 | Z5: 999 | AA5: 999 | AB5: 9999 | AC5: 9999 | AD5: Accrued Liabilities - Public Sector | AE5: - | AF5: - | AG5: CLOUD | AI5: - | AJ5: 44895 | AK5: EBS OPR | AL5: WWT US Ledger
A6: 68 | B6: 61-90 | D6: VA EA Deal | E6: Federal Healthcare | F6: CMG-010523-10 Accrue Dec-22 Portion of Yearly VA EA Invoice PO 3633043 06-JAN-2023 12:29: 11409092 N | G6: CMG-010523-10 Accrue Dec-22 Portion of Yearly VA EA Invoice PO 3633043 OPR Adjustments | H6: Accrual: Dropship | I6: Dec-22 | J6: -50160.75 | K6: -50160.75 | L6: -50160.75 | M6: USD | N6: USD | O6: Accrue Dec-22 Portion of Yearly VA EA Invoice PO 3633043 | P6: Journal Import Created | Q6: World Wide Technology, LLC (WWT) | R6: Public Sector | S6: Federal | T6: Federal Civilian | U6: 101.11010.245011.9999.999.999.9999.9999 | V6: 101 | W6: 11010 | X6: 245011 | Y6: 9999 | Z6: 999 | AA6: 999 | AB6: 9999 | AC6: 9999 | AD6: Accrued Liabilities - Public Sector | AE6: - | AF6: - | AG6: CLOUD | AI6: - | AJ6: 44926 | AK6: EBS OPR | AL6: WWT US Ledger
A7: 37 | B7: 31-60 | D7: VA EA Deal | E7: Federal Healthcare | F7: CDW-020323-15 Accrue Jan-23 Portion of Yearly VA EA Invoice PO 3633043 03-FEB-2023 15:30: 11896705 N | G7: CDW-020323-15 Accrue Jan-23 Portion of Yearly VA EA Invoice PO 3633043 OPR Adjustments | H7: Accrual: Program Specific Margin Accrual | I7: Jan-23 | J7: -50160.75 | K7: -50160.75 | L7: -50160.75 | M7: USD | N7: USD | O7: Accrue Jan-23 Portion of Yearly VA EA Invoice PO 3633043 | P7: Journal Import Created | Q7: World Wide Technology, LLC (WWT) | R7: Public Sector | S7: Federal | T7: Federal Civilian | U7: 101.11010.245011.9999.999.999.9999.9999 | V7: 101 | W7: 11010 | X7: 245011 | Y7: 9999 | Z7: 999 | AA7: 999 | AB7: 9999 | AC7: 9999 | AD7: Accrued Liabilities - Public Sector | AE7: - | AF7: - | AG7: CLOUD | AI7: - | AJ7: 44957 | AK7: EBS OPR | AL7: WWT US Ledger
A8: 37 | B8: 31-60 | D8: VA EA Deal | E8: Federal Healthcare | F8: CDW-020623-3 Accrue VA EA Jan-23 AP Invoices 06-FEB-2023 08:57:24 EBS OPR A 2417086 11898421 N | G8: CDW-020623-3 Accrue VA EA Jan-23 AP Invoices OPR Adjustments | H8: Accrual: Dropship | I8: Jan-23 | J8: -1446298.1 | K8: -1446298.1 | L8: -1446298.1 | M8: USD | N8: USD | O8: CDW-020623-3 Accrue VA EA Jan-23 AP Invoices | P8: Journal Import Created | Q8: World Wide Technology, LLC (WWT) | R8: Public Sector | S8: Federal | T8: Federal Civilian | U8: 101.11010.245011.9999.999.999.9999.9999 | V8: 101 | W8: 11010 | X8: 245011 | Y8: 9999 | Z8: 999 | AA8: 999 | AB8: 9999 | AC8: 9999 | AD8: Accrued Liabilities - Public Sector | AE8: - | AF8: - | AG8: CLOUD | AI8: - | AJ8: 44957 | AK8: EBS OPR | AL8: WWT US Ledger
A9: 10 | B9: 0-30 | E9: Federal Healthcare | F9: Reverses ""CMG-120622-3 Accrue Nov-22 Portion of Yearly VA EA""27-FEB-23 16:49:57 - 3778448 12237262 N | G9: Reverses ""CMG-120622-3 Accrue Nov-22 Portion of Yearly VA EA Invoice PO 363304327-FEB-2023 16:49:57 | H9: Accrual: Dropship | I9: Feb-23 | J9: 50160.75 | K9: 50160.75 | L9: 50160.75 | M9: USD | N9: USD | O9: Reverses CMG-120622-3 Accrue Nov-22 Portion of Yearly VA EA Invoice PO 3633043 journal entry of CMG-120622-3 Accrue Nov-22 Portion of Yearly VA EA Invoice PO 3633043 06-DEC-2022 10:21:16 batch from NOV-22. | P9: Journal Import Created | Q9: World Wide Technology, LLC (WWT) | R9: Public Sector | S9: Federal | T9: Federal Civilian | U9: 101.11010.245011.9999.999.999.9999.9999 | V9: 101 | W9: 11010 | X9: 245011 | Y9: 9999 | Z9: 999 | AA9: 999 | AB9: 9999 | AC9: 9999 | AD9: Accrued Liabilities - Public Sector | AE9: - | AF9: - | AG9: CLOUD | AI9: - | AJ9: 44984 | AK9: EBS OPR | AL9: WWT US Ledger
A10: 10 | B10: 0-30 | E10: Federal Healthcare | F10: Reverses ""CDW-020623-3 Accrue VA EA Jan-23 AP Invoices""27-FEB-23 16:51:47 - 377844998 EBS 12237262 N | G10: Reverses ""CDW-020623-3 Accrue VA EA Jan-23 AP Invoices""27-FEB-2023 16:51:47 OPR Adjustments | H10: Accrual: Dropship | I10: Feb-23 | J10: 1446298.1 | K10: 1446298.1 | L10: 1446298.1 | M10: USD | N10: USD | O10: Reverses CDW-020623-3 Accrue VA EA Jan-23 AP Invoices journal entry of CDW-020623-3 Accrue VA EA Jan-23 AP Invoices 06-FEB-2023 08:57:24 batch from JAN-23. | P10: Journal Import Created | Q10: World Wide Technology, LLC (WWT) | R10: Public Sector | S10: Federal | T10: Federal Civilian | U10: 101.11010.245011.9999.999.999.9999.9999 | V10: 101 | W10: 11010 | X10: 245011 | Y10: 9999 | Z10: 999 | AA10: 999 | AB10: 9999 | AC10: 9999 | AD10: Accrued Liabilities - Public Sector | AE10: - | AF10: - | AG10: CLOUD | AI10: - | AJ10: 44984 | AK10: EBS OPR | AL10: WWT US Ledger
A11: 10 | B11: 0-30 | E11: Federal Healthcare | F11: Reverses ""CMG-010523-10 Accrue Dec-22 Portion of Yearly VA E""27-FEB-23 16:50:56 - 3778449 12237262 N | G11: Reverses ""CMG-010523-10 Accrue Dec-22 Portion of Yearly VA EA Invoice PO 36330427-FEB-2023 16:50:56 | H11: Accrual: Dropship | I11: Feb-23 | J11: 50160.75 | K11: 50160.75 | L11: 50160.75 | M11: USD | N11: USD | O11: Reverses CMG-010523-10 Accrue Dec-22 Portion of Yearly VA EA Invoice PO 3633043 journal entry of CMG-010523-10 Accrue Dec-22 Portion of Yearly VA EA Invoice PO 3633043 06-JAN-2023 12:29:30 batch from DEC-22. | P11: Journal Import Created | Q11: World Wide Technology, LLC (WWT) | R11: Public Sector | S11: Federal | T11: Federal Civilian | U11: 101.11010.245011.9999.999.999.9999.9999 | V11: 101 | W11: 11010 | X11: 245011 | Y11: 9999 | Z11: 999 | AA11: 999 | AB11: 9999 | AC11: 9999 | AD11: Accrued Liabilities - Public Sector | AE11: - | AF11: - | AG11: CLOUD | AI11: - | AJ11: 44984 | AK11: EBS OPR | AL11: WWT US Ledger
A12: 10 | B12: 0-30 | E12: Federal Healthcare | F12: Reverses ""CDW-020323-15 Accrue Jan-23 Portion of Yearly VA E""27-FEB-23 16:51:16 - 3778449 12237262 N | G12: Reverses ""CDW-020323-15 Accrue Jan-23 Portion of Yearly VA EA Invoice PO 36330427-FEB-2023 16:51:16 | H12: Accrual: Program Specific Margin Accrual | I12: Feb-23 | J12: 50160.75 | K12: 50160.75 | L12: 50160.75 | M12: USD | N12: USD | O12: Reverses CDW-020323-15 Accrue Jan-23 Portion of Yearly VA EA Invoice PO 3633043 journal entry of CDW-020323-15 Accrue Jan-23 Portion of Yearly VA EA Invoice PO 3633043 03-FEB-2023 15:30:36 batch from JAN-23. | P12: Journal Import Created | Q12: World Wide Technology, LLC (WWT) | R12: Public Sector | S12: Federal | T12: Federal Civilian | U12: 101.11010.245011.9999.999.999.9999.9999 | V12: 101 | W12: 11010 | X12: 245011 | Y12: 9999 | Z12: 999 | AA12: 999 | AB12: 9999 | AC12: 9999 | AD12: Accrued Liabilities - Public Sector | AE12: - | AF12: - | AG12: CLOUD | AI12: - | AJ12: 44984 | AK12: EBS OPR | AL12: WWT US Ledger
A13: 10 | B13: 0-30 | E13: Federal Healthcare | F13: Reverses ""CMG-120622-4 Accrue Oct-22 Portion of Yearly VA EA""27-FEB-23 16:50:27 - 3778449 12237262 N | G13: Reverses ""CMG-120622-4 Accrue Oct-22 Portion of Yearly VA EA Invoice PO 363304327-FEB-2023 16:50:27 | H13: Accrual: Dropship | I13: Feb-23 | J13: 50160.75 | K13: 50160.75 | L13: 50160.75 | M13: USD | N13: USD | O13: Reverses CMG-120622-4 Accrue Oct-22 Portion of Yearly VA EA Invoice PO 3633043 journal entry of CMG-120622-4 Accrue Oct-22 Portion of Yearly VA EA Invoice PO 3633043 06-DEC-2022 10:22:58 batch from NOV-22. | P13: Journal Import Created | Q13: World Wide Technology, LLC (WWT) | R13: Public Sector | S13: Federal | T13: Federal Civilian | U13: 101.11010.245011.9999.999.999.9999.9999 | V13: 101 | W13: 11010 | X13: 245011 | Y13: 9999 | Z13: 999 | AA13: 999 | AB13: 9999 | AC13: 9999 | AD13: Accrued Liabilities - Public Sector | AE13: - | AF13: - | AG13: CLOUD | AI13: - | AJ13: 44984 | AK13: EBS OPR | AL13: WWT US Ledger
A14: 160 | B14: 151-180 | D14: Four Points Order on hold - Emailed Dawn 2/13/2023 - Check Cost Rec for reversal 2/17 | E14: Federal Healthcare | F14: CDW-100522-7 SO 10094921 on hold Federal VA - Dick | G14: CDW-100522-7 SO 10094921 on hold Federal VA - Dick | H14: - | I14: Sep-22 | J14: 11429.1 | K14: 11429.1 | L14: 11429.1 | M14: USD | N14: USD | O14: SO 10094921 on hold Federal VA - Dick | P14: SO 10094921 on hold Federal VA - Dick | Q14: World Wide Technology, LLC (WWT) | R14: Public Sector | S14: Federal | T14: Federal Civilian | U14: 101.11010.245011.9999.950.999.9999.9999 | V14: 101 | W14: 11010 | X14: 245011 | Y14: 9999 | Z14: 950 | AA14: 999 | AB14: 9999 | AC14: 9999 | AD14: Accrued Liabilities - Public Sector | AE14: 106360-1 | AF14: - | AG14: CLOUD | AI14: - | AJ14: 44834 | AK14: Manual | AL14: WWT US Ledger
A15: 9 | B15: 0-30 | E15: Federal Healthcare | F15: Reverses CDW-100522-7 SO 10094921 on hold Federal VA - Dick 03-03-23 15:44:35 12311216 | G15: Reverses CDW-100522-7 SO 10094921 on hold Federal VA - Dick 03-03-23 15:44:36 | H15: - | I15: Feb-23 | J15: -11429.1 | K15: -11429.1 | L15: -11429.1 | M15: USD | N15: USD | O15: Reverses journal CDW-100522-7 SO 10094921 on hold Federal VA - Dick of journal batch CDW-100522-7 SO 10094921 on hold Federal VA - Dick from period Sep-22. | P15: SO 10094921 on hold Federal VA - Dick | Q15: World Wide Technology, LLC (WWT) | R15: Public Sector | S15: Federal | T15: Federal Civilian | U15: 101.11010.245011.9999.950.999.9999.9999 | V15: 101 | W15: 11010 | X15: 245011 | Y15: 9999 | Z15: 950 | AA15: 999 | AB15: 9999 | AC15: 9999 | AD15: Accrued Liabilities - Public Sector | AE15: 106360-1 | AF15: - | AG15: CLOUD | AI15: - | AJ15: 44985 | AK15: Manual | AL15: WWT US Ledger
A16: 129 | B16: 121-150 | D16: Four Points Order on hold - Emailed Dawn 2/13/2023 - Check Cost Rec for reversal 2/17 | E16: Federal Healthcare | F16: CDW-110122-25 Order on hold 10094921 | G16: CDW-110122-25 Order on hold 10094921 | H16: - | I16: Oct-22 | J16: 9524.25 | K16: 9524.25 | L16: 9524.25 | M16: USD | N16: USD | O16: CDW-110122-25 Order on hold 10094921 | P16: Order on hold 10094921 | Q16: World Wide Technology, LLC (WWT) | R16: Public Sector | S16: Federal | T16: Federal Civilian | U16: 101.11010.245011.9999.950.999.9999.9999 | V16: 101 | W16: 11010 | X16: 245011 | Y16: 9999 | Z16: 950 | AA16: 999 | AB16: 9999 | AC16: 9999 | AD16: Accrued Liabilities - Public Sector | AE16: 106360-1 | AF16: - | AG16: CLOUD | AI16: - | AJ16: 44865 | AK16: Manual | AL16: WWT US Ledger
A17: 9 | B17: 0-30 | E17: Federal Healthcare | F17: Reverses CDW-110122-25 Order on hold 10094921 03-03-23 15:47:04 12311236 | G17: Reverses CDW-110122-25 Order on hold 10094921 03-03-23 15:47:05 | H17: - | I17: Feb-23 | J17: -9524.25 | K17: -9524.25 | L17: -9524.25 | M17: USD | N17: USD | O17: Reverses journal CDW-110122-25 Order on hold 10094921 of journal batch CDW-110122-25 Order on hold 10094921 from period Oct-22. | P17: Order on hold 10094921 | Q17: World Wide Technology, LLC (WWT) | R17: Public Sector | S17: Federal | T17: Federal Civilian | U17: 101.11010.245011.9999.950.999.9999.9999 | V17: 101 | W17: 11010 | X17: 245011 | Y17: 9999 | Z17: 950 | AA17: 999 | AB17: 9999 | AC17: 9999 | AD17: Accrued Liabilities - Public Sector | AE17: 106360-1 | AF17: - | AG17: CLOUD | AI17: - | AJ17: 44985 | AK17: Manual | AL17: WWT US Ledger
A18: 99 | B18: 91-120 | D18: PO 1CDATA-21-C-0075, to reverse US postal in February | E18: Federal House | F18: JMM-120222-26 Postal Order 172443 Spreadsheet A 150498 371374842 EBS OPR A 747693 10902181 N | G18: JMM-120522-26 Postal Order 172443 OPR Adjustment USD User 1 OPR Adjustments | H18: Timing: Streamline | I18: Nov-22 | J18: 44929.56 | K18: 44929.56 | L18: 44929.56 | M18: USD | N18: USD | O18: Deferring GP until PO 1CDATA-21-C-0075 closes | P18: Journal Import Created | Q18: World Wide Technology, LLC (WWT) | R18: Public Sector | S18: Federal | T18: Federal House | U18: 101.11016.245011.9999.999.999.9999.9999 | V18: 101 | W18: 11016 | X18: 245011 | Y18: 9999 | Z18: 999 | AA18: 999 | AB18: 9999 | AC18: 9999 | AD18: Accrued Liabilities - Public Sector | AE18: - | AF18: - | AG18: CLOUD | AI18: - | AJ18: 44895 | AK18: EBS OPR | AL18: WWT US Ledger
A19: 16 | B19: 0-30 | E19: Federal House | F19: Reverses ""JMM-120522-26 Postal Order 172443 OPR Adjustment U""21-FEB-23 16:03:11 - 3773807 12156923 N | G19: Reverses ""JMM-120522-26 Postal Order 172443 OPR Adjustment USD User 1""21-FEB-2023 16:03:11 OPR Adju | H19: Timing: Streamline | I19: Feb-23 | J19: -44929.56 | K19: -44929.56 | L19: -44929.56 | M19: USD | N19: USD | O19: Reverses JMM-120522-26 Postal Order 172443 OPR Adjustment USD User 1 journal entry of JMM-120222-26 Postal Order 172443 Spreadsheet A 150498 371374842 batch from NOV-22. | P19: Journal Import Created | Q19: World Wide Technology, LLC (WWT) | R19: Public Sector | S19: Federal | T19: Federal House | U19: 101.11016.245011.9999.999.999.9999.9999 | V19: 101 | W19: 11016 | X19: 245011 | Y19: 9999 | Z19: 999 | AA19: 999 | AB19: 9999 | AC19: 9999 | AD19: Accrued Liabilities - Public Sector | AE19: - | AF19: - | AG19: CLOUD | AI19: - | AJ19: 44978 | AK19: EBS OPR | AL19: WWT US Ledger
A20: 37 | B20: 31-60 | D20: Moonshot SAAS RecVue | E20: Federal Intel Moonshot | F20: CDW-020623-12 Accrue RecVue SAAS Cost 06-FEB-2023 15:06:13 EBS OPR A 2419405 11901030 N | G20: CDW-020623-12 Accrue RecVue SAAS Cost OPR Adjustments | H20: Accrual: Dropship | I20: Jan-23 | J20: -1100000 | K20: -1100000 | L20: -1100000 | M20: USD | N20: USD | O20: Accrue RecVue SAAS Cost | P20: Journal Import Created | Q20: World Wide Technology, LLC (WWT) | R20: Public Sector | S20: Federal | T20: Federal Department of Defense | U20: 101.12022.245011.9999.999.999.9999.9999 | V20: 101 | W20: 12022 | X20: 245011 | Y20: 9999 | Z20: 999 | AA20: 999 | AB20: 9999 | AC20: 9999 | AD20: Accrued Liabilities - Public Sector | AE20: - | AF20: - | AG20: CLOUD | AI20: - | AJ20: 44957 | AK20: EBS OPR | AL20: WWT US Ledger
A21: 9 | B21: 0-30 | E21: Federal Intel Moonshot | F21: Reverses ""CDW-020623-12 Accrue RecVue SAAS Cost""06-MAR-23 14:07:13 - 378383974 EBS OPR A 12362749 N | G21: Reverses ""CDW-020623-12 Accrue RecVue SAAS Cost""06-MAR-2023 14:07:13 OPR Adjustments | H21: Accrual: Dropship | I21: Feb-23 | J21: 1100000 | K21: 1100000 | L21: 1100000 | M21: USD | N21: USD | O21: Reverses CDW-020623-12 Accrue RecVue SAAS Cost journal entry of CDW-020623-12 Accrue RecVue SAAS Cost 06-FEB-2023 15:06:13 batch from JAN-23. | P21: Journal Import Created | Q21: World Wide Technology, LLC (WWT) | R21: Public Sector | S21: Federal | T21: Federal Department of Defense | U21: 101.12022.245011.9999.999.999.9999.9999 | V21: 101 | W21: 12022 | X21: 245011 | Y21: 9999 | Z21: 999 | AA21: 999 | AB21: 9999 | AC21: 9999 | AD21: Accrued Liabilities - Public Sector | AE21: - | AF21: - | AG21: CLOUD | AI21: - | AJ21: 44985 | AK21: EBS OPR | AL21: WWT US Ledger
A22: 252 | B22: 241-270 | D22: Timing - Pending Credit - See email for pending Cisco Credit… Descrepancy on amount billed vs credited. Sitting in 24500 code to 50210 6k diff to SC | E22: SLED Central | F22: CMG-070622-12 Defer Replacement Cost Pending Cisco Credit 06-JUL-2022 21:16:01 EBS OPR A 1 8686094 N | G22: CMG-070622-12 Defer Replacement Cost Pending Cisco Credit OPR Adjustments | H22: Issue: AP Correction Needed | I22: Jun-22 | J22: 53552.52 | K22: 53552.52 | L22: 53552.52 | M22: USD | N22: USD | O22: https://quote-system.apps.wwt.com/#/quotes/6071628/versions/2/detail | P22: Journal Import Created | Q22: World Wide Technology, LLC (WWT) | R22: Public Sector | S22: SLED | T22: SLED East | U22: 101.13006.245011.9999.999.999.9999.9999 | V22: 101 | W22: 13006 | X22: 245011 | Y22: 9999 | Z22: 999 | AA22: 999 | AB22: 9999 | AC22: 9999 | AD22: Accrued Liabilities - Public Sector | AE22: - | AF22: - | AG22: CLOUD | AI22: - | AJ22: 44742 | AK22: EBS OPR | AL22: WWT US Ledger
A23: 9 | B23: 0-30 | E23: SLED Central | F23: Reverses ""CMG-070622-12 Defer Replacement Cost Pending Cisco""03-MAR-23 16:47:16 - 3781943 12353576 N | G23: Reverses ""CMG-070622-12 Defer Replacement Cost Pending Cisco Credit""03-MAR-2023 16:47:16 OPR Adjust | H23: Issue: AP Correction Needed | I23: Feb-23 | J23: -53552.52 | K23: -53552.52 | L23: -53552.52 | M23: USD | N23: USD | O23: Reverses CMG-070622-12 Defer Replacement Cost Pending Cisco Credit journal entry of CMG-070622-12 Defer Replacement Cost Pending Cisco Credit 06-JUL-2022 21:16:01 batch from JUN-22. | P23: Journal Import Created | Q23: World Wide Technology, LLC (WWT) | R23: Public Sector | S23: SLED | T23: SLED East | U23: 101.13006.245011.9999.999.999.9999.9999 | V23: 101 | W23: 13006 | X23: 245011 | Y23: 9999 | Z23: 999 | AA23: 999 | AB23: 9999 | AC23: 9999 | AD23: Accrued Liabilities - Public Sector | AE23: - | AF23: - | AG23: CLOUD | AI23: - | AJ23: 44985 | AK23: EBS OPR | AL23: WWT US Ledger
A24: 204 | B24: 181-210 | D24: 1CDATA-21-C-0075 Reclassing streamline balance to correct PL - Should resolve in the next couple months. $374K CR in other BS Account | E24: Federal Citizen Services | F24: Reverses BDM-031522-1 17-08-22 15:04:15 9168774 | G24: Reverses BDM-031522-1 17-08-22 15:04:16 | H24: - | I24: Aug-22 | J24: 543000 | K24: 543000 | L24: 543000 | M24: USD | N24: USD | O24: Reverses journal BDM-031522-1 of journal batch BDM-031522-1 15-MAR-2022 09:28:40 from period Mar-22. | P24: - | Q24: World Wide Technology, LLC (WWT) | R24: Public Sector | S24: Federal | T24: Federal Civilian | U24: 101.12014.245011.9999.999.999.9999.9999 | V24: 101 | W24: 12014 | X24: 245011 | Y24: 9999 | Z24: 999 | AA24: 999 | AB24: 9999 | AC24: 9999 | AD24: Accrued Liabilities - Public Sector | AE24: - | AF24: - | AG24: CLOUD | AI24: - | AJ24: 44790 | AK24: Manual | AL24: WWT US Ledger
A25: 9 | B25: 0-30 | E25: Federal Citizen Services | F25: Reverses ""BDM-120621-4""04-MAR-23 08:32:41 - 378238061 EBS OPR A 3165371 12353576 N | G25: Reverses ""BDM-120621-4""04-MAR-2023 08:32:41 OPR Adjustments | H25: Timing Issue - Recognition Exception | I25: Feb-23 | J25: -543000 | K25: -543000 | L25: -543000 | M25: USD | N25: USD | O25: Reverses BDM-120621-4 journal entry of BDM-120621-4 06-DEC-2021 08:42:36 batch from NOV-21. | P25: Journal Import Created | Q25: World Wide Technology, LLC (WWT) | R25: Public Sector | S25: Federal | T25: Federal Civilian | U25: 101.12014.245011.9999.999.999.9999.9999 | V25: 101 | W25: 12014 | X25: 245011 | Y25: 9999 | Z25: 999 | AA25: 999 | AB25: 9999 | AC25: 9999 | AD25: Accrued Liabilities - Public Sector | AE25: - | AF25: - | AG25: CLOUD | AI25: - | AJ25: 44985 | AK25: EBS OPR | AL25: WWT US Ledger
A26: 73 | B26: 61-90 | D26: Reversed in March Orders on hold - follow up with team 10702660/10702659/10702554/10705836/10702668 | E26: Federal Healthcare | F26: CDW-020323-8 Defer OPS issue Deferred Billing to Timing 03-FEB-2023 11:21:31 EBS OPR A 23 11896705 N | G26: CDW-020323-8 Defer OPS issue Deferred Billing to Timing OPR Adjustments | H26: Issue: Ops Correction Needed - Order Type | I26: Jan-23 | J26: 221281.44 | K26: 221281.44 | L26: 221281.44 | M26: USD | N26: USD | O26: CDW-020323-8 Defer OPS issue Deferred Billing to Timing | P26: Journal Import Created | Q26: World Wide Technology, LLC (WWT) | R26: Public Sector | S26: Federal | T26: Federal Civilian | U26: 101.11010.245011.9999.999.999.9999.9999 | V26: 101 | W26: 11010 | X26: 245011 | Y26: 9999 | Z26: 999 | AA26: 999 | AB26: 9999 | AC26: 9999 | AD26: Accrued Liabilities - Public Sector | AE26: - | AF26: - | AG26: CLOUD | AI26: - | AJ26: 44957 | AK26: EBS OPR | AL26: WWT US Ledger
A27: 45 | B27: 31-60 | D27: Reversed in March VA EA Deal | E27: Federal Healthcare | F27: CMG-030223-4 Accrue VA EA Feb-23 AP Invoices 02-MAR-2023 16:33:18 EBS OPR A 3104533 12295172 N | G27: CMG-030223-4 Accrue VA EA Feb-23 AP Invoices OPR Adjustments | H27: Accrual: Dropship | I27: Feb-23 | J27: -1415877.9 | K27: -1415877.9 | L27: -1415877.9 | M27: USD | N27: USD | O27: Accrue VA EA Feb-23 AP Invoices | P27: Journal Import Created | Q27: World Wide Technology, LLC (WWT) | R27: Public Sector | S27: Federal | T27: Federal Civilian | U27: 101.11010.245011.9999.999.999.9999.9999 | V27: 101 | W27: 11010 | X27: 245011 | Y27: 9999 | Z27: 999 | AA27: 999 | AB27: 9999 | AC27: 9999 | AD27: Accrued Liabilities - Public Sector | AE27: - | AF27: - | AG27: CLOUD | AI27: - | AJ27: 44985 | AK27: EBS OPR | AL27: WWT US Ledger
E28: Federal Healthcare | F28: Reverses ""CDW-020323-8 Defer OPS issue Deferred Billing to T""13-MAR-23 16:46:30 - 3789373 12531556 N | G28: Reverses ""CDW-020323-8 Defer OPS issue Deferred Billing to Timing""13-MAR-2023 16:46:30 OPR Adjustme | H28: Issue: Ops Correction Needed - Order Type | I28: Mar-23 | J28: -221281.44 | K28: -221281.44 | L28: -221281.44 | M28: USD | N28: USD | O28: Reverses CDW-020323-8 Defer OPS issue Deferred Billing to Timing journal entry of CDW-020323-8 Defer OPS issue Deferred Billing to Timing 03-FEB-2023 11:21:31 batch from JAN-23. | P28: Journal Import Created | Q28: World Wide Technology, LLC (WWT) | R28: Public Sector | S28: Federal | T28: Federal Civilian | U28: 101.11010.245011.9999.999.999.9999.9999 | V28: 101 | W28: 11010 | X28: 245011 | Y28: 9999 | Z28: 999 | AA28: 999 | AB28: 9999 | AC28: 9999 | AD28: Accrued Liabilities - Public Sector | AE28: - | AF28: - | AG28: CLOUD | AI28: - | AJ28: 44998 | AK28: EBS OPR | AL28: WWT US Ledger
E29: Federal Healthcare | F29: Reverses ""CMG-030223-4 Accrue VA EA Feb-23 AP Invoices""29-MAR-23 16:58:53 - 380216967 EBS 12758769 N | G29: Reverses ""CMG-030223-4 Accrue VA EA Feb-23 AP Invoices""29-MAR-2023 16:58:53 OPR Adjustments | H29: Accrual: Dropship | I29: Mar-23 | J29: 1415877.9 | K29: 1415877.9 | L29: 1415877.9 | M29: USD | N29: USD | O29: Reverses CMG-030223-4 Accrue VA EA Feb-23 AP Invoices journal entry of CMG-030223-4 Accrue VA EA Feb-23 AP Invoices 02-MAR-2023 16:33:18 batch from FEB-23. | P29: Journal Import Created | Q29: World Wide Technology, LLC (WWT) | R29: Public Sector | S29: Federal | T29: Federal Civilian | U29: 101.11010.245011.9999.999.999.9999.9999 | V29: 101 | W29: 11010 | X29: 245011 | Y29: 9999 | Z29: 999 | AA29: 999 | AB29: 9999 | AC29: 9999 | AD29: Accrued Liabilities - Public Sector | AE29: - | AF29: - | AG29: CLOUD | AI29: - | AJ29: 45014 | AK29: EBS OPR | AL29: WWT US Ledger
A30: 45 | B30: 31-60 | D30: VA EA Consultant Fee | E30: Federal Healthcare | F30: Manual A 155398 378241195 EBS OPR A 3165371 12353576 N | G30: JMM-030423-2 VA Accrual Reverse Mar-23 OPR Adjustment USD User 1 OPR Adjustments | H30: Accrual: Dropship | I30: Feb-23 | J30: -200000 | K30: -200000 | L30: -200000 | M30: USD | N30: USD | O30: Accruing VA consultant fee SO 10781310 | P30: Journal Import Created | Q30: World Wide Technology, LLC (WWT) | R30: Public Sector | S30: Federal | T30: Federal Civilian | U30: 101.11010.245011.9999.999.999.9999.9999 | V30: 101 | W30: 11010 | X30: 245011 | Y30: 9999 | Z30: 999 | AA30: 999 | AB30: 9999 | AC30: 9999 | AD30: Accrued Liabilities - Public Sector | AE30: - | AF30: - | AG30: CLOUD | AI30: - | AJ30: 44985 | AK30: EBS OPR | AL30: WWT US Ledger
E31: Federal Healthcare | F31: Reverses ""JMM-030423-2 VA Accrual Reverse Mar-23 OPR Adjustm""07-MAR-23 09:53:08 - 3784517 12430628 N | G31: Reverses ""JMM-030423-2 VA Accrual Reverse Mar-23 OPR Adjustment USD User 1""07-MAR-2023 09:53:09 OPR | H31: Accrual: Dropship | I31: Mar-23 | J31: 200000 | K31: 200000 | L31: 200000 | M31: USD | N31: USD | O31: Reverses JMM-030423-2 VA Accrual Reverse Mar-23 OPR Adjustment USD User 1 journal entry of Manual A 155398 378241195 batch from FEB-23. | P31: Journal Import Created | Q31: World Wide Technology, LLC (WWT) | R31: Public Sector | S31: Federal | T31: Federal Civilian | U31: 101.11010.245011.9999.999.999.9999.9999 | V31: 101 | W31: 11010 | X31: 245011 | Y31: 9999 | Z31: 999 | AA31: 999 | AB31: 9999 | AC31: 9999 | AD31: Accrued Liabilities - Public Sector | AE31: - | AF31: - | AG31: CLOUD | AI31: - | AJ31: 44992 | AK31: EBS OPR | AL31: WWT US Ledger
A32: 45 | B32: 31-60 | D32: Deferring AP cost hit related to PO 4088227 APINVD0064364 | E32: Federal Air Force | F32: JDP-030623-2 06-MAR-2023 09:00:59 | G32: JDP-030623-2 | H32: - | I32: Feb-23 | J32: 106212.6 | K32: 106212.6 | L32: 106212.6 | M32: USD | N32: USD | O32: Deferring AP cost hit related to PO 4088227 APINVD0064364 | P32: - | Q32: World Wide Technology, LLC (WWT) | R32: Public Sector | S32: Federal | T32: Federal Department of Defense | U32: 101.11001.245011.9999.999.999.9999.9999 | V32: 101 | W32: 11001 | X32: 245011 | Y32: 9999 | Z32: 999 | AA32: 999 | AB32: 9999 | AC32: 9999 | AD32: Accrued Liabilities - Public Sector | AE32: - | AF32: - | AG32: CLOUD | AI32: - | AJ32: 44985 | AK32: Manual | AL32: WWT US Ledger
E33: Federal Air Force | F33: Reverses JDP-030623-2 06-03-23 23:00:10 12349467 | G33: Reverses JDP-030623-2 06-03-23 23:00:11 | H33: - | I33: Mar-23 | J33: -106212.6 | K33: -106212.6 | L33: -106212.6 | M33: USD | N33: USD | O33: Reverses journal JDP-030623-2 of journal batch JDP-030623-2 06-MAR-2023 09:00:59 from period Feb-23. | P33: - | Q33: World Wide Technology, LLC (WWT) | R33: Public Sector | S33: Federal | T33: Federal Department of Defense | U33: 101.11001.245011.9999.999.999.9999.9999 | V33: 101 | W33: 11001 | X33: 245011 | Y33: 9999 | Z33: 999 | AA33: 999 | AB33: 9999 | AC33: 9999 | AD33: Accrued Liabilities - Public Sector | AE33: - | AF33: - | AG33: CLOUD | AI33: - | AJ33: 44991 | AK33: Manual | AL33: WWT US Ledger
A34: 45 | B34: 31-60 | D34: Reversed in March Accruing SO 10716226 | E34: Federal Scientific | F34: Manual A 155397 378240450 EBS OPR A 3165371 12353576 N | G34: JMM-030423-1 USDA CEC FLEX EA Reverse Mar-23 OPR Adjustment USD User 1 OPR Adjustments | H34: Accrual: Dropship | I34: Feb-23 | J34: -1772700 | K34: -1772700 | L34: -1772700 | M34: USD | N34: USD | O34: Accruing SO 10716226 | P34: Journal Import Created | Q34: World Wide Technology, LLC (WWT) | R34: Public Sector | S34: Federal | T34: Federal Civilian | U34: 101.12021.245011.9999.999.999.9999.9999 | V34: 101 | W34: 12021 | X34: 245011 | Y34: 9999 | Z34: 999 | AA34: 999 | AB34: 9999 | AC34: 9999 | AD34: Accrued Liabilities - Public Sector | AE34: - | AF34: - | AG34: CLOUD | AI34: - | AJ34: 44985 | AK34: EBS OPR | AL34: WWT US Ledger
E35: Federal Scientific | F35: Reverses ""JMM-030423-1 USDA CEC FLEX EA Reverse Mar-23 OPR A""07-MAR-23 09:52:28 - 3784516 12430628 N | G35: Reverses ""JMM-030423-1 USDA CEC FLEX EA Reverse Mar-23 OPR Adjustment USD User 07-MAR-2023 09:52:28 | H35: Accrual: Dropship | I35: Mar-23 | J35: 1772700 | K35: 1772700 | L35: 1772700 | M35: USD | N35: USD | O35: Reverses JMM-030423-1 USDA CEC FLEX EA Reverse Mar-23 OPR Adjustment USD User 1 journal entry of Manual A 155397 378240450 batch from FEB-23. | P35: Journal Import Created | Q35: World Wide Technology, LLC (WWT) | R35: Public Sector | S35: Federal | T35: Federal Civilian | U35: 101.12021.245011.9999.999.999.9999.9999 | V35: 101 | W35: 12021 | X35: 245011 | Y35: 9999 | Z35: 999 | AA35: 999 | AB35: 9999 | AC35: 9999 | AD35: Accrued Liabilities - Public Sector | AE35: - | AF35: - | AG35: CLOUD | AI35: - | AJ35: 44992 | AK35: EBS OPR | AL35: WWT US Ledger
E36: SLED Central | F36: Reverses ""CDW-040323-3 Accruing Cost SO 10764155 Drop Ship""04-APR-23 09:48:27 - 380642063 12856347 N | G36: Reverses ""CDW-040323-3 Accruing Cost SO 10764155 Drop Ship""04-APR-2023 09:48:27 OPR Adjustments | H36: Accrual: Dropship | I36: Mar-23 | J36: -45396.3 | K36: -45396.3 | L36: -45396.3 | M36: USD | N36: USD | O36: Reverses CDW-040323-3 Accruing Cost SO 10764155 Drop Ship journal entry of CDW-040323-3 Accruing Cost SO 10764155 Drop Ship 03-APR-2023 14:50:31 batch from MAR-23. | P36: Journal Import Created | Q36: World Wide Technology, LLC (WWT) | R36: Public Sector | S36: SLED | T36: SLED East | U36: 101.13006.245011.9999.999.999.9999.9999 | V36: 101 | W36: 13006 | X36: 245011 | Y36: 9999 | Z36: 999 | AA36: 999 | AB36: 9999 | AC36: 9999 | AD36: Accrued Liabilities - Public Sector | AE36: - | AF36: - | AG36: CLOUD | AI36: - | AJ36: 45016 | AK36: EBS OPR | AL36: WWT US Ledger
E37: SLED Central | F37: CDW-040323-3 Accruing Cost SO 10764155 Drop Ship 03-APR-2023 14:50:31 EBS OPR A 4039700 12835103 N | G37: CDW-040323-3 Accruing Cost SO 10764155 Drop Ship OPR Adjustments | H37: Accrual: Dropship | I37: Mar-23 | J37: 45396.3 | K37: 45396.3 | L37: 45396.3 | M37: USD | N37: USD | O37: Accruing Cost SO 10764155 Drop Ship | P37: Journal Import Created | Q37: World Wide Technology, LLC (WWT) | R37: Public Sector | S37: SLED | T37: SLED East | U37: 101.13006.245011.9999.999.999.9999.9999 | V37: 101 | W37: 13006 | X37: 245011 | Y37: 9999 | Z37: 999 | AA37: 999 | AB37: 9999 | AC37: 9999 | AD37: Accrued Liabilities - Public Sector | AE37: - | AF37: - | AG37: CLOUD | AI37: - | AJ37: 45016 | AK37: EBS OPR | AL37: WWT US Ledger
A38: 45 | B38: 31-60 | D38: Reversed in April - VA EA March AP Invoices | E38: Federal Healthcare | F38: CDW-040523-11 Accrue VA EA Mar-23 AP Invoices 05-APR-2023 15:28:07 EBS OPR A 4123544 12887131 N | G38: CDW-040523-11 Accrue VA EA Mar-23 AP Invoices OPR Adjustments | H38: Accrual: Dropship | I38: Mar-23 | J38: -1415877.9 | K38: -1415877.9 | L38: -1415877.9 | M38: USD | N38: USD | O38: Accrue VA EA Mar-23 AP Invoices | P38: Journal Import Created | Q38: World Wide Technology, LLC (WWT) | R38: Public Sector | S38: Federal | T38: Federal Civilian | U38: 101.11010.245011.9999.999.999.9999.9999 | V38: 101 | W38: 11010 | X38: 245011 | Y38: 9999 | Z38: 999 | AA38: 999 | AB38: 9999 | AC38: 9999 | AD38: Accrued Liabilities - Public Sector | AE38: - | AF38: - | AG38: CLOUD | AI38: - | AJ38: 45016 | AK38: EBS OPR | AL38: WWT US Ledger
A39: 34 | B39: 31-60 | D39: Reversal | E39: Federal Healthcare | F39: Reverses ""CDW-040523-11 Accrue VA EA Mar-23 AP Invoices""11-APR-23 19:32:24 - 381207367 EB 13016761 N | G39: Reverses ""CDW-040523-11 Accrue VA EA Mar-23 AP Invoices""11-APR-2023 19:32:24 OPR Adjustments | H39: Accrual: Dropship | I39: Apr-23 | J39: 1415877.9 | K39: 1415877.9 | L39: 1415877.9 | M39: USD | N39: USD | O39: Reverses CDW-040523-11 Accrue VA EA Mar-23 AP Invoices journal entry of CDW-040523-11 Accrue VA EA Mar-23 AP Invoices 05-APR-2023 15:28:07 batch from MAR-23. | P39: Journal Import Created | Q39: World Wide Technology, LLC (WWT) | R39: Public Sector | S39: Federal | T39: Federal Civilian | U39: 101.11010.245011.9999.999.999.9999.9999 | V39: 101 | W39: 11010 | X39: 245011 | Y39: 9999 | Z39: 999 | AA39: 999 | AB39: 9999 | AC39: 9999 | AD39: Accrued Liabilities - Public Sector | AE39: - | AF39: - | AG39: CLOUD | AH39: - | AI39: - | AJ39: 45027 | AK39: EBS OPR | AL39: WWT US Ledger
A40: 45 | B40: 31-60 | D40: Reversed in April | E40: Federal Healthcare | F40: CDW-040523-1 Defer SO10173798 Ops Issue Needs RMA/RTV 05-APR-2023 11:30:47 EBS OPR A 4123 12887131 N | G40: CDW-040523-1 Defer SO10173798 Ops Issue Needs RMA/RTV OPR Adjustments | H40: Issue: Ops Correction Needed - Order Type | I40: Mar-23 | J40: 456543 | K40: 456543 | L40: 456543 | M40: USD | N40: USD | O40: Defer SO10173798 Ops Issue Needs RMA/RTV | P40: Journal Import Created | Q40: World Wide Technology, LLC (WWT) | R40: Public Sector | S40: Federal | T40: Federal Civilian | U40: 101.11010.245011.9999.999.999.9999.9999 | V40: 101 | W40: 11010 | X40: 245011 | Y40: 9999 | Z40: 999 | AA40: 999 | AB40: 9999 | AC40: 9999 | AD40: Accrued Liabilities - Public Sector | AE40: - | AF40: - | AG40: CLOUD | AI40: - | AJ40: 45016 | AK40: EBS OPR | AL40: WWT US Ledger
A41: 35 | B41: 31-60 | D41: Reversal | E41: Federal Healthcare | F41: Reverses ""CDW-040523-1 Defer SO10173798 Ops Issue Needs RMA/""10-APR-23 09:32:19 - 3810847 13016761 N | G41: Reverses ""CDW-040523-1 Defer SO10173798 Ops Issue Needs RMA/RTV""10-APR-2023 09:32:19 OPR Adjustment | H41: Issue: Ops Correction Needed - Order Type | I41: Apr-23 | J41: -456543 | K41: -456543 | L41: -456543 | M41: USD | N41: USD | O41: Reverses CDW-040523-1 Defer SO10173798 Ops Issue Needs RMA/RTV journal entry of CDW-040523-1 Defer SO10173798 Ops Issue Needs RMA/RTV 05-APR-2023 11:30:47 batch from MAR-23. | P41: Journal Import Created | Q41: World Wide Technology, LLC (WWT) | R41: Public Sector | S41: Federal | T41: Federal Civilian | U41: 101.11010.245011.9999.999.999.9999.9999 | V41: 101 | W41: 11010 | X41: 245011 | Y41: 9999 | Z41: 999 | AA41: 999 | AB41: 9999 | AC41: 9999 | AD41: Accrued Liabilities - Public Sector | AE41: - | AF41: - | AG41: CLOUD | AH41: - | AI41: - | AJ41: 45026 | AK41: EBS OPR | AL41: WWT US Ledger
A42: 45 | B42: 31-60 | D42: Reversed in April | E42: SLED Central | F42: CDW-040423-5 Streamlining SO 10813373 Cost 04-APR-2023 10:35:02 EBS OPR A 4057831 12856347 N | G42: CDW-040423-5 Streamlining SO 10813373 Cost OPR Adjustments | H42: Timing: Streamline | I42: Mar-23 | J42: -96517.01 | K42: -96517.01 | L42: -96517.01 | M42: USD | N42: USD | O42: Streamlining SO 10813373 Cost | P42: Journal Import Created | Q42: World Wide Technology, LLC (WWT) | R42: Public Sector | S42: SLED | T42: SLED East | U42: 101.13006.245011.9999.999.999.9999.9999 | V42: 101 | W42: 13006 | X42: 245011 | Y42: 9999 | Z42: 999 | AA42: 999 | AB42: 9999 | AC42: 9999 | AD42: Accrued Liabilities - Public Sector | AE42: - | AF42: - | AG42: CLOUD | AI42: - | AJ42: 45016 | AK42: EBS OPR | AL42: WWT US Ledger
A43: 35 | B43: 31-60 | D43: Reversal | E43: SLED Central | F43: Reverses ""CDW-040423-5 Streamlining SO 10813373 Cost""10-APR-23 16:04:00 - 381113629 EBS O 13016761 N | G43: Reverses ""CDW-040423-5 Streamlining SO 10813373 Cost""10-APR-2023 16:04:01 OPR Adjustments | H43: Timing: Streamline | I43: Apr-23 | J43: 96517.01 | K43: 96517.01 | L43: 96517.01 | M43: USD | N43: USD | O43: Reverses CDW-040423-5 Streamlining SO 10813373 Cost journal entry of CDW-040423-5 Streamlining SO 10813373 Cost 04-APR-2023 10:35:02 batch from MAR-23. | P43: Journal Import Created | Q43: World Wide Technology, LLC (WWT) | R43: Public Sector | S43: SLED | T43: SLED East | U43: 101.13006.245011.9999.999.999.9999.9999 | V43: 101 | W43: 13006 | X43: 245011 | Y43: 9999 | Z43: 999 | AA43: 999 | AB43: 9999 | AC43: 9999 | AD43: Accrued Liabilities - Public Sector | AE43: - | AF43: - | AG43: CLOUD | AH43: - | AI43: - | AJ43: 45026 | AK43: EBS OPR | AL43: WWT US Ledger
A44: 45 | B44: 31-60 | D44: Streamline P3882300203 SO 10539163 | E44: SLED Central | F44: CDW-040323-2 Releasing portion of PO P3882300203 SO 10539163 03-APR-2023 14:36:32 EBS OPR 12835103 N | G44: CDW-040323-2 Releasing portion of PO P3882300203 SO 10539163 OPR Adjustments | H44: Timing: Streamline | I44: Mar-23 | J44: 60000 | K44: 60000 | L44: 60000 | M44: USD | N44: USD | O44: Releasing portion of PO P3882300203 SO 10539163 | P44: Journal Import Created | Q44: World Wide Technology, LLC (WWT) | R44: Public Sector | S44: SLED | T44: SLED East | U44: 101.13006.245011.9999.999.999.9999.9999 | V44: 101 | W44: 13006 | X44: 245011 | Y44: 9999 | Z44: 999 | AA44: 999 | AB44: 9999 | AC44: 9999 | AD44: Accrued Liabilities - Public Sector | AE44: - | AF44: - | AG44: CLOUD | AI44: - | AJ44: 45016 | AK44: EBS OPR | AL44: WWT US Ledger
A45: 26 | B45: 0-30 | D45: Reversal | E45: SLED Central | F45: Reverses ""CDW-040323-2 Releasing portion of PO P3882300203 S""19-APR-23 16:05:38 - 3818123 13175759 N | G45: Reverses ""CDW-040323-2 Releasing portion of PO P3882300203 SO 10539163""19-APR-2023 16:05:38 OPR Adj | H45: Timing: Streamline | I45: Apr-23 | J45: -60000 | K45: -60000 | L45: -60000 | M45: USD | N45: USD | O45: Reverses CDW-040323-2 Releasing portion of PO P3882300203 SO 10539163 journal entry of CDW-040323-2 Releasing portion of PO P3882300203 SO 10539163 03-APR-2023 14:36:32 batch from MAR-23. | P45: Journal Import Created | Q45: World Wide Technology, LLC (WWT) | R45: Public Sector | S45: SLED | T45: SLED East | U45: 101.13006.245011.9999.999.999.9999.9999 | V45: 101 | W45: 13006 | X45: 245011 | Y45: 9999 | Z45: 999 | AA45: 999 | AB45: 9999 | AC45: 9999 | AD45: Accrued Liabilities - Public Sector | AE45: - | AF45: - | AG45: CLOUD | AH45: - | AI45: - | AJ45: 45035 | AK45: EBS OPR | AL45: WWT US Ledger
A46: 47 | B46: 31-60 | D46: Reverse in April emailed M Hofer about AR inv hitting in March | E46: SLED HI/Comm | F46: CDW-032923-2 Accrue in SO 10358949 Cost 29-MAR-2023 13:57:15 EBS OPR A 3899084 12758769 N | G46: CDW-032923-2 Accrue in SO 10358949 Cost OPR Adjustments | H46: Accrual: Dropship | I46: Mar-23 | J46: -22112.74 | K46: -22112.74 | L46: -22112.74 | M46: USD | N46: USD | O46: Accrue in SO 10358949 Cost | P46: Journal Import Created | Q46: World Wide Technology, LLC (WWT) | R46: Public Sector | S46: SLED | T46: SLED West | U46: 101.13001.245011.9999.999.999.9999.9999 | V46: 101 | W46: 13001 | X46: 245011 | Y46: 9999 | Z46: 999 | AA46: 999 | AB46: 9999 | AC46: 9999 | AD46: Accrued Liabilities - Public Sector | AE46: - | AF46: - | AG46: CLOUD | AI46: - | AJ46: 45014 | AK46: EBS OPR | AL46: WWT US Ledger
A47: 25 | B47: 0-30 | D47: Reversal | E47: SLED HI/Comm | F47: Reverses ""CDW-032923-2 Accrue in SO 10358949 Cost""20-APR-23 11:14:10 - 381874022 EBS OPR 13175759 N | G47: Reverses ""CDW-032923-2 Accrue in SO 10358949 Cost""20-APR-2023 11:14:10 OPR Adjustments | H47: Accrual: Dropship | I47: Apr-23 | J47: 22112.74 | K47: 22112.74 | L47: 22112.74 | M47: USD | N47: USD | O47: Reverses CDW-032923-2 Accrue in SO 10358949 Cost journal entry of CDW-032923-2 Accrue in SO 10358949 Cost 29-MAR-2023 13:57:15 batch from MAR-23. | P47: Journal Import Created | Q47: World Wide Technology, LLC (WWT) | R47: Public Sector | S47: SLED | T47: SLED West | U47: 101.13001.245011.9999.999.999.9999.9999 | V47: 101 | W47: 13001 | X47: 245011 | Y47: 9999 | Z47: 999 | AA47: 999 | AB47: 9999 | AC47: 9999 | AD47: Accrued Liabilities - Public Sector | AE47: - | AF47: - | AG47: CLOUD | AH47: - | AI47: - | AJ47: 45036 | AK47: EBS OPR | AL47: WWT US Ledger
A48: 91 | B48: 91-120 | D48: Reclass between P&L | E48: Federal House | F48: Reverses ""JMM-120522-26 Postal Order 172443 OPR Adjustment U""21-FEB-23 16:03:11 - 3773807 12156923 N | G48: Reverses ""JMM-120522-26 Postal Order 172443 OPR Adjustment USD User 1""21-FEB-2023 16:03:11 OPR Adju | H48: Timing: Streamline | I48: Feb-23 | J48: 575000 | K48: 575000 | L48: 575000 | M48: USD | N48: USD | O48: Reverses JMM-120522-26 Postal Order 172443 OPR Adjustment USD User 1 journal entry of JMM-120222-26 Postal Order 172443 Spreadsheet A 150498 371374842 batch from NOV-22. | P48: Journal Import Created | Q48: World Wide Technology, LLC (WWT) | R48: Public Sector | S48: Federal | T48: Federal House | U48: 101.11016.245011.9999.999.999.9999.9999 | V48: 101 | W48: 11016 | X48: 245011 | Y48: 9999 | Z48: 999 | AA48: 999 | AB48: 9999 | AC48: 9999 | AD48: Accrued Liabilities - Public Sector | AE48: - | AF48: - | AG48: CLOUD | AI48: - | AJ48: 44978 | AK48: EBS OPR | AL48: WWT US Ledger
A49: 35 | B49: 31-60 | D49: Reclass | E49: Federal House | F49: CDW-041823-1 Reclass between P& L's | G49: CDW-041823-1 Reclass between P& L's | H49: Reclass: P&L Move | I49: Apr-23 | J49: -575000 | K49: -575000 | L49: -575000 | M49: USD | N49: USD | O49: Reclass between P& L's | P49: Reclass between P& L's | Q49: World Wide Technology, LLC (WWT) | R49: Public Sector | S49: Federal | T49: Federal House | U49: 101.11016.245011.9999.999.999.9999.9999 | V49: 101 | W49: 11016 | X49: 245011 | Y49: 9999 | Z49: 999 | AA49: 999 | AB49: 9999 | AC49: 9999 | AD49: Accrued Liabilities - Public Sector | AE49: - | AF49: - | AG49: CLOUD | AH49: - | AI49: - | AJ49: 45034 | AK49: Manual | AL49: WWT US Ledger
A50: 91 | B50: 91-120 | D50: Reclass between P&L | E50: Federal Citizen Services | F50: Reverses ""JMM-120522-26 Postal Order 172443 OPR Adjustment U""21-FEB-23 16:03:11 - 3773807 12156923 N | G50: Reverses ""JMM-120522-26 Postal Order 172443 OPR Adjustment USD User 1""21-FEB-2023 16:03:11 OPR Adju | H50: Timing: Streamline | I50: Feb-23 | J50: -575000 | K50: -575000 | L50: -575000 | M50: USD | N50: USD | O50: Reverses JMM-120522-26 Postal Order 172443 OPR Adjustment USD User 1 journal entry of JMM-120222-26 Postal Order 172443 Spreadsheet A 150498 371374842 batch from NOV-22. | P50: Journal Import Created | Q50: World Wide Technology, LLC (WWT) | R50: Public Sector | S50: Federal | T50: Federal Civilian | U50: 101.12014.245011.9999.999.999.9999.9999 | V50: 101 | W50: 12014 | X50: 245011 | Y50: 9999 | Z50: 999 | AA50: 999 | AB50: 9999 | AC50: 9999 | AD50: Accrued Liabilities - Public Sector | AE50: - | AF50: - | AG50: CLOUD | AI50: - | AJ50: 44978 | AK50: EBS OPR | AL50: WWT US Ledger
A51: 35 | B51: 31-60 | D51: Reclass | E51: Federal Citizen Services | F51: CDW-041823-1 Reclass between P& L's | G51: CDW-041823-1 Reclass between P& L's | H51: Reclass: P&L Move | I51: Apr-23 | J51: 575000 | K51: 575000 | L51: 575000 | M51: USD | N51: USD | O51: Reclass between P& L's | P51: Reclass between P& L's | Q51: World Wide Technology, LLC (WWT) | R51: Public Sector | S51: Federal | T51: Federal Civilian | U51: 101.12014.245011.9999.999.999.9999.9999 | V51: 101 | W51: 12014 | X51: 245011 | Y51: 9999 | Z51: 999 | AA51: 999 | AB51: 9999 | AC51: 9999 | AD51: Accrued Liabilities - Public Sector | AE51: - | AF51: - | AG51: CLOUD | AH51: - | AI51: - | AJ51: 45034 | AK51: Manual | AL51: WWT US Ledger
A52: 68 | B52: 61-90 | D52: Reclass to AR other account offsets | E52: Federal USACE | F52: JMM-031623-2 Spreadsheet A 300000031755431 12529088 N | G52: JMM-031623-2 Adjustment | H52: - | I52: Mar-23 | J52: -4784.22 | K52: -4784.22 | L52: -4784.22 | M52: USD | N52: USD | O52: Reclassing JMM-022723-24/Deferring SO on hold 2209775 | P52: Journal Import Created | Q52: World Wide Technology, LLC (WWT) | R52: Public Sector | S52: Federal | T52: Federal Department of Defense | U52: 101.12016.245011.9999.950.999.9999.9999 | V52: 101 | W52: 12016 | X52: 245011 | Y52: 9999 | Z52: 950 | AA52: 999 | AB52: 9999 | AC52: 9999 | AD52: Accrued Liabilities - Public Sector | AE52: - | AF52: - | AG52: CLOUD | AI52: - | AJ52: 45001 | AK52: Spreadsheet | AL52: WWT US Ledger
A53: 68 | B53: 61-90 | D53: RMA on hold - Reclass to AR other account | E53: Federal USACE | F53: JMM-031623-1 Spreadsheet A 300000031755431 12529088 N | G53: JMM-031623-1 Adjustment | H53: - | I53: Mar-23 | J53: -1238.14 | K53: -1238.14 | L53: -1238.14 | M53: USD | N53: USD | O53: Reclassing JMM-022723-25/Deferring SO on hold 2209779 | P53: Journal Import Created | Q53: World Wide Technology, LLC (WWT) | R53: Public Sector | S53: Federal | T53: Federal Department of Defense | U53: 101.12016.245011.9999.950.999.9999.9999 | V53: 101 | W53: 12016 | X53: 245011 | Y53: 9999 | Z53: 950 | AA53: 999 | AB53: 9999 | AC53: 9999 | AD53: Accrued Liabilities - Public Sector | AE53: - | AF53: - | AG53: CLOUD | AI53: - | AJ53: 45001 | AK53: Spreadsheet | AL53: WWT US Ledger
A54: 35 | B54: 31-60 | D54: Reclass | E54: Federal USACE | F54: CDW-041823-2 Reclass Accounts to AR other | G54: CDW-041823-2 Reclass Accounts to AR other | H54: Reclass: Account Move | I54: Apr-23 | J54: 4784.22 | K54: 4784.22 | L54: 4784.22 | M54: USD | N54: USD | O54: Reclass Accounts to AR other | P54: Reclass Accounts to AR other | Q54: World Wide Technology, LLC (WWT) | R54: Public Sector | S54: Federal | T54: Federal Department of Defense | U54: 101.12016.245011.9999.950.999.9999.9999 | V54: 101 | W54: 12016 | X54: 245011 | Y54: 9999 | Z54: 950 | AA54: 999 | AB54: 9999 | AC54: 9999 | AD54: Accrued Liabilities - Public Sector | AE54: W9127S22F0135 | AF54: - | AG54: CLOUD | AH54: - | AI54: - | AJ54: 45034 | AK54: Manual | AL54: WWT US Ledger
A55: 35 | B55: 31-60 | D55: Reclass | E55: Federal USACE | F55: CDW-041823-3 Reclass Account to AR Other SO 2209779 | G55: CDW-041823-3 Reclass Account to AR Other SO 2209779 | H55: Reclass: Account Move | I55: Apr-23 | J55: 1238.14 | K55: 1238.14 | L55: 1238.14 | M55: USD | N55: USD | O55: Reclass Account to AR Other SO 2209779 | P55: Reclass Account to AR Other SO 2209779 | Q55: World Wide Technology, LLC (WWT) | R55: Public Sector | S55: Federal | T55: Federal Department of Defense | U55: 101.12016.245011.9999.950.999.9999.9999 | V55: 101 | W55: 12016 | X55: 245011 | Y55: 9999 | Z55: 950 | AA55: 999 | AB55: 9999 | AC55: 9999 | AD55: Accrued Liabilities - Public Sector | AE55: P010267288 | AF55: - | AG55: CLOUD | AH55: - | AI55: - | AJ55: 45034 | AK55: Manual | AL55: WWT US Ledger
A56: 44 | B56: 31-60 | D56: Reversed in May Accrual | E56: Federal Intel | F56: CDW-050123-7 Flywheel funding SO 10845844 01-MAY-2023 15:55:26 EBS OPR A 4755965 13294942 N | G56: CDW-050123-7 Flywheel funding SO 10845844 OPR Adjustments | H56: Accrual: Dropship | I56: Apr-23 | J56: -25000 | K56: -25000 | L56: -25000 | M56: USD | N56: USD | O56: Flywheel funding SO 10845844 | P56: Journal Import Created | Q56: World Wide Technology, LLC (WWT) | R56: Public Sector | S56: Federal | T56: Federal Department of Defense | U56: 101.12012.245011.9999.999.999.9999.9999 | V56: 101 | W56: 12012 | X56: 245011 | Y56: 9999 | Z56: 999 | AA56: 999 | AB56: 9999 | AC56: 9999 | AD56: Accrued Liabilities - Public Sector | AE56: - | AF56: - | AG56: CLOUD | AH56: - | AI56: - | AJ56: 45046 | AK56: EBS OPR | AL56: WWT US Ledger
A57: 28 | B57: 0-30 | E57: Federal Intel | F57: Reverses ""CDW-050123-7 Flywheel funding SO 10845844""16-MAY-23 07:29:42 - 383812001 EBS OP 13649717 N | G57: Reverses ""CDW-050123-7 Flywheel funding SO 10845844""16-MAY-2023 07:29:42 OPR Adjustments | H57: Accrual: Dropship | I57: 45069 | J57: 25000 | K57: 25000 | L57: 25000 | M57: USD | N57: USD | O57: Reverses CDW-050123-7 Flywheel funding SO 10845844 journal entry of CDW-050123-7 Flywheel funding SO 10845844 01-MAY-2023 15:55:26 batch from APR-23. | P57: Journal Import Created | Q57: World Wide Technology, LLC (WWT) | R57: Public Sector | S57: Federal | T57: Federal Department of Defense | U57: 101.12012.245011.9999.999.999.9999.9999 | V57: 101 | W57: 12012 | X57: 245011 | Y57: 9999 | Z57: 999 | AA57: 999 | AB57: 9999 | AC57: 9999 | AD57: Accrued Liabilities - Public Sector | AE57: - | AF57: - | AG57: CLOUD | AH57: - | AI57: - | AJ57: 45062 | AK57: EBS OPR | AL57: WWT US Ledger
A58: 44 | B58: 31-60 | D58: Reversed in May Accrual | E58: SLED Central | F58: CDW-050223-1 Accruing SAAS Cost WWTINCSAAS159 02-MAY-2023 09:57:25 EBS OPR A 4778592 13313526 N | G58: CDW-050223-1 Accruing SAAS Cost WWTINCSAAS159 OPR Adjustments | H58: Issue: AP Correction Needed | I58: Apr-23 | J58: -50226 | K58: -50226 | L58: -50226 | M58: USD | N58: USD | O58: Accruing SAAS Cost WWTINCSAAS159 | P58: Journal Import Created | Q58: World Wide Technology, LLC (WWT) | R58: Public Sector | S58: SLED | T58: SLED East | U58: 101.13006.245011.9999.999.999.9999.9999 | V58: 101 | W58: 13006 | X58: 245011 | Y58: 9999 | Z58: 999 | AA58: 999 | AB58: 9999 | AC58: 9999 | AD58: Accrued Liabilities - Public Sector | AE58: - | AF58: - | AG58: CLOUD | AH58: - | AI58: - | AJ58: 45046 | AK58: EBS OPR | AL58: WWT US Ledger
A59: 28 | B59: 0-30 | E59: SLED Central | F59: Reverses ""CDW-050223-1 Accruing SAAS Cost WWTINCSAAS159""16-MAY-23 12:43:19 - 383835303 EB 13649717 N | G59: Reverses ""CDW-050223-1 Accruing SAAS Cost WWTINCSAAS159""16-MAY-2023 12:43:19 OPR Adjustments | H59: Issue: AP Correction Needed | I59: 45069 | J59: 50226 | K59: 50226 | L59: 50226 | M59: USD | N59: USD | O59: Reverses CDW-050223-1 Accruing SAAS Cost WWTINCSAAS159 journal entry of CDW-050223-1 Accruing SAAS Cost WWTINCSAAS159 02-MAY-2023 09:57:25 batch from APR-23. | P59: Journal Import Created | Q59: World Wide Technology, LLC (WWT) | R59: Public Sector | S59: SLED | T59: SLED East | U59: 101.13006.245011.9999.999.999.9999.9999 | V59: 101 | W59: 13006 | X59: 245011 | Y59: 9999 | Z59: 999 | AA59: 999 | AB59: 9999 | AC59: 9999 | AD59: Accrued Liabilities - Public Sector | AE59: - | AF59: - | AG59: CLOUD | AH59: - | AI59: - | AJ59: 45062 | AK59: EBS OPR | AL59: WWT US Ledger
A60: 92 | B60: 91-120 | D60: Streamline P3882300203 SO 10539163 | E60: SLED Central | F60: MPA-031323-5 MO OA - ITSD Office of Admin Streamline Adj FEB-23 Reclass | G60: MPA-031323-5 MO OA - ITSD Office of Admin Streamline Adj FEB-23 Reclass | H60: - | I60: Mar-23 | J60: -96764.26 | K60: -96764.26 | L60: -96764.26 | M60: USD | N60: USD | O60: Reclassing FEB-23 Adj to Correct Liability Acct // Streamline P3882300203 SO10539163 to 9%GP | P60: - | Q60: World Wide Technology, LLC (WWT) | R60: Public Sector | S60: SLED | T60: SLED East | U60: 101.13006.245011.9999.999.999.9999.9999 | V60: 101 | W60: 13006 | X60: 245011 | Y60: 9999 | Z60: 999 | AA60: 999 | AB60: 9999 | AC60: 9999 | AD60: Accrued Liabilities - Public Sector | AE60: - | AF60: - | AG60: CLOUD | AI60: - | AJ60: 44998 | AK60: Manual | AL60: WWT US Ledger
A61: 13 | B61: 0-30 | E61: SLED Central | F61: MPA-060223-12 | G61: MPA-060223-12 | H61: Timing: Streamline | I61: 45069 | J61: 96764.26 | K61: 96764.26 | L61: 96764.26 | M61: USD | N61: USD | O61: Reclass SLED Streamline Reversal to Correct Acct | P61: - | Q61: World Wide Technology, LLC (WWT) | R61: Public Sector | S61: SLED | T61: SLED East | U61: 101.13006.245011.9999.999.999.9999.9999 | V61: 101 | W61: 13006 | X61: 245011 | Y61: 9999 | Z61: 999 | AA61: 999 | AB61: 9999 | AC61: 9999 | AD61: Accrued Liabilities - Public Sector | AE61: - | AF61: - | AG61: CLOUD | AH61: - | AI61: - | AJ61: 45077 | AK61: Manual | AL61: WWT US Ledger
A62: 44 | B62: 31-60 | D62: Reversed in May Accrual AP moonshot Invoice - Emailed 5/23 | E62: Federal Intel Moonshot | F62: CDW-050423-2 Accruing AP Inv 005196 to Moonshot 04-MAY-2023 12:05:52 EBS OPR A 4852273 13366499 N | G62: CDW-050423-2 Accruing AP Inv 005196 to Moonshot OPR Adjustments | H62: Accrual: Dropship | I62: Apr-23 | J62: -268104.01 | K62: -268104.01 | L62: -268104.01 | M62: USD | N62: USD | O62: Accruing AP Inv 005196 to Moonshot | P62: Journal Import Created | Q62: World Wide Technology, LLC (WWT) | R62: Public Sector | S62: Federal | T62: Federal Department of Defense | U62: 101.12022.245011.9999.999.999.9999.9999 | V62: 101 | W62: 12022 | X62: 245011 | Y62: 9999 | Z62: 999 | AA62: 999 | AB62: 9999 | AC62: 9999 | AD62: Accrued Liabilities - Public Sector | AE62: - | AF62: - | AG62: CLOUD | AH62: - | AI62: - | AJ62: 45046 | AK62: EBS OPR | AL62: WWT US Ledger
A63: 13 | B63: 0-30 | E63: Federal Intel Moonshot | F63: Reverses ""CDW-050423-2 Accruing AP Inv 005196 to Moonshot""01-JUN-23 10:50:10 - 385005396 13900848 N | G63: Reverses ""CDW-050423-2 Accruing AP Inv 005196 to Moonshot""01-JUN-2023 10:50:10 OPR Adjustments | H63: Accrual: Dropship | I63: 45069 | J63: 268104.01 | K63: 268104.01 | L63: 268104.01 | M63: USD | N63: USD | O63: Reverses CDW-050423-2 Accruing AP Inv 005196 to Moonshot journal entry of CDW-050423-2 Accruing AP Inv 005196 to Moonshot 04-MAY-2023 12:05:52 batch from APR-23. | P63: Journal Import Created | Q63: World Wide Technology, LLC (WWT) | R63: Public Sector | S63: Federal | T63: Federal Department of Defense | U63: 101.12022.245011.9999.999.999.9999.9999 | V63: 101 | W63: 12022 | X63: 245011 | Y63: 9999 | Z63: 999 | AA63: 999 | AB63: 9999 | AC63: 9999 | AD63: Accrued Liabilities - Public Sector | AE63: - | AF63: - | AG63: CLOUD | AH63: - | AI63: - | AJ63: 45077 | AK63: EBS OPR | AL63: WWT US Ledger
A64: 44 | B64: 31-60 | D64: Reversed in May Accrual | E64: Federal COCOMs | F64: CDW-050223-9 Accruing Cost SO 10297785 02-MAY-2023 11:03:52 EBS OPR A 4778592 13313526 N | G64: CDW-050223-9 Accruing Cost SO 10297785 OPR Adjustments | H64: Accrual: Dropship | I64: Apr-23 | J64: -303524.08 | K64: -303524.08 | L64: -303524.08 | M64: USD | N64: USD | O64: Accruing Cost SO 10297785 | P64: Journal Import Created | Q64: World Wide Technology, LLC (WWT) | R64: Public Sector | S64: Federal | T64: Federal Department of Defense | U64: 101.12015.245011.9999.999.999.9999.9999 | V64: 101 | W64: 12015 | X64: 245011 | Y64: 9999 | Z64: 999 | AA64: 999 | AB64: 9999 | AC64: 9999 | AD64: Accrued Liabilities - Public Sector | AE64: - | AF64: - | AG64: CLOUD | AH64: - | AI64: - | AJ64: 45046 | AK64: EBS OPR | AL64: WWT US Ledger
A65: 28 | B65: 0-30 | E65: Federal COCOMs | F65: Reverses ""CDW-050223-9 Accruing Cost SO 10297785""16-MAY-23 12:40:04 - 383835131 EBS OPR A 13649717 N | G65: Reverses ""CDW-050223-9 Accruing Cost SO 10297785""16-MAY-2023 12:40:04 OPR Adjustments | H65: Accrual: Dropship | I65: 45069 | J65: 303524.08 | K65: 303524.08 | L65: 303524.08 | M65: USD | N65: USD | O65: Reverses CDW-050223-9 Accruing Cost SO 10297785 journal entry of CDW-050223-9 Accruing Cost SO 10297785 02-MAY-2023 11:03:52 batch from APR-23. | P65: Journal Import Created | Q65: World Wide Technology, LLC (WWT) | R65: Public Sector | S65: Federal | T65: Federal Department of Defense | U65: 101.12015.245011.9999.999.999.9999.9999 | V65: 101 | W65: 12015 | X65: 245011 | Y65: 9999 | Z65: 999 | AA65: 999 | AB65: 9999 | AC65: 9999 | AD65: Accrued Liabilities - Public Sector | AE65: - | AF65: - | AG65: CLOUD | AH65: - | AI65: - | AJ65: 45062 | AK65: EBS OPR | AL65: WWT US Ledger
A66: 40 | B66: 31-60 | D66: Awaiting fufillment, follow up with Dawn - Reversed in June | E66: Federal Healthcare | F66: CDW-060623-2 Defer SO 9834148 Ops issue Awaiting Fulfillment Reverse in June | G66: CDW-060623-2 Defer SO 9834148 Ops issue Awaiting Fulfillment Reverse in June | H66: Issue: Needs Research | I66: 45069 | J66: 18800 | K66: 18800 | L66: 18800 | M66: USD | N66: USD | O66: Defer SO 9834148 Ops issue Awaiting Fulfillment Reverse in June | P66: Defer SO 9834148 Ops issue Awaiting Fulfillment Reverse in June | Q66: World Wide Technology, LLC (WWT) | R66: Public Sector | S66: Federal | T66: Federal Civilian | U66: 101.11010.245011.9999.950.999.9999.9999 | V66: 101 | W66: 11010 | X66: 245011 | Y66: 9999 | Z66: 950 | AA66: 999 | AB66: 9999 | AC66: 9999 | AD66: Accrued Liabilities - Public Sector | AE66: HT001521F0143 | AF66: - | AG66: CLOUD | AH66: - | AI66: - | AJ66: 45077 | AK66: Manual | AL66: WWT US Ledger
A67: 34 | B67: 31-60 | E67: Federal Healthcare | F67: Reverses CDW-060623-2 Defer SO 9834148 Ops issue Awaiting Ful 06-06-23 16:31:11 13980092 | G67: Reverses CDW-060623-2 Defer SO 9834148 Ops issue Awaiting Fulfillment Reverse in 06-06-23 16:31:12 | H67: Issue: Needs Research | I67: Jun-23 | J67: -18800 | K67: -18800 | L67: -18800 | M67: USD | N67: USD | O67: Reverses journal CDW-060623-2 Defer SO 9834148 Ops issue Awaiting Fulfillment Reverse in June of journal batch CDW-060623-2 Defer SO 9834148 Ops issue Awaiting Fulfillment Reverse in June from period May-23. | P67: Defer SO 9834148 Ops issue Awaiting Fulfillment Reverse in June | Q67: World Wide Technology, LLC (WWT) | R67: Public Sector | S67: Federal | T67: Federal Civilian | U67: 101.11010.245011.9999.950.999.9999.9999 | V67: 101 | W67: 11010 | X67: 245011 | Y67: 9999 | Z67: 950 | AA67: 999 | AB67: 9999 | AC67: 9999 | AD67: Accrued Liabilities - Public Sector | AE67: HT001521F0143 | AF67: - | AG67: CLOUD | AI67: - | AJ67: 45083 | AK67: Manual | AL67: WWT US Ledger
A68: 101 | B68: 91-120 | D68: Defer Federal Health WWTINCSAAS924, PO 22P09282 | E68: Federal Healthcare | F68: CDW-040623-4 Defer VA EA Cost WWTINCSAAS1177 06-APR-2023 12:37:06 EBS OPR A 4133055 12891247 N | G68: CDW-040623-4 Defer VA EA Cost WWTINCSAAS1177 OPR Adjustments | H68: Issue: AP Correction Needed | I68: Mar-23 | J68: 270985 | K68: 270985 | L68: 270985 | M68: USD | N68: USD | O68: Defer VA EA Cost WWTINCSAAS1177 | P68: Journal Import Created | Q68: World Wide Technology, LLC (WWT) | R68: Public Sector | S68: Federal | T68: Federal Civilian | U68: 101.11010.245011.9999.999.999.9999.9999 | V68: 101 | W68: 11010 | X68: 245011 | Y68: 9999 | Z68: 999 | AA68: 999 | AB68: 9999 | AC68: 9999 | AD68: Accrued Liabilities - Public Sector | AE68: - | AF68: - | AG68: CLOUD | AI68: - | AJ68: 45016 | AK68: EBS OPR | AL68: WWT US Ledger
A69: 71 | B69: 61-90 | D69: Reversing portion of VA EA related cost | E69: Federal Healthcare | F69: CDW-050323-11 Releasing VA EA cost from timing 03-MAY-2023 15:27:11 EBS OPR A 4822727 13337477 N | G69: CDW-050323-11 Releasing VA EA cost from timing OPR Adjustments | H69: Issue: AP Correction Needed | I69: Apr-23 | J69: -171249.44 | K69: -171249.44 | L69: -171249.44 | M69: USD | N69: USD | O69: Releasing VA EA cost from timing | P69: Journal Import Created | Q69: World Wide Technology, LLC (WWT) | R69: Public Sector | S69: Federal | T69: Federal Civilian | U69: 101.11010.245011.9999.999.999.9999.9999 | V69: 101 | W69: 11010 | X69: 245011 | Y69: 9999 | Z69: 999 | AA69: 999 | AB69: 9999 | AC69: 9999 | AD69: Accrued Liabilities - Public Sector | AE69: - | AF69: - | AG69: CLOUD | AH69: - | AI69: - | AJ69: 45046 | AK69: EBS OPR | AL69: WWT US Ledger
A70: 40 | B70: 31-60 | D70: Reversing portion of VA EA related cost | E70: Federal Healthcare | F70: CDW-060523-15 Releasing VA EA cost from timing 05-JUN-2023 14:18:19 EBS OPR A 5827140 13964957 N | G70: CDW-060523-15 Releasing VA EA cost from timing OPR Adjustments | H70: Issue: AP Correction Needed | I70: 45069 | J70: -198767.21 | K70: -198767.21 | L70: -198767.21 | M70: USD | N70: USD | O70: Releasing VA EA cost from timing | P70: Journal Import Created | Q70: World Wide Technology, LLC (WWT) | R70: Public Sector | S70: Federal | T70: Federal Civilian | U70: 101.11010.245011.9999.999.999.9999.9999 | V70: 101 | W70: 11010 | X70: 245011 | Y70: 9999 | Z70: 999 | AA70: 999 | AB70: 9999 | AC70: 9999 | AD70: Accrued Liabilities - Public Sector | AE70: - | AF70: - | AG70: CLOUD | AH70: - | AI70: - | AJ70: 45077 | AK70: EBS OPR | AL70: WWT US Ledger
A71: 10 | B71: 0-30 | E71: Federal Healthcare | F71: Reverses "CDW-040623-4 Defer VA EA Cost WWTINCSAAS1177"06-JUL-23 14:09:04 - 387625398 EBS 14497649 N | G71: Reverses "CDW-040623-4 Defer VA EA Cost WWTINCSAAS1177"06-JUL-2023 14:09:05 OPR Adjustments | H71: Issue: AP Correction Needed | I71: Jun-23 | J71: -270985 | K71: -270985 | L71: -270985 | M71: USD | N71: USD | O71: Reverses CDW-040623-4 Defer VA EA Cost WWTINCSAAS1177 journal entry of CDW-040623-4 Defer VA EA Cost WWTINCSAAS1177 06-APR-2023 12:37:06 batch from MAR-23. | P71: Journal Import Created | Q71: World Wide Technology, LLC (WWT) | R71: Public Sector | S71: Federal | T71: Federal Civilian | U71: 101.11010.245011.9999.999.999.9999.9999 | V71: 101 | W71: 11010 | X71: 245011 | Y71: 9999 | Z71: 999 | AA71: 999 | AB71: 9999 | AC71: 9999 | AD71: Accrued Liabilities - Public Sector | AE71: - | AF71: - | AG71: CLOUD | AI71: - | AJ71: 45107 | AK71: EBS OPR | AL71: WWT US Ledger
A72: 10 | B72: 0-30 | E72: Federal Healthcare | F72: Reverses "CDW-060523-15 Releasing VA EA cost from timing"06-JUL-23 14:10:37 - 387625543 E 14497649 N | G72: Reverses "CDW-060523-15 Releasing VA EA cost from timing"06-JUL-2023 14:10:37 OPR Adjustments | H72: Issue: AP Correction Needed | I72: Jun-23 | J72: 198767.21 | K72: 198767.21 | L72: 198767.21 | M72: USD | N72: USD | O72: Reverses CDW-060523-15 Releasing VA EA cost from timing journal entry of CDW-060523-15 Releasing VA EA cost from timing 05-JUN-2023 14:18:19 batch from MAY-23. | P72: Journal Import Created | Q72: World Wide Technology, LLC (WWT) | R72: Public Sector | S72: Federal | T72: Federal Civilian | U72: 101.11010.245011.9999.999.999.9999.9999 | V72: 101 | W72: 11010 | X72: 245011 | Y72: 9999 | Z72: 999 | AA72: 999 | AB72: 9999 | AC72: 9999 | AD72: Accrued Liabilities - Public Sector | AE72: - | AF72: - | AG72: CLOUD | AI72: - | AJ72: 45107 | AK72: EBS OPR | AL72: WWT US Ledger
A73: 10 | B73: 0-30 | E73: Federal Healthcare | F73: Reverses "CDW-050323-11 Releasing VA EA cost from timing"06-JUL-23 14:09:55 - 387625478 E 14497649 N | G73: Reverses "CDW-050323-11 Releasing VA EA cost from timing"06-JUL-2023 14:09:55 OPR Adjustments | H73: Issue: AP Correction Needed | I73: Jun-23 | J73: 171249.44 | K73: 171249.44 | L73: 171249.44 | M73: USD | N73: USD | O73: Reverses CDW-050323-11 Releasing VA EA cost from timing journal entry of CDW-050323-11 Releasing VA EA cost from timing 03-MAY-2023 15:27:11 batch from APR-23. | P73: Journal Import Created | Q73: World Wide Technology, LLC (WWT) | R73: Public Sector | S73: Federal | T73: Federal Civilian | U73: 101.11010.245011.9999.999.999.9999.9999 | V73: 101 | W73: 11010 | X73: 245011 | Y73: 9999 | Z73: 999 | AA73: 999 | AB73: 9999 | AC73: 9999 | AD73: Accrued Liabilities - Public Sector | AE73: - | AF73: - | AG73: CLOUD | AI73: - | AJ73: 45107 | AK73: EBS OPR | AL73: WWT US Ledger
A74: 40 | B74: 31-60 | E74: Federal Army Enterprise | F74: CDW-060223-11 Accruing SO 10912564 Cost 02-JUN-2023 15:10:20 EBS OPR A 5729704 13920745 N | G74: CDW-060223-11 Accruing SO 10912564 Cost OPR Adjustments | H74: Accrual: Dropship | I74: 45069 | J74: -130197.21 | K74: -130197.21 | L74: -130197.21 | M74: USD | N74: USD | O74: Accruing SO 10912564 Cost | P74: Journal Import Created | Q74: World Wide Technology, LLC (WWT) | R74: Public Sector | S74: Federal | T74: Federal Department of Defense | U74: 101.11003.245011.9999.999.999.9999.9999 | V74: 101 | W74: 11003 | X74: 245011 | Y74: 9999 | Z74: 999 | AA74: 999 | AB74: 9999 | AC74: 9999 | AD74: Accrued Liabilities - Public Sector | AE74: - | AF74: - | AG74: CLOUD | AH74: - | AI74: - | AJ74: 45077 | AK74: EBS OPR | AL74: WWT US Ledger
A75: 24 | B75: 0-30 | E75: Federal Army Enterprise | F75: Reverses "CDW-060223-11 Accruing SO 10912564 Cost"16-JUN-23 15:21:31 - 386206761 EBS OPR 14313013 N | G75: Reverses "CDW-060223-11 Accruing SO 10912564 Cost"16-JUN-2023 15:21:31 OPR Adjustments | H75: Accrual: Dropship | I75: Jun-23 | J75: 130197.21 | K75: 130197.21 | L75: 130197.21 | M75: USD | N75: USD | O75: Reverses CDW-060223-11 Accruing SO 10912564 Cost journal entry of CDW-060223-11 Accruing SO 10912564 Cost 02-JUN-2023 15:10:20 batch from MAY-23. | P75: Journal Import Created | Q75: World Wide Technology, LLC (WWT) | R75: Public Sector | S75: Federal | T75: Federal Department of Defense | U75: 101.11003.245011.9999.999.999.9999.9999 | V75: 101 | W75: 11003 | X75: 245011 | Y75: 9999 | Z75: 999 | AA75: 999 | AB75: 9999 | AC75: 9999 | AD75: Accrued Liabilities - Public Sector | AE75: - | AF75: - | AG75: CLOUD | AI75: - | AJ75: 45093 | AK75: EBS OPR | AL75: WWT US Ledger
A76: 20 | B76: 0-30 | E76: Federal House | F76: CDW-062023-14 Reserve Reclass to Federal House | G76: CDW-062023-14 Reserve Reclass to Federal House | H76: Reclass: P&L Move | I76: Jun-23 | J76: -1556155 | K76: -1556155 | L76: -1556155 | M76: USD | N76: USD | O76: Reserve Reclass to Federal House | P76: Reserve Reclass to Federal House | Q76: World Wide Technology, LLC (WWT) | R76: Public Sector | S76: Federal | T76: Federal House | U76: 101.11016.245011.9999.999.999.9999.9999 | V76: 101 | W76: 11016 | X76: 245011 | Y76: 9999 | Z76: 999 | AA76: 999 | AB76: 9999 | AC76: 9999 | AD76: Accrued Liabilities - Public Sector | AE76: - | AF76: - | AG76: CLOUD | AI76: - | AJ76: 45097 | AK76: Manual | AL76: WWT US Ledger
A77: 20 | B77: 0-30 | E77: Federal House | F77: CDW-062023-13 Reserve reclass to Federal House 20-JUN-2023 11:34:01 EBS OPR A 6535678 14397616 N | G77: CDW-062023-13 Reserve reclass to Federal House OPR Adjustments | H77: Accrual: Dropship | I77: Jun-23 | J77: 1553790.8 | K77: 1553790.8 | L77: 1553790.8 | M77: USD | N77: USD | O77: Reserve reclass to Federal House | P77: Journal Import Created | Q77: World Wide Technology, LLC (WWT) | R77: Public Sector | S77: Federal | T77: Federal House | U77: 101.11016.245011.9999.999.999.9999.9999 | V77: 101 | W77: 11016 | X77: 245011 | Y77: 9999 | Z77: 999 | AA77: 999 | AB77: 9999 | AC77: 9999 | AD77: Accrued Liabilities - Public Sector | AE77: - | AF77: - | AG77: CLOUD | AI77: - | AJ77: 45097 | AK77: EBS OPR | AL77: WWT US Ledger
A78: 10 | B78: 0-30 | E78: Federal House | F78: CDW-070723-5 Reserve funds to Federal House 07-JUL-2023 10:55:11 EBS OPR A 6710516 14512317 N | G78: CDW-070723-5 Reserve funds to Federal House OPR Adjustments | H78: Accrual: Dropship | I78: Jun-23 | J78: 2364.24 | K78: 2364.24 | L78: 2364.24 | M78: USD | N78: USD | O78: Reserve funds to Federal House | P78: Journal Import Created | Q78: World Wide Technology, LLC (WWT) | R78: Public Sector | S78: Federal | T78: Federal House | U78: 101.11016.245011.9999.999.999.9999.9999 | V78: 101 | W78: 11016 | X78: 245011 | Y78: 9999 | Z78: 999 | AA78: 999 | AB78: 9999 | AC78: 9999 | AD78: Accrued Liabilities - Public Sector | AE78: - | AF78: - | AG78: CLOUD | AI78: - | AJ78: 45107 | AK78: EBS OPR | AL78: WWT US Ledger
A79: 101 | B79: 91-120 | D79: Reversed in June - Needs to be reversed in May | E79: Federal Law Enforcement | F79: CDW-040323-8 Defer SO 10811006 Ops Issue 04-APR-2023 00:08:35 EBS OPR A 4057831 12856347 N | G79: CDW-040323-8 Defer SO 10811006 Ops Issue OPR Adjustments | H79: Issue: Ops Correction Needed - Line Type | I79: Mar-23 | J79: 9054.62 | K79: 9054.62 | L79: 9054.62 | M79: USD | N79: USD | O79: Defer SO 10811006 Ops Issue | P79: Journal Import Created | Q79: World Wide Technology, LLC (WWT) | R79: Public Sector | S79: Federal | T79: Federal Civilian | U79: 101.12013.245011.9999.999.999.9999.9999 | V79: 101 | W79: 12013 | X79: 245011 | Y79: 9999 | Z79: 999 | AA79: 999 | AB79: 9999 | AC79: 9999 | AD79: Accrued Liabilities - Public Sector | AE79: - | AF79: - | AG79: CLOUD | AI79: - | AJ79: 45016 | AK79: EBS OPR | AL79: WWT US Ledger
A80: 25 | B80: 0-30 | E80: Federal Law Enforcement | F80: Reverses "CDW-040323-8 Defer SO 10811006 Ops Issue"15-JUN-23 10:14:26 - 386100880 EBS OPR 14133391 N | G80: Reverses "CDW-040323-8 Defer SO 10811006 Ops Issue"15-JUN-2023 10:14:26 OPR Adjustments | H80: Issue: Ops Correction Needed - Line Type | I80: Jun-23 | J80: -9054.62 | K80: -9054.62 | L80: -9054.62 | M80: USD | N80: USD | O80: Reverses CDW-040323-8 Defer SO 10811006 Ops Issue journal entry of CDW-040323-8 Defer SO 10811006 Ops Issue 04-APR-2023 00:08:35 batch from MAR-23. | P80: Journal Import Created | Q80: World Wide Technology, LLC (WWT) | R80: Public Sector | S80: Federal | T80: Federal Civilian | U80: 101.12013.245011.9999.999.999.9999.9999 | V80: 101 | W80: 12013 | X80: 245011 | Y80: 9999 | Z80: 999 | AA80: 999 | AB80: 9999 | AC80: 9999 | AD80: Accrued Liabilities - Public Sector | AE80: - | AF80: - | AG80: CLOUD | AI80: - | AJ80: 45092 | AK80: EBS OPR | AL80: WWT US Ledger
A81: 101 | B81: 91-120 | D81: Reversed in June - Part of Inv Reserve in AR other account | E81: Federal Navy NGEN | F81: CDW-040523-12 Defer cost SO 10843632 portion of Prelim Reserve 05-APR-2023 15:58:33 EBS O 12887131 N | G81: CDW-040523-12 Defer cost SO 10843632 portion of Prelim Reserve OPR Adjustments | H81: Reserve Funds | I81: Mar-23 | J81: 73709.27 | K81: 73709.27 | L81: 73709.27 | M81: USD | N81: USD | O81: SO 10843632 portion of Prelim Reserve | P81: Journal Import Created | Q81: World Wide Technology, LLC (WWT) | R81: Public Sector | S81: Federal | T81: Federal Department of Defense | U81: 101.11024.245011.9999.999.999.9999.9999 | V81: 101 | W81: 11024 | X81: 245011 | Y81: 9999 | Z81: 999 | AA81: 999 | AB81: 9999 | AC81: 9999 | AD81: Accrued Liabilities - Public Sector | AE81: - | AF81: - | AG81: CLOUD | AI81: - | AJ81: 45016 | AK81: EBS OPR | AL81: WWT US Ledger
A82: 71 | B82: 61-90 | D82: Reversed in June - Part of Inv Reserve in AR other account | E82: Federal Navy NGEN | F82: CDW-050223-7 Defer cost SO 10866627 portion of Reserve 02-MAY-2023 10:48:24 EBS OPR A 477 13313526 N | G82: CDW-050223-7 Defer cost SO 10866627 portion of Reserve OPR Adjustments | H82: Reserve Funds | I82: Apr-23 | J82: 1251945.2 | K82: 1251945.2 | L82: 1251945.2 | M82: USD | N82: USD | O82: Defer cost SO 10866627 portion of Reserve | P82: Journal Import Created | Q82: World Wide Technology, LLC (WWT) | R82: Public Sector | S82: Federal | T82: Federal Department of Defense | U82: 101.11024.245011.9999.999.999.9999.9999 | V82: 101 | W82: 11024 | X82: 245011 | Y82: 9999 | Z82: 999 | AA82: 999 | AB82: 9999 | AC82: 9999 | AD82: Accrued Liabilities - Public Sector | AE82: - | AF82: - | AG82: CLOUD | AH82: - | AI82: - | AJ82: 45046 | AK82: EBS OPR | AL82: WWT US Ledger
A83: 71 | B83: 61-90 | D83: Reversed in June - Part of Inv Reserve in AR other account | E83: Federal Navy NGEN | F83: CDW-050223-6 Defer cost SO 10866610 portion of Reserve 02-MAY-2023 10:42:25 EBS OPR A 477 13313526 N | G83: CDW-050223-6 Defer cost SO 10866610 portion of Reserve OPR Adjustments | H83: Reserve Funds | I83: Apr-23 | J83: 228136.27 | K83: 228136.27 | L83: 228136.27 | M83: USD | N83: USD | O83: Defer cost SO 10866610 portion of Reserve | P83: Journal Import Created | Q83: World Wide Technology, LLC (WWT) | R83: Public Sector | S83: Federal | T83: Federal Department of Defense | U83: 101.11024.245011.9999.999.999.9999.9999 | V83: 101 | W83: 11024 | X83: 245011 | Y83: 9999 | Z83: 999 | AA83: 999 | AB83: 9999 | AC83: 9999 | AD83: Accrued Liabilities - Public Sector | AE83: - | AF83: - | AG83: CLOUD | AH83: - | AI83: - | AJ83: 45046 | AK83: EBS OPR | AL83: WWT US Ledger
A84: 27 | B84: 0-30 | E84: Federal Navy NGEN | F84: Reverses "CDW-050223-6 Defer cost SO 10866610 portion of Res"13-JUN-23 14:31:02 - 3859503 14102309 N | G84: Reverses "CDW-050223-6 Defer cost SO 10866610 portion of Reserve"13-JUN-2023 14:31:02 OPR Adjustmen | H84: Reserve Funds | I84: Jun-23 | J84: -228136.27 | K84: -228136.27 | L84: -228136.27 | M84: USD | N84: USD | O84: Reverses CDW-050223-6 Defer cost SO 10866610 portion of Reserve journal entry of CDW-050223-6 Defer cost SO 10866610 portion of Reserve 02-MAY-2023 10:42:25 batch from APR-23. | P84: Journal Import Created | Q84: World Wide Technology, LLC (WWT) | R84: Public Sector | S84: Federal | T84: Federal Department of Defense | U84: 101.11024.245011.9999.999.999.9999.9999 | V84: 101 | W84: 11024 | X84: 245011 | Y84: 9999 | Z84: 999 | AA84: 999 | AB84: 9999 | AC84: 9999 | AD84: Accrued Liabilities - Public Sector | AE84: - | AF84: - | AG84: CLOUD | AI84: - | AJ84: 45090 | AK84: EBS OPR | AL84: WWT US Ledger
A85: 27 | B85: 0-30 | E85: Federal Navy NGEN | F85: Reverses "CDW-040523-12 Defer cost SO 10843632 portion of Pr"13-JUN-23 14:31:00 - 3859494 14102309 N | G85: Reverses "CDW-040523-12 Defer cost SO 10843632 portion of Prelim Reserve"13-JUN-2023 14:31:00 OPR A | H85: Reserve Funds | I85: Jun-23 | J85: -73709.27 | K85: -73709.27 | L85: -73709.27 | M85: USD | N85: USD | O85: Reverses CDW-040523-12 Defer cost SO 10843632 portion of Prelim Reserve journal entry of CDW-040523-12 Defer cost SO 10843632 portion of Prelim Reserve 05-APR-2023 15:58:33 batch from MAR-23. | P85: Journal Import Created | Q85: World Wide Technology, LLC (WWT) | R85: Public Sector | S85: Federal | T85: Federal Department of Defense | U85: 101.11024.245011.9999.999.999.9999.9999 | V85: 101 | W85: 11024 | X85: 245011 | Y85: 9999 | Z85: 999 | AA85: 999 | AB85: 9999 | AC85: 9999 | AD85: Accrued Liabilities - Public Sector | AE85: - | AF85: - | AG85: CLOUD | AI85: - | AJ85: 45090 | AK85: EBS OPR | AL85: WWT US Ledger
A86: 27 | B86: 0-30 | E86: Federal Navy NGEN | F86: Reverses "CDW-050223-7 Defer cost SO 10866627 portion of Res"13-JUN-23 14:31:01 - 3859503 14102309 N | G86: Reverses "CDW-050223-7 Defer cost SO 10866627 portion of Reserve"13-JUN-2023 14:31:01 OPR Adjustmen | H86: Reserve Funds | I86: Jun-23 | J86: -1251945.2 | K86: -1251945.2 | L86: -1251945.2 | M86: USD | N86: USD | O86: Reverses CDW-050223-7 Defer cost SO 10866627 portion of Reserve journal entry of CDW-050223-7 Defer cost SO 10866627 portion of Reserve 02-MAY-2023 10:48:24 batch from APR-23. | P86: Journal Import Created | Q86: World Wide Technology, LLC (WWT) | R86: Public Sector | S86: Federal | T86: Federal Department of Defense | U86: 101.11024.245011.9999.999.999.9999.9999 | V86: 101 | W86: 11024 | X86: 245011 | Y86: 9999 | Z86: 999 | AA86: 999 | AB86: 9999 | AC86: 9999 | AD86: Accrued Liabilities - Public Sector | AE86: - | AF86: - | AG86: CLOUD | AI86: - | AJ86: 45090 | AK86: EBS OPR | AL86: WWT US Ledger
A87: 467 | B87: 365+ | D87: Timing - Streamline FEDERAL RESOURCES PO 157803 - should reverse in May | E87: Federal Navy | F87: BDM-050322-1 03-MAY-2022 08:39:40 EBS OPR A 17429488 7937391 N | G87: BDM-050322-1 OPR Adjustments | H87: Timing: Streamline | I87: Apr-22 | J87: 200826 | K87: 200826 | L87: 200826 | M87: USD | N87: USD | O87: Streamline for PO 157803 - OPR to justify | P87: Journal Import Created | Q87: World Wide Technology, LLC (WWT) | R87: Public Sector | S87: Federal | T87: Federal Department of Defense | U87: 101.11023.245011.9999.999.999.9999.9999 | V87: 101 | W87: 11023 | X87: 245011 | Y87: 9999 | Z87: 999 | AA87: 999 | AB87: 9999 | AC87: 9999 | AD87: Accrued Liabilities - Public Sector | AE87: - | AF87: - | AG87: CLOUD | AI87: - | AJ87: 44681 | AK87: EBS OPR | AL87: WWT US Ledger
A88: 132 | B88: 121-150 | D88: Reversed in July - PO P3152301398 SO 10764155 Expecting Cost in July | E88: SLED Central | F88: CDW-040423-4 Accruing Cost SO 10764155 Drop Ship 04-APR-2023 09:48:44 EBS OPR A 4057831 12856347 N | G88: CDW-040423-4 Accruing Cost SO 10764155 Drop Ship OPR Adjustments | H88: Accrual: Dropship | I88: Mar-23 | J88: -45396.3 | K88: -45396.3 | L88: -45396.3 | M88: USD | N88: USD | O88: Accruing Cost SO 10764155 Drop Ship | P88: Journal Import Created | Q88: World Wide Technology, LLC (WWT) | R88: Public Sector | S88: SLED | T88: SLED East | U88: 101.13006.245011.9999.999.999.9999.9999 | V88: 101 | W88: 13006 | X88: 245011 | Y88: 9999 | Z88: 999 | AA88: 999 | AB88: 9999 | AC88: 9999 | AD88: Accrued Liabilities - Public Sector | AE88: - | AF88: - | AG88: CLOUD | AI88: - | AJ88: 45016 | AK88: EBS OPR | AL88: WWT US Ledger
A89: 102 | B89: 91-120 | D89: Cost Accrual - expected in October | E89: SLED Southeast | F89: CDW-050123-8 Accruing cost on SO 10861252 01-MAY-2023 16:00:24 EBS OPR A 4755965 13294942 N | G89: CDW-050123-8 Accruing cost on SO 10861252 OPR Adjustments | H89: Accrual: Dropship | I89: Apr-23 | J89: -37685.19 | K89: -37685.19 | L89: -37685.19 | M89: USD | N89: USD | O89: Accruing cost on SO 10861252 | P89: Journal Import Created | Q89: World Wide Technology, LLC (WWT) | R89: Public Sector | S89: SLED | T89: SLED East | U89: 101.13008.245011.9999.999.999.9999.9999 | V89: 101 | W89: 13008 | X89: 245011 | Y89: 9999 | Z89: 999 | AA89: 999 | AB89: 9999 | AC89: 9999 | AD89: Accrued Liabilities - Public Sector | AE89: - | AF89: - | AG89: CLOUD | AH89: - | AI89: - | AJ89: 45046 | AK89: EBS OPR | AL89: WWT US Ledger
A90: 41 | B90: 31-60 | D90: Reversed in July | E90: Federal Healthcare | F90: CDW-070623-3 Accruing VA EA AP Inv 6101529240 06-JUL-2023 10:41:45 EBS OPR A 6682848 14497649 N | G90: CDW-070623-3 Accruing VA EA AP Inv 6101529240 OPR Adjustments | H90: Accrual: Dropship | I90: Jun-23 | J90: -14985 | K90: -14985 | L90: -14985 | M90: USD | N90: USD | O90: Accruing VA EA AP Inv 6101529240 | P90: Journal Import Created | Q90: World Wide Technology, LLC (WWT) | R90: Public Sector | S90: Federal | T90: Federal Civilian | U90: 101.11010.245011.9999.999.999.9999.9999 | V90: 101 | W90: 11010 | X90: 245011 | Y90: 9999 | Z90: 999 | AA90: 999 | AB90: 9999 | AC90: 9999 | AD90: Accrued Liabilities - Public Sector | AE90: - | AF90: - | AG90: CLOUD | AI90: - | AJ90: 45107 | AK90: EBS OPR | AL90: WWT US Ledger
A91: 41 | B91: 31-60 | D91: Reversed in July | E91: SLED Southeast | F91: CDW-070623-2 Defer SO 10917153 hits in July | G91: CDW-070623-2 Defer SO 10917153 hits in July | H91: Accrual: Dropship | I91: Jun-23 | J91: 671.7 | K91: 671.7 | L91: 671.7 | M91: USD | N91: USD | O91: Defer SO 10917153 hits in July | P91: Defer SO 10917153 hits in July | Q91: World Wide Technology, LLC (WWT) | R91: Public Sector | S91: SLED | T91: SLED East | U91: 101.13008.245011.9999.950.999.9999.9999 | V91: 101 | W91: 13008 | X91: 245011 | Y91: 9999 | Z91: 950 | AA91: 999 | AB91: 9999 | AC91: 9999 | AD91: Accrued Liabilities - Public Sector | AE91: C1AD6E | AF91: - | AG91: CLOUD | AI91: - | AJ91: 45107 | AK91: Manual | AL91: WWT US Ledger
A92: 41 | B92: 31-60 | E92: SLED PANYNJ NESS | F92: CDW-070523-3 Accruing Finder's fee SO 10764905 05-JUL-2023 12:04:51 EBS OPR A 6635210 14477816 N | G92: CDW-070523-3 Accruing Finder's fee SO 10937434 OPR Adjustments | H92: Accrual: Dropship | I92: Jun-23 | J92: -125000 | K92: -125000 | L92: -125000 | M92: USD | N92: USD | O92: Accruing Finder's fee SO 10937434 | P92: Journal Import Created | Q92: World Wide Technology, LLC (WWT) | R92: Public Sector | S92: SLED | T92: SLED East | U92: 101.13017.245011.9999.999.999.9999.9999 | V92: 101 | W92: 13017 | X92: 245011 | Y92: 9999 | Z92: 999 | AA92: 999 | AB92: 9999 | AC92: 9999 | AD92: Accrued Liabilities - Public Sector | AE92: - | AF92: - | AG92: CLOUD | AI92: - | AJ92: 45107 | AK92: EBS OPR | AL92: WWT US Ledger
A93: 23 | B93: 0-30 | E93: SLED PANYNJ NESS | F93: Reverses "CDW-070523-3 Accruing Finder's fee SO 10937434"18-JUL-23 11:17:27 - 388597249 E 14714103 N | G93: Reverses "CDW-070523-3 Accruing Finder's fee SO 10937434"18-JUL-2023 11:17:27 OPR Adjustments | H93: Accrual: Dropship | I93: Jul-23 | J93: 125000 | K93: 125000 | L93: 125000 | M93: USD | N93: USD | O93: Reverses CDW-070523-3 Accruing Finder's fee SO 10937434 journal entry of CDW-070523-3 Accruing Finder's fee SO 10764905 05-JUL-2023 12:04:51 batch from JUN-23. | P93: Journal Import Created | Q93: World Wide Technology, LLC (WWT) | R93: Public Sector | S93: SLED | T93: SLED East | U93: 101.13017.245011.9999.999.999.9999.9999 | V93: 101 | W93: 13017 | X93: 245011 | Y93: 9999 | Z93: 999 | AA93: 999 | AB93: 9999 | AC93: 9999 | AD93: Accrued Liabilities - Public Sector | AE93: - | AF93: - | AG93: CLOUD | AI93: - | AJ93: 45125 | AK93: EBS OPR | AL93: WWT US Ledger
A94: 30 | B94: 0-30 | E94: SLED Central | F94: Reverses "CDW-040423-4 Accruing Cost SO 10764155 Drop Ship"11-JUL-23 15:50:11 - 388040419 14609531 N | G94: Reverses "CDW-040423-4 Accruing Cost SO 10764155 Drop Ship"11-JUL-2023 15:50:12 OPR Adjustments | H94: Accrual: Dropship | I94: Jul-23 | J94: 45396.3 | K94: 45396.3 | L94: 45396.3 | M94: USD | N94: USD | O94: Reverses CDW-040423-4 Accruing Cost SO 10764155 Drop Ship journal entry of CDW-040423-4 Accruing Cost SO 10764155 Drop Ship 04-APR-2023 09:48:44 batch from MAR-23. | P94: Journal Import Created | Q94: World Wide Technology, LLC (WWT) | R94: Public Sector | S94: SLED | T94: SLED East | U94: 101.13006.245011.9999.999.999.9999.9999 | V94: 101 | W94: 13006 | X94: 245011 | Y94: 9999 | Z94: 999 | AA94: 999 | AB94: 9999 | AC94: 9999 | AD94: Accrued Liabilities - Public Sector | AE94: - | AF94: - | AG94: CLOUD | AI94: - | AJ94: 45118 | AK94: EBS OPR | AL94: WWT US Ledger
A95: 30 | B95: 0-30 | E95: Federal Navy | F95: Reverses "BDM-050322-1"11-JUL-23 10:00:47 - 388012388 EBS OPR A 6861803 14609531 N | G95: Reverses "BDM-050322-1"11-JUL-2023 10:00:47 OPR Adjustments | H95: Timing: Streamline | I95: Jul-23 | J95: -200826 | K95: -200826 | L95: -200826 | M95: USD | N95: USD | O95: Reverses BDM-050322-1 journal entry of BDM-050322-1 03-MAY-2022 08:39:40 batch from APR-22. | P95: Journal Import Created | Q95: World Wide Technology, LLC (WWT) | R95: Public Sector | S95: Federal | T95: Federal Department of Defense | U95: 101.11023.245011.9999.999.999.9999.9999 | V95: 101 | W95: 11023 | X95: 245011 | Y95: 9999 | Z95: 999 | AA95: 999 | AB95: 9999 | AC95: 9999 | AD95: Accrued Liabilities - Public Sector | AE95: - | AF95: - | AG95: CLOUD | AI95: - | AJ95: 45118 | AK95: EBS OPR | AL95: WWT US Ledger
A96: 31 | B96: 31-60 | E96: SLED Southeast | F96: Reverses CDW-070623-2 Defer SO 10917153 hits in July 10-07-23 17:20:40 14562430 | G96: Reverses CDW-070623-2 Defer SO 10917153 hits in July 10-07-23 17:20:41 | H96: Accrual: Dropship | I96: Jul-23 | J96: -671.7 | K96: -671.7 | L96: -671.7 | M96: USD | N96: USD | O96: Reverses journal CDW-070623-2 Defer SO 10917153 hits in July of journal batch CDW-070623-2 Defer SO 10917153 hits in July from period Jun-23. | P96: Defer SO 10917153 hits in July | Q96: World Wide Technology, LLC (WWT) | R96: Public Sector | S96: SLED | T96: SLED East | U96: 101.13008.245011.9999.950.999.9999.9999 | V96: 101 | W96: 13008 | X96: 245011 | Y96: 9999 | Z96: 950 | AA96: 999 | AB96: 9999 | AC96: 9999 | AD96: Accrued Liabilities - Public Sector | AE96: C1AD6E | AF96: - | AG96: CLOUD | AI96: - | AJ96: 45117 | AK96: Manual | AL96: WWT US Ledger
A97: 31 | B97: 31-60 | E97: Federal Healthcare | F97: Reverses "CDW-070623-3 Accruing VA EA AP Inv 6101529240"10-JUL-23 12:46:51 - 387942308 EB 14565161 N | G97: Reverses "CDW-070623-3 Accruing VA EA AP Inv 6101529240"10-JUL-2023 12:46:51 OPR Adjustments | H97: Accrual: Dropship | I97: Jul-23 | J97: 14985 | K97: 14985 | L97: 14985 | M97: USD | N97: USD | O97: Reverses CDW-070623-3 Accruing VA EA AP Inv 6101529240 journal entry of CDW-070623-3 Accruing VA EA AP Inv 6101529240 06-JUL-2023 10:41:45 batch from JUN-23. | P97: Journal Import Created | Q97: World Wide Technology, LLC (WWT) | R97: Public Sector | S97: Federal | T97: Federal Civilian | U97: 101.11010.245011.9999.999.999.9999.9999 | V97: 101 | W97: 11010 | X97: 245011 | Y97: 9999 | Z97: 999 | AA97: 999 | AB97: 9999 | AC97: 9999 | AD97: Accrued Liabilities - Public Sector | AE97: - | AF97: - | AG97: CLOUD | AI97: - | AJ97: 45117 | AK97: EBS OPR | AL97: WWT US Ledger
A98: 10 | B98: 0-30 | E98: SLED Southeast | F98: Reverses "CDW-050123-8 Accruing cost on SO 10861252"01-AUG-23 23:21:06 - 389653813 EBS OP 14960993 N | G98: Reverses "CDW-050123-8 Accruing cost on SO 10861252"01-AUG-2023 23:21:06 OPR Adjustments | H98: Accrual: Dropship | I98: Jul-23 | J98: 37685.19 | K98: 37685.19 | L98: 37685.19 | M98: USD | N98: USD | O98: Reverses CDW-050123-8 Accruing cost on SO 10861252 journal entry of CDW-050123-8 Accruing cost on SO 10861252 01-MAY-2023 16:00:24 batch from APR-23. | P98: Journal Import Created | Q98: World Wide Technology, LLC (WWT) | R98: Public Sector | S98: SLED | T98: SLED East | U98: 101.13008.245011.9999.999.999.9999.9999 | V98: 101 | W98: 13008 | X98: 245011 | Y98: 9999 | Z98: 999 | AA98: 999 | AB98: 9999 | AC98: 9999 | AD98: Accrued Liabilities - Public Sector | AE98: - | AF98: - | AG98: CLOUD | AI98: - | AJ98: 45138 | AK98: EBS OPR | AL98: WWT US Ledger
A99: 196 | B99: 181-210 | D99: Reversed in AugustTo defer cost on Customer PO 10000410, SO 10768674, Emailed Shelly on 2/23, 3/14, 4/19, 6/15 - Jake is working on matching Hours completed with customer and IUB will be booked | E99: Federal COCOMs | F99: MNS-030223-6 02-MAR-2023 12:18:20 EBS OPR A 3111139 12300142 N | G99: MNS-030223-6 OPR Adjustments | H99: Issue: Ops Correction Needed - Pricing | I99: Feb-23 | J99: 369435.6 | K99: 369435.6 | L99: 369435.6 | M99: USD | N99: USD | O99: To defer cost on Customer PO 10000410, SO 10768674 | P99: Journal Import Created | Q99: World Wide Technology, LLC (WWT) | R99: Public Sector | S99: Federal | T99: Federal Department of Defense | U99: 101.12015.245011.9999.999.999.9999.9999 | V99: 101 | W99: 12015 | X99: 245011 | Y99: 9999 | Z99: 999 | AA99: 999 | AB99: 9999 | AC99: 9999 | AD99: Accrued Liabilities - Public Sector | AE99: - | AF99: - | AG99: CLOUD | AI99: - | AJ99: 44985 | AK99: EBS OPR | AL99: WWT US Ledger
A100: 196 | B100: 181-210 | D100: Reversed in AugustTo defer cost on Customer PO 10000410, SO 10768674, Emailed Shelly on 2/23, 3/14, 4/19, 6/15 - Jake is working on matching Hours completed with customer and IUB will be booked | E100: Federal COCOMs | F100: MNS-030223-5 02-MAR-2023 12:07:09 EBS OPR A 3111139 12300142 N | G100: MNS-030223-5 OPR Adjustments | H100: Issue: Ops Correction Needed - Pricing | I100: Feb-23 | J100: 179262 | K100: 179262 | L100: 179262 | M100: USD | N100: USD | O100: To defer revenue & cost on Customer PO 10000410, SO 10230194 | P100: Journal Import Created | Q100: World Wide Technology, LLC (WWT) | R100: Public Sector | S100: Federal | T100: Federal Department of Defense | U100: 101.12015.245011.9999.999.999.9999.9999 | V100: 101 | W100: 12015 | X100: 245011 | Y100: 9999 | Z100: 999 | AA100: 999 | AB100: 9999 | AC100: 9999 | AD100: Accrued Liabilities - Public Sector | AE100: - | AF100: - | AG100: CLOUD | AI100: - | AJ100: 44985 | AK100: EBS OPR | AL100: WWT US Ledger
A101: 196 | B101: 181-210 | D101: Reversed in AugustTo defer cost on Customer PO 10000410, SO 10768674, Emailed Shelly on 2/23, 3/14, 4/19, 6/15 - Jake is working on matching Hours completed with customer and IUB will be booked | E101: Federal COCOMs | F101: MNS-030223-5 02-MAR-2023 12:07:09 EBS OPR A 3111139 12300142 N | G101: MNS-030223-5 OPR Adjustments | H101: Issue: Ops Correction Needed - Pricing | I101: Feb-23 | J101: -213440 | K101: -213440 | L101: -213440 | M101: USD | N101: USD | O101: To defer revenue & cost on Customer PO 10000410, SO 10230194 | P101: Journal Import Created | Q101: World Wide Technology, LLC (WWT) | R101: Public Sector | S101: Federal | T101: Federal Department of Defense | U101: 101.12015.245011.9999.999.999.9999.9999 | V101: 101 | W101: 12015 | X101: 245011 | Y101: 9999 | Z101: 999 | AA101: 999 | AB101: 9999 | AC101: 9999 | AD101: Accrued Liabilities - Public Sector | AE101: - | AF101: - | AG101: CLOUD | AI101: - | AJ101: 44985 | AK101: EBS OPR | AL101: WWT US Ledger
...

Sheet Offsets prior to 2023
A1: A/R Other - Federal
O2: =SUBTOTAL(9,O417:O1048576) -> 0 | P2: =SUBTOTAL(9,P4:P3045) -> 0 | U2: BDM-110321-35
A3: Type | B3: Invoice # | C3: Invoice Date | D3: Period | E3: Financial Program | F3: Subprogram | G3: P_L Rollup | H3: P_L | I3: GL Account | J3: Co | K3: SD | L3: Acct | M3: CC | N3: Natural Account Description | O3: Entered Amount | P3: Accounted Amount | Q3: Comments | R3: Description | S3: Justification | T3: Invoice Line # | U3: Batch | V3: Source | W3: PO | X3: PO Description | Y3: Effective Date | Z3: Posted Date
A4: - | B4: - | D4: Dec-21 | E4: Public Sector | F4: SLED | G4: SLED East | H4: SLED Southeast | I4: 101.13008.245011.9999.999.999.9999.9999 | J4: 101 | K4: 13008 | L4: 245011 | M4: 9999 | N4: Accrued Liabilities - Public Sector | O4: 760.24 | P4: 760.24 | Q4: offset | R4: Prelim 9916664 on hold | S4: Journal Import Created | U4: BDM-010622-10 Spreadsheet A 300000031763616 6594278 N | V4: Spreadsheet | W4: 9/30/2021 | X4: - | Y4: 44561 | Z4: 44568
A5: - | B5: - | D5: Dec-21 | E5: Public Sector | F5: SLED | G5: SLED East | H5: SLED Southeast | I5: 101.13008.245011.9999.999.999.9999.9999 | J5: 101 | K5: 13008 | L5: 245011 | M5: 9999 | N5: Accrued Liabilities - Public Sector | O5: 646.8 | P5: 646.8 | Q5: offset | R5: Prelim 9912076 on hold | S5: Journal Import Created | U5: BDM-010622-11 Spreadsheet A 300000031763616 6594278 N | V5: Spreadsheet | W5: 10/11/2021 | X5: - | Y5: 44561 | Z5: 44568
A6: - | B6: - | D6: Oct-21 | E6: Public Sector | F6: Federal | G6: Federal Department of Defense | H6: Federal Army Enterprise | I6: 101.11003.245011.9999.999.999.9999.9999 | J6: 101 | K6: 11003 | L6: 245011 | M6: 9999 | N6: Accrued Liabilities - Public Sector | O6: 81585.48 | P6: 81585.48 | Q6: offset | R6: SO 9882617 lines awaiting fufillment | S6: Journal Import Created | U6: BDM-110221-8 Spreadsheet A 300000031712966 5869187 N | V6: Spreadsheet | W6: - | X6: - | Y6: 44500 | Z6: 44503
A7: - | B7: - | D7: Dec-21 | E7: Public Sector | F7: Federal | G7: Federal Department of Defense | H7: Federal Army Enterprise | I7: 101.11003.245011.9999.999.999.9999.9999 | J7: 101 | K7: 11003 | L7: 245011 | M7: 9999 | N7: Accrued Liabilities - Public Sector | O7: 22138.74 | P7: 22138.74 | Q7: offset | R7: SO 9882587 awaiting fufillment | S7: Journal Import Created | U7: BDM-010622-14 Spreadsheet A 300000031763616 6594278 N | V7: Spreadsheet | W7: W52P1J21F0537 | X7: - | Y7: 44561 | Z7: 44568
A8: - | B8: - | D8: Nov-21 | E8: Public Sector | F8: SLED | G8: SLED West | H8: SLED Pacific Southwest | I8: 101.13004.245011.9999.999.999.9999.9999 | J8: 101 | K8: 13004 | L8: 245011 | M8: 9999 | N8: Accrued Liabilities - Public Sector | O8: 75405.9 | P8: 75405.9 | Q8: offset | R8: Deferring cost that transacted on Prelim PO# R-00651516, RMA to correct in December (REVERSE IN DEC) | S8: Journal Import Created | U8: BDM-120621-7 06-DEC-2021 09:42:28 EBS OPR A 14490946 6225790 N | V8: EBS OPR | W8: - | X8: - | Y8: 44530 | Z8: 44536
A9: - | B9: - | D9: Dec-21 | E9: Public Sector | F9: SLED | G9: SLED West | H9: SLED Pacific Southwest | I9: 101.13004.245011.9999.999.999.9999.9999 | J9: 101 | K9: 13004 | L9: 245011 | M9: 9999 | N9: Accrued Liabilities - Public Sector | O9: -75405.9 | P9: -75405.9 | Q9: offset | R9: Reverses BDM-120621-7 journal entry of BDM-120621-7 06-DEC-2021 09:42:28 batch from NOV-21. | S9: Journal Import Created | U9: Reverses "BDM-120621-7"13-DEC-21 14:36:22 - 343847307 EBS OPR A 14655364 6320865 N | V9: EBS OPR | W9: - | X9: - | Y9: 44543 | Z9: 44544
A10: - | B10: - | D10: Apr-21 | E10: Public Sector | F10: Federal | G10: Federal Civilian | H10: Federal Scientific | I10: 101.12021.245011.9999.999.999.9999.9999 | J10: 101 | K10: 12021 | L10: 245011 | M10: 9999 | N10: Accrued Liabilities - Public Sector | O10: 475200 | P10: 475200 | Q10: offset | R10: Deferring SAAS credit on WWTINCSAAS341 to validate accuracy - see email from Jessica Laux, invoiced from Recvue in March, credited in full in April, will be rebilled from Oracle on SO 9630354 (still booked as of 11/16) - followed up with Jessica | S10: Journal Import Created | U10: BDM-050621-4 06-MAY-2021 07:32:46 EBS OPR A 9298322 4008025 N | V10: EBS OPR | W10: - | X10: - | Y10: 44316 | Z10: 44322
A11: - | B11: - | D11: Dec-21 | E11: Public Sector | F11: Federal | G11: Federal Department of Defense | H11: Federal Intel Moonshot | I11: 101.12022.245011.9999.999.999.9999.9999 | J11: 101 | K11: 12022 | L11: 245011 | M11: 9999 | N11: Accrued Liabilities - Public Sector | O11: 6568037.7 | P11: 6568037.7 | Q11: offset | R11: Defer PPV for Moonshot Cisco AS Renewal for Yr 2, Ops Reworking in Jan | S11: Journal Import Created | U11: CMG-010722-1 Defer PPV for Moonshot Cisco AS Renewal for Yr 2, Ops Reworking in 07-JAN-202 6594795 N | V11: EBS OPR | W11: - | X11: - | Y11: 44561 | Z11: 44568
A12: - | B12: - | D12: Dec-21 | E12: Public Sector | F12: Federal | G12: Federal Department of Defense | H12: Federal Air Force | I12: 101.11001.245011.9999.999.999.9999.9999 | J12: 101 | K12: 11001 | L12: 245011 | M12: 9999 | N12: Accrued Liabilities - Public Sector | O12: 265219.5 | P12: 265219.5 | Q12: offset | R12: Defer AP W/O RMA Approved - will reverse to 502550 | S12: Journal Import Created | U12: CMG-010622-17 Defer AP W/O RMA Approved Spreadsheet A 300000031763616 6589071 N | V12: Spreadsheet | W12: - | X12: - | Y12: 44561 | Z12: 44568
A13: - | B13: - | D13: Dec-21 | E13: Public Sector | F13: SLED | G13: SLED East | H13: SLED Southeast | I13: 101.13008.245011.9999.999.999.9999.9999 | J13: 101 | K13: 13008 | L13: 245011 | M13: 9999 | N13: Accrued Liabilities - Public Sector | O13: 5392.9 | P13: 5392.9 | Q13: offset | R13: Prelim 9920693 on hold | S13: Journal Import Created | U13: BDM-010622-9 Spreadsheet A 300000031763616 6594278 N | V13: Spreadsheet | W13: 9/30/2021 | X13: - | Y13: 44561 | Z13: 44568
A14: - | B14: - | D14: Dec-21 | E14: Public Sector | F14: SLED | G14: SLED East | H14: SLED Southeast | I14: 101.13008.245011.9999.999.999.9999.9999 | J14: 101 | K14: 13008 | L14: 245011 | M14: 9999 | N14: Accrued Liabilities - Public Sector | O14: 39872.44 | P14: 39872.44 | Q14: offset | R14: Prelim 9920688 on hold | S14: Journal Import Created | U14: BDM-010622-8 Spreadsheet A 300000031763616 6594278 N | V14: Spreadsheet | W14: 9/30/2021 | X14: - | Y14: 44561 | Z14: 44568
A15: - | B15: - | D15: Dec-21 | E15: Public Sector | F15: SLED | G15: SLED West | H15: SLED HI/Comm | I15: 101.13001.245011.9999.999.999.9999.9999 | J15: 101 | K15: 13001 | L15: 245011 | M15: 9999 | N15: Accrued Liabilities - Public Sector | O15: 203797.08 | P15: 203797.08 | Q15: offset | R15: Prelim 9978548 on hold | S15: Journal Import Created | U15: BDM-010922-6 Spreadsheet A 300000031763616 6625251 N | V15: Spreadsheet | W15: - | X15: - | Y15: 44561 | Z15: 44571
... A63: - | B63: - | D63: Dec-21 | E63: Public Sector | F63: Federal | G63: Federal DISA ESSII | H63: Federal DISA ESSII | I63: 101.11011.245011.9999.999.999.9999.9999 | J63: 101 | K63: 11011 | L63: 245011 | M63: 9999 | N63: Accrued Liabilities - Public Sector | O63: -136207.82 | P63: -136207.82 | Q63: offset | R63: Accrue Dec GS Invoice | S63: Journal Import Created | U63: CMG-010922-1 Accrue Dec GS Invoice 09-JAN-2022 15:48:54 EBS OPR A 15113834 6625041 N | V63: EBS OPR | W63: - | X63: - | Y63: 44561 | Z63: 44571
A64: Performance Technology Group, Inc. | B64: 004209 | C64: 44556 | D64: Feb-22 | E64: Public Sector | F64: Federal | G64: Federal DISA ESSII | H64: Federal DISA ESSII | I64: 101.11011.245011.9999.999.999.9999.9999 | J64: 101 | K64: 11011 | L64: 245011 | M64: 9999 | N64: Accrued Liabilities - Public Sector | O64: 136207.82 | P64: 136207.82 | Q64: offset | R64: - | S64: - | T64: 1 | U64: Payables A 7195879000001 7195904 N | V64: Payables | W64: - | X64: - | Y64: 44620 | Z64: 44621
A65: - | B65: - | D65: Feb-22 | E65: Public Sector | F65: Federal | G65: Federal Civilian | H65: Federal Healthcare | I65: 101.11010.245011.9999.999.999.9999.9999 | J65: 101 | K65: 11010 | L65: 245011 | M65: 9999 | N65: Accrued Liabilities - Public Sector | O65: -414006 | P65: -414006 | Q65: offset | R65: Reverses BDM-030422-6 journal entry of BDM-030422-6 04-MAR-2022 08:15:36 batch from FEB-22. | S65: Journal Import Created | U65: Reverses "BDM-030422-6"04-MAR-22 12:57:10 - 349928122 EBS OPR A 16139893 7248822 N | V65: EBS OPR | W65: - | X65: - | Y65: 44620 | Z65: 44624
A66: - | B66: - | D66: Feb-22 | E66: Public Sector | F66: Federal | G66: Federal Civilian | H66: Federal Healthcare | I66: 101.11010.245011.9999.999.999.9999.9999 | J66: 101 | K66: 11010 | L66: 245011 | M66: 9999 | N66: Accrued Liabilities - Public Sector | O66: 414006 | P66: 414006 | Q66: offset | R66: Software accrual for 21P10391 - see template | S66: Journal Import Created | U66: BDM-030422-17 04-MAR-2022 12:57:08 EBS OPR A 16160027 7248951 N | V66: EBS OPR | W66: - | X66: - | Y66: 44620 | Z66: 44624
A67: - | B67: - | D67: Dec-21 | E67: Public Sector | F67: Federal | G67: Federal Department of Defense | H67: Federal Intel Moonshot | I67: 101.12022.245011.9999.999.999.9999.9999 | J67: 101 | K67: 12022 | L67: 245011 | M67: 9999 | N67: Accrued Liabilities - Public Sector | O67: -117294.64 | P67: -117294.64 | Q67: offset | R67: Accrue Moonshot AT&T Invoices | S67: Journal Import Created | U67: CMG-010922-2 Accrue Moonshot AT&T Invoices 09-JAN-2022 15:51:18 EBS OPR A 15113834 6625041 N | V67: EBS OPR | W67: - | X67: - | Y67: 44561 | Z67: 44571
A68: - | B68: - | D68: Feb-22 | E68: Public Sector | F68: Federal | G68: Federal Department of Defense | H68: Federal Intel Moonshot | I68: 101.12022.245011.9999.999.999.9999.9999 | J68: 101 | K68: 12022 | L68: 245011 | M68: 9999 | N68: Accrued Liabilities - Public Sector | O68: 117294.64 | P68: 117294.64 | Q68: offset | R68: Reverses CMG-010922-2 Accrue Moonshot AT&T Invoices journal entry of CMG-010922-2 Accrue Moonshot AT&T Invoices 09-JAN-2022 15:51:18 batch from DEC-21. | S68: Journal Import Created | U68: Reverses "CMG-010922-2 Accrue Moonshot AT&T Invoices"04-MAR-22 07:31:45 - 349903624 EBS OP 7246308 N | V68: EBS OPR | W68: - | X68: - | Y68: 44620 | Z68: 44624
A69: - | B69: - | D69: Dec-21 | E69: Public Sector | F69: SLED | G69: SLED West | H69: SLED HI/Comm | I69: 101.13001.245011.9999.999.999.9999.9999 | J69: 101 | K69: 13001 | L69: 245011 | M69: 9999 | N69: Accrued Liabilities - Public Sector | O69: 291214.65 | P69: 291214.65 | Q69: offset | R69: Prelim 10008276 on hold | S69: Journal Import Created | U69: BDM-010922-5 Spreadsheet A 300000031763616 6625251 N | V69: Spreadsheet | W69: - | X69: - | Y69: 44561 | Z69: 44571
A70: - | B70: - | D70: Dec-21 | E70: Public Sector | F70: SLED | G70: SLED West | H70: SLED HI/Comm | I70: 101.13001.245011.9999.999.999.9999.9999 | J70: 101 | K70: 13001 | L70: 245011 | M70: 9999 | N70: Accrued Liabilities - Public Sector | O70: 160280.5 | P70: 160280.5 | Q70: offset | R70: Prelim 9893523 on hold | S70: Journal Import Created | U70: BDM-010922-8 Spreadsheet A 300000031763616 6625251 N | V70: Spreadsheet | W70: - | X70: - | Y70: 44561 | Z70: 44571
A71: - | B71: - | D71: Dec-21 | E71: Public Sector | F71: SLED | G71: SLED West | H71: SLED HI/Comm | I71: 101.13001.245011.9999.999.999.9999.9999 | J71: 101 | K71: 13001 | L71: 245011 | M71: 9999 | N71: Accrued Liabilities - Public Sector | O71: 199719.5 | P71: 199719.5 | Q71: offset | R71: Prelim 9893522 on hold | S71: Journal Import Created | U71: BDM-010922-7 Spreadsheet A 300000031763616 6625251 N | V71: Spreadsheet | W71: - | X71: - | Y71: 44561 | Z71: 44571
A72: - | B72: - | D72: Oct-21 | E72: Public Sector | F72: Federal | G72: Federal Civilian | H72: Federal Healthcare | I72: 101.11010.245011.9999.999.999.9999.9999 | J72: 101 | K72: 11010 | L72: 245011 | M72: 9999 | N72: Accrued Liabilities - Public Sector | O72: 91935 | P72: 91935 | Q72: offset | R72: SO 9908929 on hold Eldridge, Dawn - UNRECOVERED HIT | S72: Journal Import Created | U72: BDM-110221-23 Spreadsheet A 300000031712966 5869187 N | V72: Spreadsheet | W72: - | X72: - | Y72: 44500 | Z72: 44503
A73: - | B73: - | D73: Feb-22 | E73: Public Sector | F73: Federal | G73: Federal Department of Defense | H73: Federal Intel | I73: 101.12012.245011.9999.999.999.9999.9999 | J73: 101 | K73: 12012 | L73: 245011 | M73: 9999 | N73: Accrued Liabilities - Public Sector | O73: 1495907.9 | P73: 1495907.9 | Q73: offset | R73: Accrual for PO 5500008094, Federal Intel Aerospace | S73: Journal Import Created | U73: BDM-030322-16 03-MAR-2022 22:49:03 EBS OPR A 16138337 7246308 N | V73: EBS OPR | W73: - | X73: - | Y73: 44620 | Z73: 44624
A74: - | B74: - | D74: Mar-22 | E74: Public Sector | F74: SLED | G74: SLED West | H74: SLED HI/Comm | I74: 101.13001.245011.9999.999.999.9999.9999 | J74: 101 | K74: 13001 | L74: 245011 | M74: 9999 | N74: Accrued Liabilities - Public Sector | O74: -291214.65 | P74: -291214.65 | Q74: offset | R74: Reverses journal BDM-010922-5 Adjustment of journal batch BDM-010922-5 Spreadsheet A 300000031763616 6625251 N from period Dec-21. | S74: Journal Import Created | U74: Reverses BDM-010922-5 Adjustment 08-03-22 17:28:36 7296418 | V74: Spreadsheet | W74: - | X74: - | Y74: 44628 | Z74: 44628
A75: - | B75: - | D75: Mar-22 | E75: Public Sector | F75: Federal | G75: Federal Civilian | H75: Federal Healthcare | I75: 101.11010.245011.9999.999.999.9999.9999 | J75: 101 | K75: 11010 | L75: 245011 | M75: 9999 | N75: Accrued Liabilities - Public Sector | O75: -91935 | P75: -91935 | Q75: offset | R75: Reverses journal BDM-110221-23 Adjustment of journal batch BDM-110221-23 Spreadsheet A 300000031712966 5869187 N from period Oct-21. | S75: Journal Import Created | U75: Reverses BDM-110221-23 Adjustment 08-03-22 17:53:52 7296571 | V75: Spreadsheet | W75: - | X75: - | Y75: 44628 | Z75: 44628
A76: - | B76: - | D76: Mar-22 | E76: Public Sector | F76: SLED | G76: SLED West | H76: SLED HI/Comm | I76: 101.13001.245011.9999.999.999.9999.9999 | J76: 101 | K76: 13001 | L76: 245011 | M76: 9999 | N76: Accrued Liabilities - Public Sector | O76: -199719.5 | P76: -199719.5 | Q76: offset | R76: Reverses journal BDM-010922-7 Adjustment of journal batch BDM-010922-7 Spreadsheet A 300000031763616 6625251 N from period Dec-21. | S76: Journal Import Created | U76: Reverses BDM-010922-7 Adjustment 08-03-22 17:50:52 7296547 | V76: Spreadsheet | W76: - | X76: - | Y76: 44628 | Z76: 44628
... A78: - | B78: - | D78: Mar-22 | E78: Public Sector | F78: SLED | G78: SLED West | H78: SLED HI/Comm | I78: 101.13001.245011.9999.999.999.9999.9999 | J78: 101 | K78: 13001 | L78: 245011 | M78: 9999 | N78: Accrued Liabilities - Public Sector | O78: -160280.5 | P78: -160280.5 | Q78: offset | R78: Reverses journal BDM-010922-8 Adjustment of journal batch BDM-010922-8 Spreadsheet A 300000031763616 6625251 N from period Dec-21. | S78: Journal Import Created | U78: Reverses BDM-010922-8 Adjustment 08-03-22 17:51:37 7296553 | V78: Spreadsheet | W78: - | X78: - | Y78: 44628 | Z78: 44628
A79: AT&T | B79: INV-0000566636 | C79: 44546 | D79: Feb-22 | E79: Public Sector | F79: Federal | G79: Federal Department of Defense | H79: Federal Intel Moonshot | I79: 101.12022.245011.9999.999.999.9999.9999 | J79: 101 | K79: 12022 | L79: 245011 | M79: 9999 | N79: Accrued Liabilities - Public Sector | O79: 53226.47 | P79: 53226.47 | Q79: offset | R79: Take to PL - Reverse today | S79: - | T79: 1 | U79: Payables A 6910809000001 6910841 N | V79: Payables | W79: - | X79: - | Y79: 44595 | Z79: 44595
A80: - | B80: - | D80: Dec-21 | E80: Public Sector | F80: SLED | G80: SLED East | H80: SLED Southeast | I80: 101.13008.245011.9999.999.999.9999.9999 | J80: 101 | K80: 13008 | L80: 245011 | M80: 9999 | N80: Accrued Liabilities - Public Sector | O80: 3247140 | P80: 3247140 | Q80: offset | R80: Streamline for Palm Beach - SO 9981826 | S80: Journal Import Created | U80: BDM-011022-5 10-JAN-2022 07:46:24 EBS OPR A 15135418 6631466 N | V80: EBS OPR | W80: - | X80: - | Y80: 44561 | Z80: 44571
A81: - | B81: - | D81: Jan-22 | E81: Public Sector | F81: SLED | G81: SLED East | H81: SLED Southeast | I81: 101.13008.245011.9999.950.999.9999.9999 | J81: 101 | K81: 13008 | L81: 245011 | M81: 9999 | N81: Accrued Liabilities - Public Sector | O81: 625174 | P81: 625174 | Q81: offset | R81: Streamline for Palm Beach - SO 9981826 | S81: - | U81: BDM-020322-40 03-FEB-2022 19:50:14 | V81: Manual | W81: - | X81: - | Y81: 44592 | Z81: 44596
A82: - | B82: - | D82: Feb-22 | E82: Public Sector | F82: SLED | G82: SLED East | H82: SLED Southeast | I82: 101.13008.245011.9999.999.999.9999.9999 | J82: 101 | K82: 13008 | L82: 245011 | M82: 9999 | N82: Accrued Liabilities - Public Sector | O82: -561197.89 | P82: -561197.89 | Q82: offset | R82: Streamline for Palm Beach - SO 9981826 | S82: Journal Import Created | U82: BDM-030422-9 04-MAR-2022 09:24:17 EBS OPR A 16139068 7247309 N | V82: EBS OPR | W82: - | X82: - | Y82: 44620 | Z82: 44624
A83: - | B83: - | D83: Mar-22 | E83: Public Sector | F83: Federal | G83: Federal Department of Defense | H83: Federal Intel Moonshot | I83: 101.12022.245011.9999.999.999.9999.9999 | J83: 101 | K83: 12022 | L83: 245011 | M83: 9999 | N83: Accrued Liabilities - Public Sector | O83: -53226.47 | P83: -53226.47 | Q83: offset | R83: Reclassing AP invoice INV-0000566636 to PL | S83: Journal Import Created | U83: BDM-033122-1 31-MAR-2022 09:21:12 EBS OPR A 16677935 7549652 N | V83: EBS OPR | W83: - | X83: - | Y83: 44651 | Z83: 44651
A84: - | B84: - | D84: Mar-22 | E84: Public Sector | F84: SLED | G84: SLED East | H84: SLED Southeast | I84: 101.13008.245011.9999.999.999.9999.9999 | J84: 101 | K84: 13008 | L84: 245011 | M84: 9999 | N84: Accrued Liabilities - Public Sector | O84: -3311116.1 | P84: -3311116.1 | Q84: offset | R84: Streamline for Palm Beach - SO 9981826 | S84: Journal Import Created | U84: BDM-032922-8 29-MAR-2022 14:25:05 EBS OPR A 16647983 7523693 N | V84: EBS OPR | W84: - | X84: - | Y84: 44649 | Z84: 44649
A85: - | B85: - | D85: Nov-21 | E85: Public Sector | F85: Federal | G85: Federal Civilian | H85: Federal Citizen Services | I85: 101.12014.245011.9999.999.999.9999.9999 | J85: 101 | K85: 12014 | L85: 245011 | M85: 9999 | N85: Accrued Liabilities - Public Sector | O85: 543000 | P85: 543000 | Q85: offset | R85: Streamline for PO 1CDATA-21-C-0075 (OPR transactions to justify streamline) - can we release 150K | S85: Journal Import Created | U85: BDM-120621-4 06-DEC-2021 08:42:36 EBS OPR A 14478610 6223697 N | V85: EBS OPR | W85: - | X85: - | Y85: 44530 | Z85: 44536
A86: - | B86: - | D86: Mar-22 | E86: Public Sector | F86: Federal | G86: Federal Civilian | H86: Federal Citizen Services | I86: 101.12014.245011.9999.999.999.9999.9999 | J86: 101 | K86: 12014 | L86: 245011 | M86: 9999 | N86: Accrued Liabilities - Public Sector | O86: -543000 | P86: -543000 | Q86: offset | R86: Reclassing streamline balance to correct PL - 1CDATA-21-C-0075 | S86: - | U86: BDM-031522-1 15-MAR-2022 09:28:40 | V86: Manual | W86: - | X86: - | Y86: 44635 | Z86: 44635
A87: - | B87: - | D87: Jun-21 | E87: Public Sector | F87: Federal | G87: Federal Department of Defense | H87: Federal COCOMs | I87: 101.12015.245011.9999.999.999.9999.9999 | J87: 101 | K87: 12015 | L87: 245011 | M87: 9999 | N87: Accrued Liabilities - Public Sector | O87: -273645 | P87: -273645 | Q87: offset | R87: Streamline for W91RUS21F0058 - remaining negative GP is slotted for JUL-22 per BL | S87: Journal Import Created | U87: BDM-070721-2 07-JUL-2021 06:30:17 EBS OPR A 10987626 4648191 N | V87: EBS OPR | W87: - | X87: - | Y87: 44377 | Z87: 44384
A88: - | B88: - | D88: Aug-21 | E88: Public Sector | F88: Federal | G88: Federal Department of Defense | H88: Federal COCOMs | I88: 101.12015.245011.9999.999.999.9999.9999 | J88: 101 | K88: 12015 | L88: 245011 | M88: 9999 | N88: Accrued Liabilities - Public Sector | O88: 29371.23 | P88: 29371.23 | Q88: offset | R88: Releasing cost for W91RUS21F0058 Streamline | S88: Journal Import Created | U88: BDM-090721-6 07-SEP-2021 05:48:51 EBS OPR A 12206354 5291105 N | V88: EBS OPR | W88: - | X88: - | Y88: 44439 | Z88: 44446
A89: - | B89: - | D89: Oct-21 | E89: Public Sector | F89: Federal | G89: Federal Department of Defense | H89: Federal COCOMs | I89: 101.12015.245011.9999.999.999.9999.9999 | J89: 101 | K89: 12015 | L89: 245011 | M89: 9999 | N89: Accrued Liabilities - Public Sector | O89: 84465.09 | P89: 84465.09 | Q89: offset | R89: Releasing cost for W91RUS21F0058 Streamline | S89: Journal Import Created | U89: BDM-110221-2 02-NOV-2021 13:53:48 EBS OPR A 13556249 5868115 N | V89: EBS OPR | W89: - | X89: - | Y89: 44500 | Z89: 44503
A90: - | B90: - | D90: Nov-21 | E90: Public Sector | F90: Federal | G90: Federal Department of Defense | H90: Federal COCOMs | I90: 101.12015.245011.9999.999.999.9999.9999 | J90: 101 | K90: 12015 | L90: 245011 | M90: 9999 | N90: Accrued Liabilities - Public Sector | O90: 16783.56 | P90: 16783.56 | Q90: offset | R90: Releasing cost for W91RUS21F0058 Streamline | S90: Journal Import Created | U90: BDM-120621-1 06-DEC-2021 07:04:40 EBS OPR A 14439868 6222903 N | V90: EBS OPR | W90: - | X90: - | Y90: 44530 | Z90: 44536
A91: - | B91: - | D91: Dec-21 | E91: Public Sector | F91: Federal | G91: Federal Department of Defense | H91: Federal COCOMs | I91: 101.12015.245011.9999.999.999.9999.9999 | J91: 101 | K91: 12015 | L91: 245011 | M91: 9999 | N91: Accrued Liabilities - Public Sector | O91: 42141.33 | P91: 42141.33 | Q91: offset | R91: Release Portion of Streamline | S91: Journal Import Created | U91: CMG-010922-4 Release Portion of Streamline 09-JAN-2022 16:04:47 EBS OPR A 15113834 6625041 N | V91: EBS OPR | W91: - | X91: - | Y91: 44561 | Z91: 44571
... A141: - | B141: - | D141: May-22 | E141: Public Sector | F141: Federal | G141: Federal House | H141: Federal House | I141: 101.11016.245011.9999.999.999.9999.9999 | J141: 101 | K141: 11016 | L141: 245011 | M141: 9999 | N141: Accrued Liabilities - Public Sector | O141: -311549.33 | P141: -311549.33 | Q141: Timing - Finder's Fee | R141: Reversed in July BDM-060522-36 7/19/22 Finder's Fee accrual - SO 9874442 | S141: Journal Import Created | U141: BDM-060522-36 05-JUN-2022 21:38:39 EBS OPR A 18091846 8322753 N | V141: EBS OPR | W141: - | X141: - | Y141: 44712 | Z141: 44718
A142: - | B142: - | D142: Jul-22 | E142: Public Sector | F142: Federal | G142: Federal House | H142: Federal House | I142: 101.11016.245011.9999.999.999.9999.9999 | J142: 101 | K142: 11016 | L142: 245011 | M142: 9999 | N142: Accrued Liabilities - Public Sector | O142: 311549.33 | P142: 311549.33 | Q142: 311549.33 | R142: Reverses BDM-060522-36 journal entry of BDM-060522-36 05-JUN-2022 21:38:39 batch from MAY-22. | S142: - | U142: Reverses "BDM-060522-36"19-JUL-22 16:20:13 - 360435677 EBS OPR A 19298577 8837785 N | V142: EBS OPR | W142: - | X142: - | Y142: 44761 | Z142: 44762
A143: - | B143: - | D143: Dec-21 | E143: Public Sector | F143: SLED | G143: SLED West | H143: SLED Pacific Southwest | I143: 101.13004.245011.9999.999.999.9999.9999 | J143: 101 | K143: 13004 | L143: 245011 | M143: 9999 | N143: Accrued Liabilities - Public Sector | O143: 583367 | P143: 583367 | Q143: Timing - Streamline Denver International Airport PO-00107191 | R143: Streamline for PO-00107191, 9986669 - SLED PSW - Kroack | S143: Journal Import Created | U143: BDM-011022-6 10-JAN-2022 07:50:39 EBS OPR A 15135418 6631466 N | V143: EBS OPR | W143: - | X143: - | Y143: 44561 | Z143: 44571
A144: - | B144: - | D144: Jul-22 | E144: Public Sector | F144: SLED | G144: SLED West | H144: SLED Pacific Southwest | I144: 101.13004.245011.9999.999.999.9999.9999 | J144: 101 | K144: 13004 | L144: 245011 | M144: 9999 | N144: Accrued Liabilities - Public Sector | O144: -583367 | P144: -583367 | Q144: -583367 | R144: Reverses BDM-011022-6 journal entry of BDM-011022-6 10-JAN-2022 07:50:39 batch from DEC-21. | S144: - | U144: Reverses ""BDM-011022-6""03-AUG-22 20:27:26 - 361671329 EBS OPR A 19621690 9007810 N | V144: EBS OPR | W144: - | X144: - | Y144: 44773 | Z144: 44777
A145: - | B145: - | D145: Jul-22 | E145: Public Sector | F145: SLED | G145: SLED East | H145: SLED Central | I145: 101.13006.245011.9999.950.999.9999.9999 | J145: 101 | K145: 13006 | L145: 245011 | M145: 9999 | N145: Accrued Liabilities - Public Sector | O145: 132501.52 | P145: 132501.52 | Q145: 132501.52 | R145: Reverses CDW-080322-5 Reclass to SLED - House SC SO 10325392 journal entry of CDW-080322-5 Reclass to SLED - House SC SO 10325392 03-AUG-2022 12:56:03 batch from JUL-22. | S145: - | U145: Reverses ""CDW-080322-5 Reclass to SLED - House SC SO 1032539""04-AUG-22 09:45:22 - 36171579 9014275 N | V145: EBS OPR | W145: - | X145: - | Y145: 44773 | Z145: 44777
A146: - | B146: - | D146: Jul-22 | E146: Public Sector | F146: SLED | G146: SLED East | H146: SLED Central | I146: 101.13006.245011.9999.950.999.9999.9999 | J146: 101 | K146: 13006 | L146: 245011 | M146: 9999 | N146: Accrued Liabilities - Public Sector | O146: -132501.52 | P146: -132501.52 | Q146: -132501.52 | R146: Reclass to SLED - House SC SO 10325392 | S146: - | U146: CDW-080322-5 Reclass to SLED - House SC SO 10325392 03-AUG-2022 12:56:03 EBS OPR A 1960491 9002583 N | V146: EBS OPR | W146: - | X146: - | Y146: 44773 | Z146: 44776
A147: - | B147: - | D147: Dec-21 | E147: Public Sector | F147: Federal | G147: Federal Department of Defense | H147: Federal Air Force | I147: 101.11001.245011.9999.999.999.9999.9999 | J147: 101 | K147: 11001 | L147: 245011 | M147: 9999 | N147: Accrued Liabilities - Public Sector | O147: 162945 | P147: 162945 | Q147: Timing - AP write off | R147: Defer AP W/O RMA Approved - will reverse to 502550 - may start taking some of this hit in June | S147: Journal Import Created | U147: CMG-010622-18 Defer AP W/O RMA Approved Spreadsheet A 300000031763616 6589071 N | V147: Spreadsheet | W147: - | X147: - | Y147: 44561 | Z147: 44568
A148: - | B148: - | D148: Jan-22 | E148: Public Sector | F148: Federal | G148: Federal Department of Defense | H148: Federal Air Force | I148: 101.11001.245011.9999.999.999.9999.9999 | J148: 101 | K148: 11001 | L148: 245011 | M148: 9999 | N148: Accrued Liabilities - Public Sector | O148: -151702.38 | P148: -151702.38 | Q148: Timing - AP write off | R148: Releasing portion of "CMG-010622-18" | S148: - | U148: BDM-020222-1 02-FEB-2022 09:55:51 | V148: Manual | W148: - | X148: - | Y148: 44592 | Z148: 44594
A149: - | B149: - | D149: Feb-22 | E149: Public Sector | F149: Federal | G149: Federal Department of Defense | H149: Federal Air Force | I149: 101.11001.245011.9999.999.999.9999.9999 | J149: 101 | K149: 11001 | L149: 245011 | M149: 9999 | N149: Accrued Liabilities - Public Sector | O149: -4929.19 | P149: -4929.19 | Q149: Timing - AP write off | R149: Releasing portion of "CMG-010622-18" | S149: - | U149: BDM-030222-12 02-MAR-2022 14:24:21 | V149: Manual | W149: - | X149: - | Y149: 44620 | Z149: 44622
A150: - | B150: - | D150: Dec-21 | E150: Public Sector | F150: Federal | G150: Federal Department of Defense | H150: Federal Air Force | I150: 101.11001.245011.9999.999.999.9999.9999 | J150: 101 | K150: 11001 | L150: 245011 | M150: 9999 | N150: Accrued Liabilities - Public Sector | O150: 352573.2 | P150: 352573.2 | Q150: Timing - AP write off | R150: Defer AP W/O RMA Approved - will reverse to 502550 - may start taking some of this hit in June | S150: Journal Import Created | U150: CMG-010622-19 Defer AP W/O RMA Approved Spreadsheet A 300000031763616 6589071 N | V150: Spreadsheet | W150: - | X150: - | Y150: 44561 | Z150: 44568
A151: - | B151: - | D151: Jun-22 | E151: Public Sector | F151: Federal | G151: Federal Department of Defense | H151: Federal Air Force | I151: 101.11001.245011.9999.999.999.9999.9999 | J151: 101 | K151: 11001 | L151: 245011 | M151: 9999 | N151: Accrued Liabilities - Public Sector | O151: -40569.17 | P151: -40569.17 | Q151: Timing - AP write off | R151: Timing - AP write off for Federal Air Force | S151: - | U151: CDW-070622-7 Timing - AP write off for Federal Air Force | V151: Manual | W151: - | X151: - | Y151: 44742 | Z151: 44748
